Workbook
Name Slicer_Year: #N/A

Sheet Dashboard

Sheet Valuation-FCFF
D2: NSE: ASIANPAINT | BSE:500820
D3: 52-WEEK (HIGH: ₹ 2985.70| LOW: ₹ 2115.00 )
D4: 2649.4
D5: (as at 13 July 2026)
B6: VALUATION USING FCFF TECHNIQUE
B7: (in ₹ Cr. unless stated otherwise)
G8: Forecasts
B9: Years | G9: 27 | H9: =G9+1 -> 28 | I9: =H9+1 -> 29 | J9: =I9+1 -> 30
B11: Reported Earnings Before Interest and Tax (EBIT) | G11: =SOPL!P24 -> 6556.1789 | H11: =SOPL!Q24 -> 7139.5081 | I11: =SOPL!R24 -> 7764.2112 | J11: =SOPL!S24 -> 8433.6894 | L11: Capital Structure (A) | M11: Weightage of Capital Structure | N11: Cost of Capital (B) | O11: A*B
B12: Less: Other Non-Operating Income | G12: =-SOPL!P19 -> -836.24905 | H12: =-SOPL!Q19 -> -966.16811 | I12: =-SOPL!R19 -> -1116.2713 | J12: =-SOPL!S19 -> -1289.6944
B13: Adjusted Earnings Before Interest And Tax | G13: =SUM(G11:G12) -> 5719.9298 | H13: =SUM(H11:H12) -> 6173.34 | I13: =SUM(I11:I12) -> 6647.9399 | J13: =SUM(J11:J12) -> 7143.995 | L13: Debt | M13: 0.12 | N13: =J30 -> 0.047119396 | O13: =M13*N13 -> 0.0056543275
B14: Less: Tax | G14: =G13*-0.268 -> -1532.9412 | H14: =H13*-0.268 -> -1654.4551 | I14: =I13*-0.268 -> -1781.6479 | J14: =J13*-0.268 -> -1914.5907 | L14: Ordinary Shares | M14: 0.88 | N14: =J23+J28*J24 -> 0.12904966 | O14: =M14*N14 -> 0.1135637
B15: Add: Depreciation and Amortisation | G15: =Schedule!AG47 -> 1338.0711 | H15: =Schedule!AH47 -> 1402.9337 | I15: =Schedule!AI47 -> 1477.7125 | J15: =Schedule!AJ47 -> 1562.8011 | M15: =SUM(M13:M14) -> 1 | O15: =SUM(O13:O14) -> 0.11921803
B16: Add: Impairment expense on Goodwill & Intangible Asset | G16: 25.72 | H16: 25.72 | I16: 25.72 | J16: 25.72 | M16: WACC | N16: =O15/M15 -> 0.11921803
B17: Less: Net CapEx (PPE, Goodwill and Intangible Asset) | G17: =-(Schedule!Z11+Schedule!Z26) -> -1109.7583 | H17: =SOCF!R28 -> -1211.2055 | I17: =SOCF!S28 -> -1321.9717 | J17: =SOCF!T28 -> -1442.9098
B18: Less: Increase in Working Capital | G18: =('SOFP '!O33-'SOFP '!O61)-('SOFP '!P33-'SOFP '!P61) -> -1416.7583 | H18: =('SOFP '!P33-'SOFP '!P61)-('SOFP '!Q33-'SOFP '!Q61) -> -1635.0982 | I18: =('SOFP '!Q33-'SOFP '!Q61)-('SOFP '!R33-'SOFP '!R61) -> -1753.1762 | J18: =('SOFP '!R33-'SOFP '!R61)-('SOFP '!S33-'SOFP '!S61) -> -1889.4196 | L18: (in ₹ Cr. unless stated otherwise)
L19: PV of FCFF (FY2027E-30E) | O19: =NPV(N16,G20:J20) -> 9749.1524
B20: FREE CASH FLOW TO FIRM (FCFF) | G20: =SUM(G13:G18) -> 3024.2631 | H20: =SUM(H13:H18) -> 3101.2349 | I20: =SUM(I13:I18) -> 3294.5765 | J20: =SUM(J13:J18) -> 3485.596 | L20: Terminal Value | O20: =J20*(1+J22)/(N16-J22)/(1+N16)^4 -> 32915.787
L21: Value of Firm | O21: =SUM(O19:O20) -> 42664.939
B22: Company | D22: 5-Year Levered Beta | E22: Debt / Equity | G22: Terminal Growth | J22: =(J20/G20)^(1/3)-1 -> 0.048461503 | L22: Value of Debt | O22: ='SOFP '!O46+'SOFP '!O47 -> 2554.11
G23: Risk-free Rate | J23: 0.067 | L23: Value of Equity | O23: =O21-O22 -> 40110.829
B24: Berger Paints India | D24: 0.67 | E24: 0.07 | G24: Equity Risk Premium | J24: 0.0731
B25: Kansai Nerolac Paints | D25: 0.82 | E25: 0.05 | G25: Median Industry Levered Beta | J25: =D28 -> 0.745
B26: Akzo Nobel India | D26: 0.39 | E26: 0.01 | G26: Industry Unlevered Beta | J26: =J25*(1-E28)/((1-E28)+E28*(1-0.268)) -> 0.72295002 | L26: Unit Share Price
B27: Indigo Paints | D27: 1.23 | E27: 0.03 | G27: Tax Rate | J27: 0.268
C28: Median | D28: =MEDIAN(D24:D27) -> 0.745 | E28: =MEDIAN(E24:E27) -> 0.04 | G28: Levered Beta for Asian Paints | J28: =J26/(0.88)/((0.88+0.12*(1-0.268))) -> 0.84883257 | L28: =O23/SOPL!O54*10000000 -> 418.42412
C29: Mean | D29: =AVERAGE(D24:D27) -> 0.7775 | E29: =AVERAGE(E24:E27) -> 0.04 | G29: Kd | J29: =(Schedule!L64-Schedule!L63-Schedule!L59)/('SOFP '!O46+'SOFP '!O47) -> 0.064370759
G30: Kd*(1-T) | J30: =J29*(1-0.268) -> 0.047119396
G31: CAPM (Ke) | J31: =J23+J28*J24 -> 0.12904966
B33: Note: The valuation has been performed using the FCFF approach under the assumption that Asian Paints Limited will continue as a going concern. Forecast financial statements were prepared using historical trends, company-specific assumptions and management-consistent operating behaviour. Market-based inputs used in estimating the discount rate were obtained from the latest publicly available sources at the valuation date, while the terminal growth rate was conservatively estimated using the forecast-period FCFF CAGR to reflect the company's long-term sustainable growth prospects.
B38: Conclusion: Based on the FCFF methodology and assumptions adopted, the calculated intrinsic value indicates that the share price appears significantly higher than the estimated fundamental value. However, the market premium may reflect investor expectations regarding Asian Paints' future growth prospects, competitive positioning, brand strength and ability to generate superior returns over the long term.

Sheet Sensitivity Analysis
D2: NSE: ASIANPAINT | BSE:500820
D3: 52-WEEK (HIGH: ₹ 2985.70| LOW: ₹ 2115.00 )
D4: 2649.4
D5: (as at 13 July 2026)
B6: SENSITIVITY ANALYSIS
B7: (in ₹ Cr. unless stated otherwise)
G8: Forecasts
B9: Years | G9: 27 | H9: =G9+1 -> 28 | I9: =H9+1 -> 29 | J9: =I9+1 -> 30
B10: Operating Revenue | G10: =SOPL!O13*(1+'Sensitivity Analysis'!$D$24) -> 40921.071 | H10: =G10*(1+$D$24) -> 47059.232 | I10: =H10*(1+$D$24) -> 54118.116 | J10: =I10*(1+$D$24) -> 62235.834
B11: Earnings Before Interest and Tax (EBIT) | G11: =G10*$D$25 -> 10230.268 | H11: =H10*$D$25 -> 11764.808 | I11: =I10*$D$25 -> 13529.529 | J11: =J10*$D$25 -> 15558.958
B12: Less: Other Non-Operating Income | G12: ='Valuation-FCFF'!G12 -> -836.24905 | H12: ='Valuation-FCFF'!H12 -> -966.16811 | I12: ='Valuation-FCFF'!I12 -> -1116.2713 | J12: ='Valuation-FCFF'!J12 -> -1289.6944
B13: Less: Tax | G13: =-SUM(G11:G12)*$D$28 -> -1409.1028 | H13: =-SUM(H11:H12)*$D$28 -> -1619.796 | I13: =-SUM(I11:I12)*$D$28 -> -1861.9887 | J13: =-SUM(J11:J12)*$D$28 -> -2140.3896
B14: Add: Depreciation and Amortisation | G14: ='Valuation-FCFF'!G15 -> 1338.0711 | H14: ='Valuation-FCFF'!H15 -> 1402.9337 | I14: ='Valuation-FCFF'!I15 -> 1477.7125 | J14: ='Valuation-FCFF'!J15 -> 1562.8011
B15: Add: Impairment expense on Goodwill & Intangible Asset | G15: ='Valuation-FCFF'!G16 -> 25.72 | H15: ='Valuation-FCFF'!H16 -> 25.72 | I15: ='Valuation-FCFF'!I16 -> 25.72 | J15: ='Valuation-FCFF'!J16 -> 25.72
B16: Less: Net CapEx (PPE, Goodwill and Intangible Asset) | G16: ='Valuation-FCFF'!G17 -> -1109.7583 | H16: ='Valuation-FCFF'!H17 -> -1211.2055 | I16: ='Valuation-FCFF'!I17 -> -1321.9717 | J16: ='Valuation-FCFF'!J17 -> -1442.9098
B17: Less: Increase in Working Capital | G17: ='Valuation-FCFF'!G18 -> -1416.7583 | H17: ='Valuation-FCFF'!H18 -> -1635.0982 | I17: ='Valuation-FCFF'!I18 -> -1753.1762 | J17: ='Valuation-FCFF'!J18 -> -1889.4196
B19: FREE CASH FLOW TO FIRM (FCFF) | G19: =SUM(G11:G17) -> 6822.1904 | H19: =SUM(H11:H17) -> 7761.1938 | I19: =SUM(I11:I17) -> 8979.5536 | J19: =SUM(J11:J17) -> 10385.066
B22: Sensitivity Table
G23: (in ₹ Cr. unless stated otherwise)
B24: Revenue Growth | D24: 0.15 | G24: ='Valuation-FCFF'!L19 -> PV of FCFF (FY2027E-30E) | J24: =NPV(D27,G19:J19) -> 26455.812 | L24: Unit Share Price
B25: EBIT Margin | D25: 0.25 | G25: ='Valuation-FCFF'!L20 -> Terminal Value | J25: =J19*(1+D26)/(D27-D26)/(1+D27)^4 -> 252988.66
B26: Terminal Growth | D26: 0.07 | G26: ='Valuation-FCFF'!L21 -> Value of Firm | J26: =SUM(J24:J25) -> 279444.47 | L26: =J28/SOPL!O54*10000000 -> 2888.437
B27: ='Valuation-FCFF'!M16 -> WACC | D27: 0.1 | G27: ='Valuation-FCFF'!L22 -> Value of Debt | J27: ='Valuation-FCFF'!O22 -> 2554.11
B28: Tax Rate | D28: 0.15 | G28: ='Valuation-FCFF'!L23 -> Value of Equity | J28: =J26-J27 -> 276890.36
D30: Bear Case | K30: EBIT Margin
D31: Base Case | K31: 0.12 | L31: Upside/(Downside) | N31: =L26/D4-1 -> 0.090223078
D32: Bull Case | K32: 0.15
K33: 0.174
B34: The sensitivity analysis demonstrates the impact of changes in the Revenue Growth, EBIT Margin, Tax Rate, Weighted Average Cost of Capital (WACC) and Terminal Growth Rate on the estimated intrinsic value per share. The valuation remains highly sensitive to these assumptions because a significant proportion of enterprise value is derived from the terminal value calculation. A lower WACC or higher terminal growth rate results in a higher intrinsic value, whereas a higher discount rate or lower growth assumption reduces the estimated value.
B37: Terminal Growth | C37: WACC | D37: Revenue Growth | E37: Tax Rate | F37: ebit
B38: 0.02 | C38: 0.1 | D38: 0.06 | E38: 0.15 | F38: 0.12
B39: 0.03 | C39: 0.11 | D39: 0.07 | E39: 0.2 | F39: 0.15
B40: 0.0485 | C40: 0.1192 | D40: 0.0917 | E40: 0.268 | F40: 0.174
B41: 0.07 | C41: 0.13 | D41: 0.12 | E41: 0.3 | F41: 0.2
B42: 0.09 | C42: 0.15 | D42: 0.15 | E42: 0.35 | F42: 0.25

Sheet SOFP 
G2: NSE: ASIANPAINT | BSE:500820
G3: 52-WEEK (HIGH: ₹ 2985.70| LOW: ₹ 2115.00 )
G4: 2649.4
G5: (as at 13 July 2026)
B6: CONSOLIDATED STATEMENT OF FINANCIAL POSITION
B7: (in ₹ Cr. unless stated otherwise)
I8: Historical | P8: Forecasts
B9: Years | I9: =J9-1 -> 20 | J9: 21 | K9: =J9+1 -> 22 | L9: =K9+1 -> 23 | M9: =L9+1 -> 24 | N9: =M9+1 -> 25 | O9: =N9+1 -> 26 | P9: =O9+1 -> 27 | Q9: =P9+1 -> 28 | R9: =Q9+1 -> 29 | S9: =R9+1 -> 30 | T9: Trend
B11: ASSETS
B12: Non-Current Assets
B13: Property, Plant & Equipment | I13: 4764.76 | J13: 4476.35 | K13: 4184.46 | L13: 4145.65 | M13: 4446.2 | N13: 6787.62 | O13: 7146.23 | P13: =Schedule!AA18 -> 7322.745 | Q13: =Schedule!AD18 -> 7562.6993 | R13: =Schedule!AG18 -> 7867.2348 | S13: =Schedule!AJ18 -> 8238.0609
B14: Right-of-Use Assets | I14: 920.09 | J14: 845.55 | K14: 905.75 | L14: 1208.92 | M14: 1856.27 | N14: 1843.72 | O14: 2018.77 | P14: =Schedule!M47 -> 2162.4989 | Q14: =Schedule!N47 -> 2316.4607 | R14: =Schedule!O47 -> 2481.3841 | S14: =Schedule!P47 -> 2658.0493
B15: Capital work-in-progress | I15: 140.24 | J15: 182.98 | K15: 426.43 | L15: 1019.59 | M15: 2698.37 | N15: 1254.49 | O15: 1848.67 | P15: =P13*Q68 -> 1847.6522 | Q15: =Q13*R68 -> 1908.1968 | R15: =R13*S68 -> 1985.0362 | S15: =S13*T68 -> 2078.6019
B16: Goodwill and Intangible Assets | I16: =319.99+267.47 -> 587.46 | J16: =302.63+233.99 -> 536.62 | K16: =242.86+185.99 -> 428.85 | L16: =228.48+187.41 -> 415.89 | M16: =419.19+424.96 -> 844.15 | N16: =219.58+369.18 -> 588.76 | O16: =219.08+256.2 -> 475.28 | P16: =Schedule!AA37 -> 690.85502 | Q16: =Schedule!AD37 -> 765.04743 | R16: =Schedule!AG37 -> 848.49359 | S16: =Schedule!AJ37 -> 942.04096
B17: Investment in Associates | I17: 456.63 | J17: 483.9 | K17: 515.47 | L17: 781.73 | M17: 583.13 | N17: 608 | O17: 656.09 | P17: =O17*(1+Q69) -> 696.02769 | Q17: =P17*(1+R69) -> 738.39648 | R17: =Q17*(1+S69) -> 783.34435 | S17: =R17*(1+T69) -> 831.0283
B18: Financial Assets | I18: =1049.74+4.21+68.24+248.31 -> 1370.5 | J18: =985.78+2.89+594.06 -> 1582.73 | K18: =551.36+2.4+486.05 -> 1039.81 | L18: =782.98+2.17+363.18 -> 1148.33 | M18: =801.38+1.78+606.51 -> 1409.67 | N18: =871.79+8.71+0+877.84 -> 1758.34 | O18: =119.82+5.36+1.57+1537.79 -> 1664.54 | P18: =O18*(1+Q70) -> 1838.2601 | Q18: =P18*(1+R70) -> 2030.1105 | R18: =Q18*(1+S70) -> 2241.9834 | S18: =R18*(1+T70) -> 2475.9685
B19: Deferred Tax Assets (Net) | I19: 16.8 | J19: 14.28 | K19: 26.02 | L19: 18.67 | M19: 23.32 | N19: 16.12 | O19: 15.74 | P19: =O19*(1+Q71) -> 15.944781 | Q19: =P19*(1+R71) -> 16.152225 | R19: =Q19*(1+S71) -> 16.362369 | S19: =R19*(1+T71) -> 16.575247
B20: Income Tax Assets (Net) | I20: 253.09 | J20: 152.23 | K20: 172.46 | L20: 189.52 | M20: 198.11 | N20: 221.62 | O20: 248.62 | P20: =O20*(1+Q72) -> 273.21386 | Q20: =P20*(1+R72) -> 300.24058 | R20: =Q20*(1+S72) -> 329.94083 | S20: =R20*(1+T72) -> 362.57907
B21: Other Non-Current Assets | I21: 65.09 | J21: 68.38 | K21: 132.87 | L21: 334.54 | M21: 327.81 | N21: 301.02 | O21: 275.91 | P21: =O21*(1+Q73) -> 292.19925 | Q21: =P21*(1+R73) -> 309.45018 | R21: =Q21*(1+S73) -> 327.71958 | S21: =R21*(1+T73) -> 347.06757
B22: Total Non-Current Assets | I22: =SUM(I13:I21) -> 8574.66 | J22: =SUM(J13:J21) -> 8343.02 | K22: =SUM(K13:K21) -> 7832.12 | L22: =SUM(L13:L21) -> 9262.84 | M22: =SUM(M13:M21) -> 12387.03 | N22: =SUM(N13:N21) -> 13379.69 | O22: =SUM(O13:O21) -> 14349.85 | P22: =SUM(P13:P21) -> 15139.397 | ... S22: =SUM(S13:S21) -> 17949.972
B24: Current Assets
B25: Inventories | I25: 3389.81 | J25: 3798.6 | K25: 6152.98 | L25: 6210.64 | M25: 5923.41 | N25: 6719.27 | O25: 5743.69 | P25: =SOPL!P17*'Ratio Analysis'!$Q$48/'Ratio Analysis'!$G$52 -> 6729.5664 | Q25: =SOPL!Q17*'Ratio Analysis'!$Q$48/'Ratio Analysis'!$G$52 -> 7344.7418 | R25: =SOPL!R17*'Ratio Analysis'!$Q$48/'Ratio Analysis'!$G$52 -> 8016.4273 | S25: =SOPL!S17*'Ratio Analysis'!$Q$48/'Ratio Analysis'!$G$52 -> 8749.7952
B26: Financial Assets
B27: Trade Receivables | I27: 1795.22 | J27: 2602.17 | K27: 3871.44 | L27: 4636.94 | M27: 4889.05 | N27: 4313.65 | O27: 4461.8 | P27: =SOPL!P13*'Ratio Analysis'!$Q$49/'Ratio Analysis'!$G$52 -> 4940.7675 | Q27: =SOPL!Q13*'Ratio Analysis'!$Q$49/'Ratio Analysis'!$G$52 -> 5392.4219 | R27: =SOPL!R13*'Ratio Analysis'!$Q$49/'Ratio Analysis'!$G$52 -> 5885.5654 | S27: =SOPL!S13*'Ratio Analysis'!$Q$49/'Ratio Analysis'!$G$52 -> 6423.9953
B28: Cash & Cash Equivalents | I28: 563.83 | J28: 346.39 | K28: 621.72 | L28: 523.1 | M28: 829.34 | N28: 445.28 | O28: 672.83 | P28: =SOCF!Q64 -> 635.78825 | Q28: =SOCF!R64 -> 780.74675 | R28: =SOCF!S64 -> 894.29715 | S28: =SOCF!T64 -> 975.35534
B29: Other Balances with Bank | I29: 219 | J29: 264.36 | K29: 242.61 | L29: 320.72 | M29: 254.67 | N29: 336.7 | O29: 400.85 | P29: =SOCF!Q65 -> 378.78175 | Q29: =SOCF!R65 -> 465.14325 | R29: =SOCF!S65 -> 532.79285 | S29: =SOCF!T65 -> 581.08466
B30: Other Financial Assets | I30: =18.67+781.65+512.48 -> 1312.8 | J30: =1197.24+3267.12 -> 4464.36 | K30: =2180.7+1533.5 -> 3714.2 | L30: =2697+1592.78 -> 4289.78 | M30: =1651.35+3203.41 -> 4854.76 | N30: =1158.11+3244.96 -> 4403.07 | O30: =6285.83+0.46+1822.67 -> 8108.96 | P30: =O30*(1+Q74) -> 9162.0102 | Q30: =P30*(1+R74) -> 10351.812 | R30: =Q30*(1+S74) -> 11696.125 | S30: =R30*(1+T74) -> 13215.013
B31: Other Current Assets | I31: 285.59 | J31: 537.23 | K31: 541.25 | L31: 553.98 | M31: 785.83 | N31: 773.71 | O31: 796.51 | P31: =O31*(1+Q75) -> 814.14421 | Q31: =P31*(1+R75) -> 832.16883 | R31: =Q31*(1+S75) -> 850.5925 | S31: =R31*(1+T75) -> 869.42406
B32: Assets classified as Held for Sale | I32: 13.86 | J32: 13.49 | K32: 8.13 | L32: 0 | M32: 0 | N32: 0 | O32: 0 | P32: 0 | Q32: 0 | R32: 0 | S32: 0
B33: Total Current Assets | I33: =SUM(I25:I32) -> 7580.11 | J33: =SUM(J25:J32) -> 12026.6 | K33: =SUM(K25:K32) -> 15152.33 | L33: =SUM(L25:L32) -> 16535.16 | M33: =SUM(M25:M31) -> 17537.06 | N33: =SUM(N25:N31) -> 16991.68 | O33: =SUM(O25:O31) -> 20184.64 | P33: =SUM(P25:P31) -> 22661.058 | Q33: =SUM(Q25:Q31) -> 25167.035 | R33: =SUM(R25:R31) -> 27875.8 | S33: =SUM(S25:S31) -> 30814.668
B34: TOTAL ASSETS | I34: =SUM(I22+I33) -> 16154.77 | J34: =SUM(J22+J33) -> 20369.62 | K34: =SUM(K22+K33) -> 22984.45 | L34: =SUM(L22+L33) -> 25798 | M34: =SUM(M22+M33) -> 29924.09 | N34: =SUM(N22+N33) -> 30371.37 | O34: =SUM(O22+O33) -> 34534.49 | P34: =SUM(P22+P33) -> 37800.455 | ... S34: =SUM(S22+S33) -> 48764.64
B36: EQUITY AND LIABILITIES
B37: Equity
B38: Equity Share capital | I38: 95.92 | J38: 95.92 | K38: 95.92 | L38: 95.92 | M38: 95.92 | N38: 95.92 | O38: 95.92 | P38: 95.92 | Q38: 95.92 | R38: 95.92 | S38: 95.92
B39: Other Equity | I39: =10034.24 -> 10034.24 | J39: =12710.37 -> 12710.37 | K39: =13715.64 -> 13715.64 | L39: =15896.31 -> 15896.31 | M39: =18632.38 -> 18632.38 | N39: =19303.89 -> 19303.89 | O39: =21275.67 -> 21275.67 | P39: =O39+(SOPL!P32-SOPL!P33)*(1-Q76) -> 23067.189 | Q39: =P39+(SOPL!Q32-SOPL!Q33)*(1-R76) -> 25019.721 | R39: =Q39+(SOPL!R32-SOPL!R33)*(1-S76) -> 27144.847 | S39: =R39+(SOPL!S32-SOPL!S33)*(1-T76) -> 29455.111
B40: NCI | I40: 403.53 | J40: 422.86 | K40: 387.53 | L40: 453.66 | M40: 695.38 | N40: 659.24 | O40: 643.39 | P40: =O40+(SOPL!P32-SOPL!P33)*'SOFP '!Q76 -> 705.04298 | Q40: =P40+(SOPL!Q32-SOPL!Q33)*'SOFP '!R76 -> 772.23706 | R40: =Q40+(SOPL!R32-SOPL!R33)*'SOFP '!S76 -> 845.37071 | S40: =R40+(SOPL!S32-SOPL!S33)*'SOFP '!T76 -> 924.87569
B41: Total Equity | I41: =SUM(I38:I40) -> 10533.69 | J41: =SUM(J38:J40) -> 13229.15 | K41: =SUM(K38:K40) -> 14199.09 | L41: =SUM(L38:L40) -> 16445.89 | M41: =SUM(M38:M40) -> 19423.68 | N41: =SUM(N38:N40) -> 20059.05 | O41: =SUM(O38:O40) -> 22014.98 | P41: =SUM(P38:P40) -> 23868.152 | ... S41: =SUM(S38:S40) -> 30475.906
B43: Liabilities
B44: Non-Current Liabilities
B45: Financial Liabilities
B46: Lease Liabilities | I46: =589.94 -> 589.94 | J46: 561.36 | K46: =598.37 -> 598.37 | L46: =728.94 -> 728.94 | M46: =1095.29 -> 1095.29 | N46: =1123.3 -> 1123.3 | O46: =1306.94 -> 1306.94 | P46: =O46*(1+Q77) -> 1556.3643 | Q46: =P46*(1+R77) -> 1853.3903 | R46: =Q46*(1+S77) -> 2207.1024 | S46: =R46*(1+T77) -> 2628.3192
B47: Borrowings | I47: 18.63 | J47: 14.53 | K47: 44.54 | L47: 76.15 | M47: 54.38 | N47: 259.62 | O47: 1247.17 | P47: =SUM(P38:P39)*'Ratio Analysis'!$Q28 -> 1338.218 | Q47: =SUM(Q38:Q39)*'Ratio Analysis'!$Q28 -> 1451.0229 | R47: =SUM(R38:R39)*'Ratio Analysis'!$Q28 -> 1573.7992 | S47: =SUM(S38:S39)*'Ratio Analysis'!$Q28 -> 1707.2717
B48: Other Financial Liabilities | I48: 2.94 | J48: =3.38 -> 3.38 | K48: 2.18 | L48: 46.38 | M48: 240.58 | N48: 79.93 | O48: 113.66 | P48: =O48*(1+Q$78) -> 113.9755 | Q48: =P48*(1+R$78) -> 114.29187 | R48: =Q48*(1+S$78) -> 114.60912 | S48: =R48*(1+T$78) -> 114.92725
B49: Deferred Tax Liabilities (Net) | I49: 443.8 | J49: 415.59 | K49: 348.85 | L49: 334.84 | M49: 352.17 | N49: 404.91 | O49: 403.26 | P49: =O49*(1+Q79) -> 412.87394 | Q49: =P49*(1+R79) -> 422.71707 | R49: =Q49*(1+S79) -> 432.79488 | S49: =R49*(1+T79) -> 443.11294
B50: Other Non-Current Liabilities | I50: =4.64+180.75 -> 185.39 | J50: =215.21+4.54 -> 219.75 | K50: =218.32+2.11 -> 220.43 | L50: =230.7+39.17 -> 269.87 | M50: =34.47+222.56 -> 257.03 | N50: =45.55+257.78 -> 303.33 | O50: =273.8+37.65 -> 311.45 | P50: =O50*(1+Q80) -> 314.17601 | Q50: =P50*(1+R80) -> 316.92588 | R50: =Q50*(1+S80) -> 319.69982 | S50: =R50*(1+T80) -> 322.49804
B51: Total Non-Current Liabilities | I51: =SUM(I46:I50) -> 1240.7 | J51: =SUM(J46:J50) -> 1214.61 | K51: =SUM(K46:K50) -> 1214.37 | L51: =SUM(L46:L50) -> 1456.18 | M51: =SUM(M46:M50) -> 1999.45 | N51: =SUM(N46:N50) -> 2171.09 | O51: =SUM(O46:O50) -> 3382.48 | P51: =SUM(P46:P50) -> 3735.6077 | ... S51: =SUM(S46:S50) -> 5216.1291
B53: Current Liabilities
B54: Financial Liabilities
B55: Trade Payables | I55: =60.72+2075.85 -> 2136.57 | J55: =91.53+3287.19 -> 3378.72 | K55: =4080.72+83.58 -> 4164.3 | L55: =143.88+3491.56 -> 3635.44 | M55: =250.27+3581.07 -> 3831.34 | N55: =208.58+3639.42 -> 3848 | O55: =258.56+3604.48 -> 3863.04 | P55: =(SOPL!P$14+SOPL!P$15)*'Ratio Analysis'!$Q$50/'Ratio Analysis'!$G$52 -> 4455.3933 | Q55: =(SOPL!Q$14+SOPL!Q$15)*'Ratio Analysis'!$Q$50/'Ratio Analysis'!$G$52 -> 4862.6778 | R55: =(SOPL!R$14+SOPL!R$15)*'Ratio Analysis'!$Q$50/'Ratio Analysis'!$G$52 -> 5307.3755 | S55: =(SOPL!S$14+SOPL!S$15)*'Ratio Analysis'!$Q$50/'Ratio Analysis'!$G$52 -> 5792.9109
B56: Borrowings | I56: 321.48 | J56: 325.7 | K56: 731.12 | L56: =896.06 -> 896.06 | M56: 1052.76 | N56: 604.16 | O56: 1046.09 | P56: =P47/Q84 -> 1122.4584 | Q56: =Q47/R84 -> 1217.0759 | R56: =R47/S84 -> 1320.0571 | S56: =S47/T84 -> 1432.0099
B57: Lease Liabilities | I57: 173.87 | J57: 183.18 | K57: =212.85 -> 212.85 | L57: 231.47 | M57: 271.95 | N57: 303.24 | O57: 328.73 | P57: =P46*Q85 -> 458.6993 | Q57: =Q46*R85 -> 546.24024 | R57: =R46*S85 -> 650.48802 | S57: =S46*T85 -> 774.63108
B58: Other Financial Liabilities | I58: =1374.34 -> 1374.34 | J58: 1603.02 | K58: =1886.61 -> 1886.61 | L58: 2436.02 | M58: 2675.44 | N58: 2742.04 | O58: 3044.72 | P58: =O58*(1+Q81) -> 3269.5067 | Q58: =P58*(1+R81) -> 3510.8891 | R58: =Q58*(1+S81) -> 3770.0923 | S58: =R58*(1+T81) -> 4048.4321
B59: Other Current Liabilities | I59: =62.46+131.61 -> 194.07 | J59: =229.58+84.43 -> 314.01 | K59: =376.09+69.7 -> 445.79 | L59: =459.04+74.21 -> 533.25 | M59: =484.48+62.48 -> 546.96 | N59: =450.58+67.15 -> 517.73 | O59: =457.86+216.58 -> 674.44 | P59: =O59*(1+Q82) -> 684.77146 | Q59: =P59*(1+R82) -> 695.26118 | R59: =Q59*(1+S82) -> 705.91158 | S59: =R59*(1+T82) -> 716.72514
B60: Income Tax Liabilities (Net) | I60: 180.05 | J60: 121.23 | K60: 130.12 | L60: 163.69 | M60: 122.51 | N60: 126.09 | O60: 180.01 | P60: =O60*(1+Q83) -> 205.86076 | Q60: =P60*(1+R83) -> 235.42388 | R60: =Q60*(1+S83) -> 269.23249 | S60: =R60*(1+T83) -> 307.89625
B61: Total Current-Liabilities | I61: =SUM(I55:I60) -> 4380.38 | J61: =SUM(J55:J60) -> 5925.86 | K61: =SUM(K55:K60) -> 7570.79 | L61: =SUM(L55:L60) -> 7895.93 | M61: =SUM(M55:M60) -> 8500.96 | N61: =SUM(N55:N60) -> 8141.26 | O61: =SUM(O55:O60) -> 9137.03 | P61: =SUM(P55:P60) -> 10196.69 | ... S61: =SUM(S55:S60) -> 13072.605
B62: TOTAL EQUITY AND LIABILITIES | I62: =I51+I61+I41 -> 16154.77 | J62: =J51+J61+J41 -> 20369.62 | K62: =K51+K61+K41 -> 22984.25 | L62: =L51+L61+L41 -> 25798 | M62: =M51+M61+M41 -> 29924.09 | N62: =N51+N61+N41 -> 30371.4 | O62: =O51+O61+O41 -> 34534.49 | P62: =P51+P61+P41 -> 37800.449 | ... S62: =S51+S61+S41 -> 48764.641
B64: FORECAST ASSUMPTIONS & BASIS
B66: Years | I66: =J66-1 -> 20 | J66: 21 | K66: =J66+1 -> 22 | L66: =K66+1 -> 23 | M66: =L66+1 -> 24 | N66: =M66+1 -> 25 | O66: =N66+1 -> 26 | P66: Basis | Q66: =O66+1 -> 27 | R66: =Q66+1 -> 28 | S66: =R66+1 -> 29 | T66: =S66+1 -> 30
B68: CWIP as % of PPE | I68: =I15/I13 -> 0.029432752 | J68: =J15/J13 -> 0.040877054 | K68: =K15/K13 -> 0.10190801 | L68: =L15/L13 -> 0.24594213 | M68: =M15/M13 -> 0.60689353 | N68: =N15/N13 -> 0.18482031 | O68: =O15/O13 -> 0.25869165 | P68: =MEDIAN(L68:O68) -> 0.25231689 | Q68: =P68 -> 0.25231689 | R68: =Q68 -> 0.25231689 | S68: =R68 -> 0.25231689 | T68: =S68 -> 0.25231689
B69: Investment in Associates Growth % | I69: 0 | J69: =J17/I17-1 -> 0.059720124 | K69: =K17/J17-1 -> 0.065240752 | L69: =L17/K17-1 -> 0.5165383 | M69: =M17/L17-1 -> -0.25405191 | N69: =N17/M17-1 -> 0.042649152 | O69: =O17/N17-1 -> 0.079095395 | P69: =MEDIAN(L69:O69) -> 0.060872273 | Q69: =P69 -> 0.060872273 | R69: =Q69 -> 0.060872273 | S69: =R69 -> 0.060872273 | T69: =S69 -> 0.060872273
B70: Non-Current Financial Assets Growth % | I70: 0 | J70: =J18/I18-1 -> 0.15485589 | K70: =K18/J18-1 -> -0.34302755 | L70: =L18/K18-1 -> 0.10436522 | M70: =M18/L18-1 -> 0.22758266 | N70: =N18/M18-1 -> 0.24734158 | O70: =O18/N18-1 -> -0.053345769 | P70: =MEDIAN(I70:O70) -> 0.10436522 | Q70: =P70 -> 0.10436522 | R70: =Q70 -> 0.10436522 | S70: =R70 -> 0.10436522 | T70: =S70 -> 0.10436522
B71: Deferred Tax Assets (Net) as % of Tax Expense | I71: ='SOFP '!I19/SOPL!I29 -> 0.019652571 | J71: ='SOFP '!J19/SOPL!J29 -> 0.013010204 | K71: ='SOFP '!K19/SOPL!K29 -> 0.023592134 | L71: ='SOFP '!L19/SOPL!L29 -> 0.012500837 | M71: ='SOFP '!M19/SOPL!M29 -> 0.013027351 | N71: ='SOFP '!N19/SOPL!N29 -> 0.011569157 | O71: ='SOFP '!O19/SOPL!O29 -> 0.0097839938 | P71: =MEDIAN(I71:O71) -> 0.013010204 | Q71: =P71 -> 0.013010204 | R71: =Q71 -> 0.013010204 | S71: =R71 -> 0.013010204 | T71: =S71 -> 0.013010204
B72: Income Tax Assets (Net) Growth % | I72: 0 | J72: =J20/I20-1 -> -0.39851436 | K72: =K20/J20-1 -> 0.13289102 | L72: =L20/K20-1 -> 0.098921489 | M72: =M20/L20-1 -> 0.045325032 | N72: =N20/M20-1 -> 0.11867145 | O72: =O20/N20-1 -> 0.12183016 | P72: =MEDIAN(I72:O72) -> 0.098921489 | Q72: =P72 -> 0.098921489 | R72: =Q72 -> 0.098921489 | S72: =R72 -> 0.098921489 | T72: =S72 -> 0.098921489
B73: Other Non-Current Assets/PPE | I73: =I21/I13 -> 0.013660709 | J73: =J21/J13 -> 0.015275839 | K73: =K21/K13 -> 0.031753201 | L73: =L21/L13 -> 0.080696634 | M73: =M21/M13 -> 0.073728127 | N73: =N21/N13 -> 0.044348387 | O73: =O21/O13 -> 0.038609169 | P73: =MEDIAN(L73:O73) -> 0.059038257 | Q73: =P73 -> 0.059038257 | R73: =Q73 -> 0.059038257 | S73: =R73 -> 0.059038257 | T73: =S73 -> 0.059038257
B74: Other Current Financial Assets as % of Revenue | I74: =I30/SOPL!I$13 -> 0.064953924 | J74: =J30/SOPL!J$13 -> 0.20560969 | K74: =K30/SOPL!K$13 -> 0.12763012 | L74: =L30/SOPL!L$13 -> 0.12438259 | M74: =M30/SOPL!M$13 -> 0.13677411 | N74: =N30/SOPL!N$13 -> 0.12986254 | O74: =O30/SOPL!O$13 -> 0.22788514 | P74: =MEDIAN(I74:O74) -> 0.12986254 | Q74: =P74 -> 0.12986254 | R74: =Q74 -> 0.12986254 | S74: =R74 -> 0.12986254 | T74: =S74 -> 0.12986254
B75: Other Current Assets as % of Revenue | I75: =I31/SOPL!I$13 -> 0.014130249 | J75: =J31/SOPL!J$13 -> 0.02474256 | K75: =K31/SOPL!K$13 -> 0.018598838 | L75: =L31/SOPL!L$13 -> 0.016062704 | M75: =M31/SOPL!M$13 -> 0.022139343 | N75: =N31/SOPL!N$13 -> 0.022819521 | O75: =O31/SOPL!O$13 -> 0.022384226 | P75: =MEDIAN(I75:O75) -> 0.022139343 | Q75: =P75 -> 0.022139343 | R75: =Q75 -> 0.022139343 | S75: =R75 -> 0.022139343 | T75: =S75 -> 0.022139343
B76: Proportion of NCI to Other Equity (RE Distribution) | I76: =I40/I39 -> 0.040215303 | J76: =J40/J39 -> 0.033268898 | K76: =K40/K39 -> 0.028254606 | L76: =L40/L39 -> 0.028538699 | M76: =M40/M39 -> 0.037321051 | N76: =N40/N39 -> 0.03415063 | O76: =O40/O39 -> 0.030240646 | P76: =MEDIAN(I76:O76) -> 0.033268898 | Q76: =P76 -> 0.033268898 | R76: =Q76 -> 0.033268898 | S76: =R76 -> 0.033268898 | T76: =S76 -> 0.033268898
B77: Non-Current Lease Liabilities Growth % | I77: 0 | J77: =J46/I46-1 -> -0.048445605 | K77: =K46/J46-1 -> 0.065929172 | L77: =L46/K46-1 -> 0.21820947 | M77: =M46/L46-1 -> 0.50257909 | N77: =N46/M46-1 -> 0.025573136 | O77: =O46/N46-1 -> 0.1634826 | P77: =MEDIAN(L77:O77) -> 0.19084603 | Q77: =P77 -> 0.19084603 | R77: =Q77 -> 0.19084603 | S77: =R77 -> 0.19084603 | T77: =S77 -> 0.19084603
B78: Other Current Financial Liabilities as % of Revenue | I78: =I48/SOPL!I13 -> 0.00014546354 | J78: =J48/SOPL!J13 -> 0.00015566862 | K78: =K48/SOPL!K13 -> 7.4910794e-05 | L78: =L48/SOPL!L13 -> 0.0013447926 | M78: =M48/SOPL!M13 -> 0.0067779076 | N78: =N48/SOPL!N13 -> 0.0023574263 | O78: =O48/SOPL!O13 -> 0.0031941735 | P78: =MEDIAN(L78:O78) -> 0.0027757999 | Q78: =P78 -> 0.0027757999 | R78: =Q78 -> 0.0027757999 | S78: =R78 -> 0.0027757999 | T78: =S78 -> 0.0027757999
B79: Deferred Tax Liabilities (Net) Growth % | I79: 0 | J79: =J49/I49-1 -> -0.063564669 | K79: =K49/J49-1 -> -0.16059097 | L79: =L49/K49-1 -> -0.040160527 | M79: =M49/L49-1 -> 0.051756063 | N79: =N49/M49-1 -> 0.14975722 | O79: =O49/N49-1 -> -0.0040749796 | P79: =MEDIAN(L79:O79) -> 0.023840541 | Q79: =P79 -> 0.023840541 | R79: =Q79 -> 0.023840541 | S79: =R79 -> 0.023840541 | T79: =S79 -> 0.023840541
B80: Other Non-Current Liabilities as % of Revenue | I80: =I50/SOPL!I13 -> 0.0091726143 | J80: =J50/SOPL!J13 -> 0.010120763 | K80: =K50/SOPL!K13 -> 0.0075745809 | L80: =L50/SOPL!L13 -> 0.0078249067 | M80: =M50/SOPL!M13 -> 0.0072413567 | N80: =N50/SOPL!N13 -> 0.0089463045 | O80: =O50/SOPL!O13 -> 0.0087526424 | P80: =MEDIAN(I80:O80) -> 0.0087526424 | Q80: =P80 -> 0.0087526424 | R80: =Q80 -> 0.0087526424 | S80: =R80 -> 0.0087526424 | T80: =S80 -> 0.0087526424
B81: Other Non-Current Financial Liabilities as % of Revenue | I81: =I58/SOPL!I$13 -> 0.067998763 | J81: =J58/SOPL!J$13 -> 0.073828375 | K81: =K58/SOPL!K$13 -> 0.064829107 | L81: =L58/SOPL!L$13 -> 0.070632635 | M81: =M58/SOPL!M$13 -> 0.075375697 | N81: =N58/SOPL!N$13 -> 0.080872728 | O81: =O58/SOPL!O$13 -> 0.085565405 | P81: =MEDIAN(I81:O81) -> 0.073828375 | Q81: =P81 -> 0.073828375 | R81: =Q81 -> 0.073828375 | S81: =R81 -> 0.073828375 | T81: =S81 -> 0.073828375
B82: Other Current Liabilities as % of Revenue | I82: =I59/SOPL!I$13 -> 0.0096020781 | J82: =J59/SOPL!J$13 -> 0.014461983 | K82: =K59/SOPL!K$13 -> 0.01531857 | L82: =L59/SOPL!L$13 -> 0.015461635 | M82: =M59/SOPL!M$13 -> 0.015409612 | N82: =N59/SOPL!N$13 -> 0.01526974 | O82: =O59/SOPL!O$13 -> 0.018953707 | P82: =MEDIAN(I82:O82) -> 0.01531857 | Q82: =P82 -> 0.01531857 | R82: =Q82 -> 0.01531857 | S82: =R82 -> 0.01531857 | T82: =S82 -> 0.01531857
B83: Income Tax Liabilities (Net) Growth % | I83: 0 | J83: =J60/I60-1 -> -0.32668703 | K83: =K60/J60-1 -> 0.073331684 | L83: =L60/K60-1 -> 0.25799262 | M83: =M60/L60-1 -> -0.2515731 | N83: =N60/M60-1 -> 0.029222104 | O83: =O60/N60-1 -> 0.42763106 | P83: =MEDIAN(L83:O83) -> 0.14360736 | Q83: =P83 -> 0.14360736 | R83: =Q83 -> 0.14360736 | S83: =R83 -> 0.14360736 | T83: =S83 -> 0.14360736
B84: Non-Current Borrowing/Current Borrowing | I84: =I47/I56 -> 0.057950728 | J84: =J47/J56 -> 0.044611606 | K84: =K47/K56 -> 0.060920232 | L84: =L47/L56 -> 0.084983148 | M84: =M47/M56 -> 0.051654698 | N84: =N47/N56 -> 0.4297206 | O84: =O47/O56 -> 1.1922206 | P84: =O84 -> 1.1922206 | Q84: =P84 -> 1.1922206 | R84: =Q84 -> 1.1922206 | S84: =R84 -> 1.1922206 | T84: =S84 -> 1.1922206
B85: Current Lease Liabilities/Non-Current Lease Liabilities | I85: =I57/I46 -> 0.29472489 | J85: =J57/J46 -> 0.32631466 | K85: =K57/K46 -> 0.35571636 | L85: =L57/L46 -> 0.31754328 | M85: =M57/M46 -> 0.24829041 | N85: =N57/N46 -> 0.2699546 | O85: =O57/O46 -> 0.25152647 | P85: =MEDIAN(I85:O85) -> 0.29472489 | Q85: =P85 -> 0.29472489 | R85: =Q85 -> 0.29472489 | S85: =R85 -> 0.29472489 | T85: =S85 -> 0.29472489

Sheet SOPL
G2: NSE: ASIANPAINT | BSE:500820
G3: 52-WEEK (HIGH: ₹ 2985.70| LOW: ₹ 2115.00 )
G4: 2649.4
G5: (as at 13 July 2026)
B6: CONSOLIDATED STATEMENT OF PROFIT AND LOSS
B7: (in ₹ Cr. unless stated otherwise)
I8: Historical | P8: Forecasts
B9: Years | I9: =J9-1 -> 20 | J9: 21 | K9: =J9+1 -> 22 | L9: =K9+1 -> 23 | M9: =L9+1 -> 24 | N9: =M9+1 -> 25 | O9: =N9+1 -> 26 | P9: =O9+1 -> 27 | Q9: =P9+1 -> 28 | R9: =Q9+1 -> 29 | S9: =R9+1 -> 30
B11: Revenue from Sale of Products and Services | I11: =20025.96+22.36 -> 20048.32 | J11: =21440.24+44.96 -> 21485.2 | K11: =28830.02+93.46 -> 28923.48 | L11: =34253.35+114.48 -> 34367.83 | M11: =35248.88+133.24 -> 35382.12 | N11: =33626.82+170.54 -> 33797.36 | O11: =35416.25+100.12 -> 35516.37 | P11: =O11*(1+Q42) -> 38772.175 | Q11: =P11*(1+R42) -> 42326.44 | R11: =Q11*(1+S42) -> 46206.528 | S11: =R11*(1+T42) -> 50442.305
B12: Other Operating Revenue | I12: 162.93 | J12: 227.59 | K12: 177.8 | L12: 120.76 | M12: 112.61 | N12: 108.26 | O12: 67.17 | P12: =O12*(1+Q43) -> 62.636748 | Q12: =P12*(1+R43) -> 58.409442 | R12: =Q12*(1+S43) -> 54.467433 | S12: =R12*(1+T43) -> 50.791468
B13: REVENUE FROM OPERATIONS | I13: =SUM(I11:I12) -> 20211.25 | J13: =SUM(J11:J12) -> 21712.79 | K13: =SUM(K11:K12) -> 29101.28 | L13: =SUM(L11:L12) -> 34488.59 | M13: =SUM(M11:M12) -> 35494.73 | N13: =SUM(N11:N12) -> 33905.62 | O13: =SUM(O11:O12) -> 35583.54 | P13: =SUM(P11:P12) -> 38834.811 | ... S13: =SUM(S11:S12) -> 50493.096
B14: Materials Cost | I14: 10091.78 | J14: 10317.09 | K14: 16254.59 | L14: 17330.58 | M14: 15868.21 | N14: 15793.92 | O14: 15384.05 | P14: =P$13*Q44 -> 18452.822 | Q14: =Q$13*R44 -> 20139.665 | R14: =R$13*S44 -> 21981.461 | S14: =S$13*T44 -> 23992.394
B15: Purchases of Stock-in-Trade | I15: 1530.83 | J15: 1872.59 | K15: 3371.13 | L15: 4135.65 | M15: 3858.2 | N15: 3926.86 | O15: 4014.05 | P15: =P$13*Q45 -> 4380.8141 | Q15: =Q$13*R45 -> 4781.2811 | R15: =R$13*S45 -> 5218.535 | S15: =S$13*T45 -> 5695.9429
B16: Changes in Inventories | I16: -239.15 | J16: -92.45 | K16: -1324.97 | L16: -309.73 | M16: 363.8 | N16: -205 | O16: 603.68 | P16: =P$13*Q46 -> -234.80285 | Q16: =Q$13*R46 -> -256.26708 | R16: =R$13*S46 -> -279.70301 | S16: =S$13*T46 -> -305.29112
B17: COST OF GOODS SOLD | I17: =SUM(I14:I16) -> 11383.46 | J17: =SUM(J14:J16) -> 12097.23 | K17: =SUM(K14:K16) -> 18300.75 | L17: =SUM(L14:L16) -> 21156.5 | M17: =SUM(M14:M16) -> 20090.21 | N17: =SUM(N14:N16) -> 19515.78 | O17: =SUM(O14:O16) -> 20001.78 | P17: =SUM(P14:P16) -> 22598.833 | ... S17: =SUM(S14:S16) -> 29383.046
B18: GROSS MARGIN | I18: =I13-I17 -> 8827.79 | J18: =J13-J17 -> 9615.56 | K18: =K13-K17 -> 10800.53 | L18: =L13-L17 -> 13332.09 | M18: =M13-M17 -> 15404.52 | N18: =N13-N17 -> 14389.84 | O18: =O13-O17 -> 15581.76 | P18: =P13-P17 -> 16235.978 | ... S18: =S13-S17 -> 21110.05
B19: Other Non-Operating Income | I19: 304.31 | J19: 303.05 | K19: 380.01 | L19: 386.48 | M19: 687.96 | N19: 572.61 | O19: 723.8 | P19: =O19*(1+Q49) -> 836.24905 | Q19: =P19*(1+R49) -> 966.16811 | R19: =Q19*(1+S49) -> 1116.2713 | S19: =R19*(1+T49) -> 1289.6944
B20: Employee Benefits Expense | I20: 1366.09 | J20: 1540.75 | K20: 1786.67 | L20: 2028.07 | M20: 2326.18 | N20: 2597.23 | O20: 2799.59 | P20: =O20*(1+Q47) -> 3167.688 | Q20: =P20*(1+R47) -> 3584.1845 | R20: =Q20*(1+S47) -> 4055.4432 | S20: =R20*(1+T47) -> 4588.6643
B21: Other Expenses | I21: 3299.93 | J21: 3219.21 | K21: 4210.25 | L21: 5044.18 | M21: 5493.36 | N21: 5786.4 | O21: 6086.25 | P21: =P$13*Q48 -> 6010.2894 | Q21: =Q$13*R48 -> 6559.7129 | R21: =R$13*S48 -> 7159.6065 | S21: =S$13*T48 -> 7814.5898
B22: EBITDA | I22: =SUM(I18:I19)-SUM(I20:I21) -> 4466.08 | J22: =SUM(J18:J19)-SUM(J20:J21) -> 5158.65 | K22: =SUM(K18:K19)-SUM(K20:K21) -> 5183.62 | L22: =SUM(L18:L19)-SUM(L20:L21) -> 6646.32 | M22: =SUM(M18:M19)-SUM(M20:M21) -> 8272.94 | N22: =SUM(N18:N19)-SUM(N20:N21) -> 6578.82 | O22: =SUM(O18:O19)-SUM(O20:O21) -> 7419.72 | P22: =SUM(P18:P19)-SUM(P20:P21) -> 7894.25 | ... S22: =SUM(S18:S19)-SUM(S20:S21) -> 9996.4905
B23: Depreciation and Amortisation Expense | I23: 780.5 | J23: 791.27 | K23: 816.36 | L23: 858.02 | M23: 853 | N23: 1026.34 | O23: 1228.85 | P23: =Schedule!AG47 -> 1338.0711 | Q23: =Schedule!AH47 -> 1402.9337 | R23: =Schedule!AI47 -> 1477.7125 | S23: =Schedule!AJ47 -> 1562.8011
B24: EBIT | I24: =I22-I23 -> 3685.58 | J24: =J22-J23 -> 4367.38 | K24: =K22-K23 -> 4367.26 | L24: =L22-L23 -> 5788.3 | M24: =M22-M23 -> 7419.94 | N24: =N22-N23 -> 5552.48 | O24: =O22-O23 -> 6190.87 | P24: =P22-P23 -> 6556.1789 | ... S24: =S22-S23 -> 8433.6894
B25: Share of Profit in Associate | I25: 50.74 | J25: 28.6 | K25: 31.57 | L25: 93.85 | M25: 133 | N25: 140.71 | O25: 165.59 | P25: =O25*(1+Q50) -> 182.78588 | Q25: =P25*(1+R50) -> 201.7675 | R25: =Q25*(1+S50) -> 222.72027 | S25: =R25*(1+T50) -> 245.84892
B26: Exceptional Items | I26: 0 | J26: 0 | K26: -115.7 | L26: -48.87 | M26: 0 | N26: -363.1 | O26: -157.61 | P26: 0 | Q26: 0 | R26: 0 | S26: 0
B27: Finance Costs | I27: 102.33 | J27: 91.63 | K27: 95.41 | L27: 144.45 | M27: 205.17 | N27: 227.02 | O27: 195.41 | P27: =Schedule!M64 -> 209.84591 | Q27: =Schedule!N64 -> 225.34826 | R27: =Schedule!O64 -> 241.99586 | S27: =Schedule!P64 -> 259.87329
B28: PROFIT BEFORE TAX | I28: =SUM(I24:I26)-I27 -> 3633.99 | J28: =SUM(J24:J26)-J27 -> 4304.35 | K28: =SUM(K24:K26)-K27 -> 4187.72 | L28: =SUM(L24:L26)-L27 -> 5688.83 | M28: =SUM(M24:M26)-M27 -> 7347.77 | N28: =SUM(N24:N26)-N27 -> 5103.07 | O28: =SUM(O24:O26)-O27 -> 6003.44 | P28: =SUM(P24:P26)-P27 -> 6529.1188 | ... S28: =SUM(S24:S26)-S27 -> 8419.665
B29: Tax Expense | I29: 854.85 | J29: 1097.6 | K29: 1102.91 | L29: 1493.5 | M29: 1790.08 | N29: 1393.36 | O29: 1608.75 | P29: =P28*Q51 -> 1749.6169 | Q29: =Q28*R51 -> 1906.8648 | R29: =R28*S51 -> 2075.4209 | S29: =S28*T51 -> 2256.2291
B30: (Loss)/Profit from Discontinued Operations | I30: -4.95 | J30: 0 | K30: 0 | L30: 0 | M30: 0 | N30: 0 | O30: 0 | P30: 0 | Q30: 0 | R30: 0 | S30: 0
B31: PROFIT AFTER TAX | I31: =I28-I29+I30 -> 2774.19 | J31: =J28-J29+J30 -> 3206.75 | K31: =K28-K29+K30 -> 3084.81 | L31: =L28-L29+L30 -> 4195.33 | M31: =M28-M29+M30 -> 5557.69 | N31: =N28-N29+N30 -> 3709.71 | O31: =O28-O29+O30 -> 4394.69 | P31: =P28-P29+P30 -> 4779.502 | ... S31: =S28-S29+S30 -> 6163.4359
B32: Profit attributable to owners | I32: 2705.17 | J32: 3139.29 | K32: 3030.57 | L32: 4106.45 | M32: 5460.23 | N32: 3667.23 | O32: 4325.35 | P32: =P31*Q52 -> 4704.0903 | Q32: =Q31*R52 -> 5126.8733 | R32: =R31*S52 -> 5580.0603 | S32: =S31*T52 -> 6066.1884
B33: Dividend | I33: 1151.04 | J33: 1712.17 | K33: 1836.68 | L33: 2532.28 | M33: 3194.13 | N33: 2378.81 | O33: 2637.79 | P33: =P32*Q53 -> 2850.9187 | Q33: =Q32*R53 -> 3107.1467 | R33: =R32*S53 -> 3381.8012 | S33: =S32*T53 -> 3676.4196
B34: Earnings Per Share (EPS) (Basic) | H34: ₹/share | I34: 28.2 | J34: 32.73 | K34: 31.59 | L34: 42.83 | M34: 56.95 | N34: 38.25 | O34: 45.12 | P34: =P32/Q54*10000000 -> 49.071657 | Q34: =Q32/R54*10000000 -> 53.482002 | R34: =R32/S54*10000000 -> 58.209512 | S34: =S32/T54*10000000 -> 63.280655
B35: Dividend Per Share (DPS) | H35: ₹/share | I35: =I33/$I$54*10000000 -> 12.000028 | J35: =J33/$I$54*10000000 -> 17.85002 | K35: =K33/$I$54*10000000 -> 19.148084 | L35: =L33/$I$54*10000000 -> 26.399977 | M35: =M33/$I$54*10000000 -> 33.300014 | N35: =N33/$I$54*10000000 -> 24.799995 | O35: =O33/$I$54*10000000 -> 27.499959 | P35: =P33/P54*10000000 -> 29.739927 | Q35: =Q33/Q54*10000000 -> 32.412821 | R35: =R33/R54*10000000 -> 35.277934 | S35: =S33/S54*10000000 -> 38.351305
B36: NOTE: Reported EBIT includes Other Non-Operating Income and is taken as it is to reconcile with the publically issued historical ASIAN PAINTS LTD. INTEGRATED FINANCIAL REPORTS. For the purpose of FCFF Valuation, the Adjusted EBIT (Reported EBIT less Other Non-Operating Income) is used .
B38: FORECAST ASSUMPTIONS & BASIS
B40: Years | I40: =J40-1 -> 20 | J40: 21 | K40: =J40+1 -> 22 | L40: =K40+1 -> 23 | M40: =L40+1 -> 24 | N40: =M40+1 -> 25 | O40: =N40+1 -> 26 | P40: Basis | Q40: =O40+1 -> 27 | R40: =Q40+1 -> 28 | S40: =R40+1 -> 29 | T40: =S40+1 -> 30
B42: Revenue from Sale of Product and Services Growth % | I42: 0 | J42: =J11/I11-1 -> 0.071670843 | K42: =K11/J11-1 -> 0.34620483 | L42: =L11/K11-1 -> 0.18823288 | M42: =M11/L11-1 -> 0.029512774 | N42: =N11/M11-1 -> -0.044789854 | O42: =O11/N11-1 -> 0.050862257 | P42: =AVERAGE(I42:O42) -> 0.091670533 | Q42: =P42 -> 0.091670533 | R42: =Q42 -> 0.091670533 | S42: =R42 -> 0.091670533 | T42: =S42 -> 0.091670533
B43: Other Operating Revenue Growth % | I43: 0 | J43: =J12/I12-1 -> 0.39685755 | K43: =K12/J12-1 -> -0.2187706 | L43: =L12/K12-1 -> -0.3208099 | M43: =M12/L12-1 -> -0.067489235 | N43: =N12/M12-1 -> -0.038628896 | O43: =O12/N12-1 -> -0.37954923 | P43: =MEDIAN(I43:O43) -> -0.067489235 | Q43: =P43 -> -0.067489235 | R43: =Q43 -> -0.067489235 | S43: =R43 -> -0.067489235 | T43: =S43 -> -0.067489235
B44: Materials Cost as % of Revenue | I44: =I14/I$13 -> 0.49931499 | J44: =J14/J$13 -> 0.47516187 | K44: =K14/K$13 -> 0.55855241 | L44: =L14/L$13 -> 0.50250184 | M44: =M14/M$13 -> 0.4470582 | N44: =N14/N$13 -> 0.46582012 | O44: =O14/O$13 -> 0.43233613 | P44: =MEDIAN(I44:O44) -> 0.47516187 | Q44: =P44 -> 0.47516187 | R44: =Q44 -> 0.47516187 | S44: =R44 -> 0.47516187 | T44: =S44 -> 0.47516187
B45: Purchases of Stock-in-Trade as % of Revenue | I45: =I15/I$13 -> 0.075741481 | J45: =J15/J$13 -> 0.086243638 | K45: =K15/K$13 -> 0.1158413 | L45: =L15/L$13 -> 0.11991357 | M45: =M15/M$13 -> 0.10869783 | N45: =N15/N$13 -> 0.11581738 | O45: =O15/O$13 -> 0.11280637 | P45: =MEDIAN(I45:O45) -> 0.11280637 | Q45: =P45 -> 0.11280637 | R45: =Q45 -> 0.11280637 | S45: =R45 -> 0.11280637 | T45: =S45 -> 0.11280637
B46: Changes in Inventories as % of Revenue | I46: =I16/I$13 -> -0.011832519 | J46: =J16/J$13 -> -0.0042578591 | K46: =K16/K$13 -> -0.045529612 | L46: =L16/L$13 -> -0.0089806513 | M46: =M16/M$13 -> 0.010249409 | N46: =N16/N$13 -> -0.0060461953 | O46: =O16/O$13 -> 0.016965147 | P46: =MEDIAN(I46:O46) -> -0.0060461953 | Q46: =P46 -> -0.0060461953 | R46: =Q46 -> -0.0060461953 | S46: =R46 -> -0.0060461953 | T46: =S46 -> -0.0060461953
B47: Employee Benefits Expense Growth % | I47: 0 | J47: =J20/I20-1 -> 0.12785395 | K47: =K20/J20-1 -> 0.15961058 | L47: =L20/K20-1 -> 0.13511169 | M47: =M20/L20-1 -> 0.14699197 | N47: =N20/M20-1 -> 0.11652151 | O47: =O20/N20-1 -> 0.077913777 | P47: =MEDIAN(J47:O47) -> 0.13148282 | Q47: =P47 -> 0.13148282 | R47: =Q47 -> 0.13148282 | S47: =R47 -> 0.13148282 | T47: =S47 -> 0.13148282
B48: Other Expenses as % of Revenue | I48: =I21/I13 -> 0.16327194 | J48: =J21/J13 -> 0.1482633 | K48: =K21/K13 -> 0.14467577 | L48: =L21/L13 -> 0.14625649 | M48: =M21/M13 -> 0.15476551 | N48: =N21/N13 -> 0.17066197 | O48: =O21/O13 -> 0.17104116 | P48: =MEDIAN(I48:O48) -> 0.15476551 | Q48: =P48 -> 0.15476551 | R48: =Q48 -> 0.15476551 | S48: =R48 -> 0.15476551 | T48: =S48 -> 0.15476551
B49: Other Non-Operating Income Growth % | I49: 0 | J49: =J19/I19-1 -> -0.0041405146 | K49: =K19/J19-1 -> 0.25395149 | L49: =L19/K19-1 -> 0.017025868 | M49: =M19/L19-1 -> 0.78006624 | N49: =N19/M19-1 -> -0.16766963 | O49: =O19/N19-1 -> 0.2640366 | P49: =(O19/I19)^(1/6)-1 -> 0.15535929 | Q49: =P49 -> 0.15535929 | R49: =Q49 -> 0.15535929 | S49: =R49 -> 0.15535929 | T49: =S49 -> 0.15535929
B50: Share of Profit in Associate Growth % | I50: 0 | J50: =J25/I25-1 -> -0.43634214 | K50: =K25/J25-1 -> 0.10384615 | L50: =L25/K25-1 -> 1.9727589 | M50: =M25/L25-1 -> 0.41715503 | N50: =N25/M25-1 -> 0.057969925 | O50: =O25/N25-1 -> 0.17681757 | P50: =MEDIAN(I50:O50) -> 0.10384615 | Q50: =P50 -> 0.10384615 | R50: =Q50 -> 0.10384615 | S50: =R50 -> 0.10384615 | T50: =S50 -> 0.10384615
B51: Effective Tax Rate | I51: =I29/I28 -> 0.2352373 | J51: =J29/J28 -> 0.25499785 | K51: =K29/K28 -> 0.26336766 | L51: =L29/L28 -> 0.26253201 | M51: =M29/M28 -> 0.24362221 | N51: =N29/N28 -> 0.27304348 | O51: =O29/O28 -> 0.26797136 | P51: =O51 -> 0.26797136 | Q51: =P51 -> 0.26797136 | R51: =Q51 -> 0.26797136 | S51: =R51 -> 0.26797136 | T51: =S51 -> 0.26797136
B52: Profit attributable to owners as % of PAT | I52: =I32/I31 -> 0.97512067 | J52: =J32/J31 -> 0.97896312 | K52: =K32/K31 -> 0.98241707 | L52: =L32/L31 -> 0.97881454 | M52: =M32/M31 -> 0.98246394 | N52: =N32/N31 -> 0.98854897 | O52: =O32/O31 -> 0.98422187 | P52: =O52 -> 0.98422187 | Q52: =P52 -> 0.98422187 | R52: =Q52 -> 0.98422187 | S52: =R52 -> 0.98422187 | T52: =S52 -> 0.98422187
B53: Dividend Payout Ratio | I53: =I33/I32 -> 0.42549636 | J53: =J33/J32 -> 0.54540039 | K53: =K33/K32 -> 0.60605101 | L53: =L33/L32 -> 0.61665916 | M53: =M33/M32 -> 0.58498085 | N53: =N33/N32 -> 0.6486667 | O53: =O33/O32 -> 0.60984429 | P53: =MEDIAN(I53:O53) -> 0.60605101 | Q53: =P53 -> 0.60605101 | R53: =Q53 -> 0.60605101 | S53: =R53 -> 0.60605101 | T53: =S53 -> 0.60605101
B54: Weighted Avg. Shares (Basic) | H54: (nos.) | I54: 959197790 | J54: 959197790 | K54: 959077302 | L54: 958868120 | M54: 958841696 | N54: 958721421 | O54: 958616565 | P54: =O54 -> 958616565 | Q54: =P54 -> 958616565 | R54: =Q54 -> 958616565 | S54: =R54 -> 958616565 | T54: =S54 -> 958616565

Sheet SOCF
D2: NSE: ASIANPAINT | BSE:500820
D3: 52-WEEK (HIGH: ₹ 2985.70| LOW: ₹ 2115.00 )
D4: 2649.4
D5: (as at 13 July 2026)
B6: CONSOLIDATED STATEMENT OF CASH FLOWS
B7: (in ₹ Cr. unless stated otherwise)
J8: Historical | Q8: Forecasts
B9: Years | J9: =K9-1 -> 20 | K9: 21 | L9: =K9+1 -> 22 | M9: =L9+1 -> 23 | N9: =M9+1 -> 24 | O9: =N9+1 -> 25 | P9: =O9+1 -> 26 | Q9: =P9+1 -> 27 | R9: =Q9+1 -> 28 | S9: =R9+1 -> 29 | T9: =S9+1 -> 30 | U9: Trend
B11: (A) CASH FLOW FROM OPERATING ACTIVITIES
B12: Profit before tax
B13: Continued Operations | J13: =SOPL!I28 -> 3633.99 | K13: =SOPL!J28 -> 4304.35 | L13: =SOPL!K28 -> 4187.72 | M13: =SOPL!L28 -> 5688.83 | N13: =SOPL!M28 -> 7347.77 | O13: =SOPL!N28 -> 5103.07 | P13: =SOPL!O28 -> 6003.44 | Q13: =SOPL!P28 -> 6529.1188 | ... T13: =SOPL!S28 -> 8419.665
B14: Discontinued Operations | J14: -5.73 | K14: 0 | L14: 0 | M14: 0 | N14: 0 | O14: 0 | P14: 0 | Q14: 0 | R14: 0 | S14: 0 | T14: 0
B15: Adjustments:
B16: Depreciation and Amortisation expense | J16: =SOPL!I23 -> 780.5 | K16: =SOPL!J23 -> 791.27 | L16: =SOPL!K23 -> 816.36 | M16: =SOPL!L23 -> 858.02 | N16: =SOPL!M23 -> 853 | O16: =SOPL!N23 -> 1026.34 | P16: =SOPL!O23 -> 1228.85 | Q16: =SOPL!P23 -> 1338.0711 | ... T16: =SOPL!S23 -> 1562.8011
B17: Finance Cost | J17: =SOPL!I27 -> 102.33 | K17: =SOPL!J27 -> 91.63 | L17: =SOPL!K27 -> 95.41 | M17: =SOPL!L27 -> 144.45 | N17: =SOPL!M27 -> 205.17 | O17: =SOPL!N27 -> 227.02 | P17: =SOPL!O27 -> 195.41 | Q17: =SOPL!P27 -> 209.84591 | ... T17: =SOPL!S27 -> 259.87329
B18: Share of Profit in Associates | J18: =-SOPL!I25 -> -50.74 | K18: =-SOPL!J25 -> -28.6 | L18: =-SOPL!K25 -> -31.57 | M18: =-SOPL!L25 -> -93.85 | N18: =-SOPL!M25 -> -133 | O18: =-SOPL!N25 -> -140.71 | P18: =-SOPL!O25 -> -165.59 | Q18: =-SOPL!P25 -> -182.78588 | ... T18: =-SOPL!S25 -> -245.84892
B19: Impairment loss on Goodwill and Intangible assets | J19: 0 | K19: 0 | L19: 13.47 | M19: -27.58 | N19: 0 | O19: 223.25 | P19: 93.87 | Q19: =Schedule!Z36 -> 25.72 | R19: =Q19 -> 25.72 | S19: =R19 -> 25.72 | T19: =S19 -> 25.72
B20: Other* | J20: =J21-SUM(J13:J19) -> -80.61 | K20: =K21-SUM(K13:K19) -> -189.12 | L20: =L21-SUM(L13:L19) -> -123.99 | M20: =M21-SUM(M13:M19) -> -110.05 | N20: =N21-SUM(N13:N19) -> -344.34 | O20: =-179.84-20.64+227.02+245.18-227.02+6.06-4.69-11.06-3.37-2.07-182.43+21.25+83.71-18.29-1.78+18.66 -> -49.31 | P20: =-180.93-2.13+5.7+121.95-4.08+2.94+3.81-6.87-286.5+29.35+19.96+70.17+56.93 -> -169.7 | Q20: =P20*(1+R73) -> -281.28826 | R20: =Q20*(1+S73) -> -466.2527 | S20: =R20*(1+T73) -> -772.84273 | T20: =S20*(1+U73) -> -1281.0347
B21: Operating Profit before working capital changes | J21: 4379.74 | K21: 4969.53 | L21: 4957.4 | M21: 6459.82 | N21: 7928.6 | O21: =SUM(O13:O20) -> 6389.66 | P21: =SUM(P13:P20) -> 7186.28 | Q21: =SUM(Q13:Q20) -> 7638.6817 | R21: =SUM(R12:R20) -> 8101.9091 | S21: =SUM(S12:S20) -> 8494.8009 | T21: =SUM(T12:T20) -> 8741.1758
B22: Change in Working Capital | J22: =J23-J21 -> -330.84 | K22: =K23-K21 -> -206.46 | L22: =L23-L21 -> -2795.22 | M22: =M23-M21 -> -772.11 | N22: =N23-N21 -> 10.05 | O22: =O23-O21 -> -570.18 | P22: =P23-P21 -> 1475.72 | Q22: =$Q$75*SOPL!P13 -> -635.69096 | R22: =$Q$75*SOPL!Q13 -> -693.8019 | S22: =$Q$75*SOPL!R13 -> -757.25092 | T22: =$Q$75*SOPL!S13 -> -826.52661
B23: Cash generated from Operating activities | J23: 4048.9 | K23: 4763.07 | L23: 2162.18 | M23: 5687.71 | N23: 7938.65 | O23: 5819.48 | P23: 8662 | Q23: =SUM(Q21:Q22) -> 7002.9908 | R23: =SUM(R21:R22) -> 7408.1072 | S23: =SUM(S21:S22) -> 7737.55 | T23: =SUM(T21:T22) -> 7914.6492
B24: Income Tax paid (net of refund) | J24: -1010.75 | K24: -1079.72 | L24: -1175.69 | M24: -1494.28 | N24: -1835.05 | O24: -1395.52 | P24: -1573.82 | Q24: =-R76*SOPL!P29 -> -1746.9088 | R24: =-S76*SOPL!Q29 -> -1903.9133 | S24: =-T76*SOPL!R29 -> -2072.2086 | T24: =-U76*SOPL!S29 -> -2252.7369
B25: Net Cash generated from Operating activities | J25: 3038.15 | K25: 3683.35 | L25: 986.49 | M25: 4193.43 | N25: 6103.6 | O25: =SUM(O23:O24) -> 4423.96 | P25: =SUM(P23:P24) -> 7088.18 | Q25: =SUM(Q23:Q24) -> 5256.082 | R25: =SUM(R23:R24) -> 5504.1939 | S25: =SUM(S23:S24) -> 5665.3414 | T25: =SUM(T23:T24) -> 5661.9123
B27: (B) CASH FLOW FROM INVESTING ACTIVITIES
B28: Net CapEx (PPE, Goodwill & Intangible Assets) | J28: =-403.54+36.6 -> -366.94 | K28: =-281.87+27.61 -> -254.26 | L28: =-538.24+39.58 -> -498.66 | M28: =-1273.37+25.92 -> -1247.45 | N28: =-2199.01+5.13 -> -2193.88 | O28: =-1805.32+10.1 -> -1795.22 | P28: =-1467.02+3.2 -> -1463.82 | Q28: =-Schedule!Z11-Schedule!Z26 -> -1109.7583 | R28: =-Schedule!AC11-Schedule!AC26 -> -1211.2055 | S28: =-Schedule!AF11-Schedule!AF26 -> -1321.9717 | T28: =-Schedule!AI11-Schedule!AI26 -> -1442.9098
B29: Payment for acquiring right-of-use assets | J29: -10.15 | K29: -6.84 | L29: -12.46 | M29: -172.24 | N29: -297.07 | O29: -24.75 | P29: -20.3 | Q29: =P29*(1+R74) -> -22.78598 | R29: =Q29*(1+S74) -> -25.576397 | S29: =R29*(1+T74) -> -28.708535 | T29: =S29*(1+U74) -> -32.224241
B30: Net Proceeds from sale of Financial Assets | J30: =J34-SUM(J28:J29,J32) -> -236.78 | K30: =-0.5+272.32-139.34-500.33 -> -367.85 | L30: =146.46+61.03-110.21 -> 97.28 | M30: =-146.07+376.61+69.43-118.71 -> 181.26 | N30: =-212.24+0.5+239.99-206.25-75-37.71 -> -290.71 | O30: =-0.92+420.65+196.8+38.29 -> 654.82 | P30: =-0.1+923.36+274.03-1316.03 -> -118.74 | Q30: =MEDIAN(J30:P30) -> -118.74 | R30: =Q30 -> -118.74 | S30: =R30 -> -118.74 | T30: =S30 -> -118.74
B31: Loan given to third party | J31: 0 | K31: 0 | L31: 0 | M31: 0 | N31: 0 | O31: 0 | P31: -2.03 | Q31: 0 | R31: 0 | S31: 0 | T31: 0
B32: Interest and Dividends Received | J32: =65.32+27.13 -> 92.45 | K32: =73.35+7.81 -> 81.16 | L32: =76.99+15.16 -> 92.15 | M32: =87.15+42.78+13.48 -> 143.41 | N32: =135.49+108.37+20.17 -> 264.03 | O32: =154.89+115.5+20.64 -> 291.03 | P32: =153.19+115.5+2.13 -> 270.82 | Q32: =R77*SOPL!P19 -> 310.30448 | R32: =S77*SOPL!Q19 -> 358.51317 | S32: =T77*SOPL!R19 -> 414.21151 | T32: =U77*SOPL!S19 -> 478.56312
B33: Other | J33: 0 | K33: 0 | L33: 0 | M33: =M34-SUM(M28:M32) -> -179.62 | N33: 0 | O33: 0 | P33: 0 | Q33: 0 | R33: 0 | S33: 0 | T33: 0
B34: Net Cash used in Investing activities | J34: -521.42 | K34: =SUM(K28:K33) -> -547.79 | L34: =SUM(L28:L33) -> -321.69 | M34: -1274.64 | N34: =SUM(N28:N33) -> -2517.63 | O34: =SUM(O28:O33) -> -874.12 | P34: =SUM(P28:P33) -> -1334.07 | Q34: =SUM(Q28:Q33) -> -940.97977 | R34: =SUM(R28:R33) -> -997.00876 | S34: =SUM(S28:S33) -> -1055.2087 | T34: =SUM(T28:T33) -> -1115.311
B36: (C) CASH FLOW FROM FINANCING ACTIVITIES
B37: Net Proceeds from Long-term Borrowings | J37: =17.91-10.49 -> 7.42 | K37: =2.14-14.21 -> -12.07 | L37: =39.87-7.89 -> 31.98 | M37: =94-15.55 -> 78.45 | N37: =5.91-14.17 -> -8.26 | O37: =219.84-21.16 -> 198.68 | P37: =993.41-32.43 -> 960.98 | Q37: =AVERAGE(J37:P37) -> 179.59714 | R37: =AVERAGE(K37:Q37) -> 204.19388 | S37: =AVERAGE(L37:R37) -> 235.08872 | T37: =AVERAGE(M37:S37) -> 264.10425
B38: Proceeds from / (Repayment of) short term borrowings (net) | J38: -268.79 | K38: 37.78 | L38: 292.68 | M38: 159.76 | N38: 94.98 | O38: -406.41 | P38: 285.44 | Q38: =MEDIAN(J38:P38) -> 94.98 | R38: =MEDIAN(K38:Q38) -> 94.98 | S38: =MEDIAN(L38:R38) -> 94.98 | T38: =MEDIAN(M38:S38) -> 94.98
B39: Finance costs (including interest on lease liabilities) paid | J39: -100.89 | K39: -89.31 | L39: -93.56 | M39: -141.95 | N39: -190.57 | O39: -203.19 | P39: -228.33 | Q39: =-SUM(Schedule!M58:M61) -> -202.25057 | R39: =-SUM(Schedule!N58:N61) -> -217.19183 | S39: =-SUM(Schedule!O58:O61) -> -233.23686 | T39: =-SUM(Schedule!P58:P61) -> -250.46723
B40: Dividend paid (including dividend paid to non-controlling shareholders) | J40: -2120.71 | K40: -499.35 | L40: -1762.8 | M40: -1936.05 | N40: -2550.88 | O40: -3140.21 | P40: -2425.38 | Q40: =MEDIAN(J40:P40) -> -2120.71 | R40: =MEDIAN(K40:Q40) -> -2120.71 | S40: =MEDIAN(L40:R40) -> -2120.71 | T40: =MEDIAN(M40:S40) -> -2120.71
B41: Other | J41: =J42-SUM(J37:J40) -> -388.49 | K41: =K42-SUM(K37:K40) -> -87.45 | L41: =L42-SUM(L37:L40) -> -275.91 | M41: =M42-SUM(M37:M40) -> -300.26 | N41: =N42-SUM(N37:N40) -> -327.77 | O41: =O42-SUM(O37:O40) -> -201.45 | P41: =P42-SUM(P37:P40) -> -969.22 | Q41: =P41*(1+((P41/J41)^(1/6)-1)) -> -1128.7457 | R41: =Q41*(1+((Q41/K41)^(1/6)-1)) -> -1728.7632 | S41: =R41*(1+((R41/L41)^(1/6)-1)) -> -2347.2725 | T41: =S41*(1+((S41/M41)^(1/6)-1)) -> -3306.7994
B42: Net Cash used in Financing activities | J42: -2871.46 | K42: -650.4 | L42: -1807.61 | M42: -2140.05 | N42: -2982.5 | O42: -3752.58 | P42: =-2376.51 -> -2376.51 | Q42: =SUM(Q37:Q41) -> -3177.1292 | R42: =SUM(R37:R41) -> -3767.4911 | S42: =SUM(S37:S41) -> -4371.1507 | T42: =SUM(T37:T41) -> -5318.8924
B43: (D) NET INCREASE / (DECREASE) IN CASH AND CASH EQUIVALENTS [A+B+C] | J43: =J25+J34+J42 -> -354.73 | K43: =K25+K34+K42 -> 2485.16 | L43: =L25+L34+L42 -> -1142.81 | M43: =M25+M34+M42 -> 778.74 | N43: =N25+N34+N42 -> 603.47 | O43: =O25+O34+O42 -> -202.74 | P43: =P25+P34+P42 -> 3377.6 | Q43: =Q25+Q34+Q42 -> 1137.973 | ... T43: =T25+T34+T42 -> -772.29109
B44: Add : Cash and cash equivalents as at 1st April | J44: 1279.97 | K44: 928.75 | L44: 3421.16 | M44: 2283.29 | N44: 3054.33 | O44: 3626.95 | P44: 3357.42 | Q44: =P46 -> 6740.86 | R44: =Q46 -> 7878.833 | S44: =R46 -> 8618.5271 | T44: =S46 -> 8857.509
B45: Net effect of exchange gain/(loss) on cash and cash equivalents | J45: 3.51 | K45: 7.25 | L45: 4.94 | M45: -7.7 | N45: -30.85 | O45: -66.79 | P45: 5.84 | Q45: 0 | R45: 0 | S45: 0 | T45: 0
B46: Cash and cash equivalents as at 31st March | J46: =SUM(J43:J45) -> 928.75 | K46: =SUM(K43:K45) -> 3421.16 | L46: =SUM(L43:L45) -> 2283.29 | M46: =SUM(M43:M45) -> 3054.33 | N46: =SUM(N43:N45) -> 3626.95 | O46: =SUM(O43:O45) -> 3357.42 | P46: =SUM(P43:P45) -> 6740.86 | Q46: =SUM(Q43:Q45) -> 7878.833 | ... T46: =SUM(T43:T45) -> 8085.2179
B49: CASH AND CASH EQUIVALENTS
B50: (in ₹ Cr. unless stated otherwise)
J51: Historical | Q51: Forecasts
B52: Years | J52: =K52-1 -> 20 | K52: 21 | L52: =K52+1 -> 22 | M52: =L52+1 -> 23 | N52: =M52+1 -> 24 | O52: =N52+1 -> 25 | P52: =O52+1 -> 26 | Q52: =P52+1 -> 27 | R52: =Q52+1 -> 28 | S52: =R52+1 -> 29 | T52: =S52+1 -> 30
B54: Cash And Cash Equivalents | J54: ='SOFP '!I28 -> 563.83 | K54: ='SOFP '!J28 -> 346.39 | L54: ='SOFP '!K28 -> 621.72 | M54: ='SOFP '!L28 -> 523.1 | N54: ='SOFP '!M28 -> 829.34 | O54: ='SOFP '!N28 -> 445.28 | P54: ='SOFP '!O28 -> 672.83 | Q54: =Q64 -> 635.78825 | R54: =R64 -> 780.74675 | S54: =S64 -> 894.29715 | T54: =T64 -> 975.35534
B55: Market Securities/Liquid Investments | J55: =J56-J54 -> 364.92 | K55: =K56-K54 -> 3074.77 | L55: =L56-L54 -> 1661.57 | M55: =M56-M54 -> 2531.23 | N55: =N56-N54 -> 2797.61 | O55: =O56-O54 -> 2912.14 | P55: =P56-P54 -> 6068.03 | Q55: =Q56-Q54 -> 7243.0448 | ... T55: =T56-T54 -> 7109.8626
B56: Cash and cash equivalents in Cash Flow Statement | J56: =J46 -> 928.75 | K56: =K46 -> 3421.16 | L56: =L46 -> 2283.29 | M56: =M46 -> 3054.33 | N56: =N46 -> 3626.95 | O56: =O46 -> 3357.42 | P56: =P46 -> 6740.86 | Q56: =Q46 -> 7878.833 | ... T56: =T46 -> 8085.2179
B59: CASH AND CASH EQUIVALENTS & OTHER BALANCES WITH BANK
B60: (in ₹ Cr. unless stated otherwise)
J61: Historical | Q61: Forecasts
B62: Years | J62: =K62-1 -> 20 | K62: 21 | L62: =K62+1 -> 22 | M62: =L62+1 -> 23 | N62: =M62+1 -> 24 | O62: =N62+1 -> 25 | P62: =O62+1 -> 26 | Q62: =P62+1 -> 27 | R62: =Q62+1 -> 28 | S62: =R62+1 -> 29 | T62: =S62+1 -> 30
B64: Cash And Cash Equivalents | J64: =J54 -> 563.83 | K64: =K54 -> 346.39 | L64: =L54 -> 621.72 | M64: =M54 -> 523.1 | N64: =N54 -> 829.34 | O64: =O54 -> 445.28 | P64: =P54 -> 672.83 | Q64: =Q66*R78 -> 635.78825 | R64: =R66*S78 -> 780.74675 | S64: =S66*T78 -> 894.29715 | T64: =T66*U78 -> 975.35534
B65: Other Balances with Bank | J65: ='SOFP '!I29 -> 219 | K65: ='SOFP '!J29 -> 264.36 | L65: ='SOFP '!K29 -> 242.61 | M65: ='SOFP '!L29 -> 320.72 | N65: ='SOFP '!M29 -> 254.67 | O65: ='SOFP '!N29 -> 336.7 | P65: ='SOFP '!O29 -> 400.85 | Q65: =Q66-Q64 -> 378.78175 | R65: =R66-R64 -> 465.14325 | S65: =S66-S64 -> 532.79285 | T65: =T66-T64 -> 581.08466
I66: Total | J66: =SUM(J64:J65) -> 782.83 | K66: =SUM(K64:K65) -> 610.75 | L66: =SUM(L64:L65) -> 864.33 | M66: =SUM(M64:M65) -> 843.82 | N66: =SUM(N64:N65) -> 1084.01 | O66: =SUM(O64:O65) -> 781.98 | P66: =SUM(P64:P65) -> 1073.68 | Q66: 1014.57 | R66: 1245.89 | S66: 1427.09 | T66: 1556.44
B69: FORECAST ASSUMPTIONS & BASIS
B71: Years | J71: =K71-1 -> 20 | K71: 21 | L71: =K71+1 -> 22 | M71: =L71+1 -> 23 | N71: =M71+1 -> 24 | O71: =N71+1 -> 25 | P71: =O71+1 -> 26 | Q71: Basis | R71: =P71+1 -> 27 | S71: =R71+1 -> 28 | T71: =S71+1 -> 29 | U71: =T71+1 -> 30
B73: Other* Growth % | J73: 0 | K73: =K20/J20-1 -> 1.3461109 | L73: =L20/K20-1 -> -0.34438452 | M73: =M20/L20-1 -> -0.11242842 | N73: =N20/M20-1 -> 2.1289414 | O73: =O20/N20-1 -> -0.85679851 | P73: =P20/O20-1 -> 2.4414926 | Q73: =AVERAGE(J73:P73) -> 0.65756192 | R73: =Q73 -> 0.65756192 | S73: =R73 -> 0.65756192 | T73: =S73 -> 0.65756192 | U73: =T73 -> 0.65756192
B74: Payment for acquiring right-of-use assets Growth % | J74: 0 | K74: =K29/J29-1 -> -0.32610837 | L74: =L29/K29-1 -> 0.82163743 | M74: =M29/L29-1 -> 12.823435 | N74: =N29/M29-1 -> 0.72474454 | O74: =O29/N29-1 -> -0.9166863 | P74: =P29/O29-1 -> -0.17979798 | Q74: =(P29/J29)^(1/6)-1 -> 0.12246205 | R74: =Q74 -> 0.12246205 | S74: =R74 -> 0.12246205 | T74: =S74 -> 0.12246205 | U74: =T74 -> 0.12246205
B75: Incremental Working Capital as % of Revenue | J75: =SOCF!J22/SOPL!I13 -> -0.016369101 | K75: =SOCF!K22/SOPL!J13 -> -0.0095086813 | L75: =SOCF!L22/SOPL!K13 -> -0.096051445 | M75: =SOCF!M22/SOPL!L13 -> -0.022387404 | N75: =SOCF!N22/SOPL!M13 -> 0.00028314062 | O75: =SOCF!O22/SOPL!N13 -> -0.016816681 | P75: =SOCF!P22/SOPL!O13 -> 0.041471984 | Q75: =MEDIAN(J75:P75) -> -0.016369101 | R75: =Q75 -> -0.016369101 | S75: =R75 -> -0.016369101 | T75: =S75 -> -0.016369101 | U75: =T75 -> -0.016369101
B76: Tax Expense/Income Tax paid (net of refund) | J76: =-SOPL!I29/SOCF!J24 -> 0.8457581 | K76: =-SOPL!J29/SOCF!K24 -> 1.0165598 | L76: =-SOPL!K29/SOCF!L24 -> 0.93809593 | M76: =-SOPL!L29/SOCF!M24 -> 0.99947801 | N76: =-SOPL!M29/SOCF!N24 -> 0.97549386 | O76: =-SOPL!N29/SOCF!O24 -> 0.99845219 | P76: =-SOPL!O29/SOCF!P24 -> 1.0221944 | Q76: =MEDIAN(J76:P76) -> 0.99845219 | R76: =Q76 -> 0.99845219 | S76: =R76 -> 0.99845219 | T76: =S76 -> 0.99845219 | U76: =T76 -> 0.99845219
B77: Interest and Dividends as % of Other Non-Operating Income | J77: =SOCF!J32/SOPL!I19 -> 0.30380204 | K77: =SOCF!K32/SOPL!J19 -> 0.26781059 | L77: =SOCF!L32/SOPL!K19 -> 0.24249362 | M77: =SOCF!M32/SOPL!L19 -> 0.37106707 | N77: =SOCF!N32/SOPL!M19 -> 0.38378685 | O77: =SOCF!O32/SOPL!N19 -> 0.50825169 | P77: =SOCF!P32/SOPL!O19 -> 0.37416413 | Q77: =MEDIAN(J77:P77) -> 0.37106707 | R77: =Q77 -> 0.37106707 | S77: =R77 -> 0.37106707 | T77: =S77 -> 0.37106707 | U77: =T77 -> 0.37106707
B78: Proportion of Cash & Cash Equivalents to Other Balances with Bank | J78: =J64/J66 -> 0.72024577 | K78: =K64/K66 -> 0.56715514 | L78: =L64/L66 -> 0.7193086 | M78: =M64/M66 -> 0.61991894 | N78: =N64/N66 -> 0.76506674 | O78: =O64/O66 -> 0.56942633 | P78: =P64/P66 -> 0.62665785 | Q78: =MEDIAN(J78:P78) -> 0.62665785 | R78: =Q78 -> 0.62665785 | S78: =R78 -> 0.62665785 | T78: =S78 -> 0.62665785 | U78: =T78 -> 0.62665785

Sheet Schedule
C2: NSE: ASIANPAINT | BSE:500820
C3: 52-WEEK (HIGH: ₹ 2985.70| LOW: ₹ 2115.00 ) | R3: SUPPORTING SCHEDULES | AJ3: -Basis for Forecasting
C4: 2649.4 | AI4: (B) | AJ4: -Balancing Adjustment
C5: (as at 13 July 2026)
B6: PROPERTY, PLANT & EQUIPMENT
B7: (in ₹ Cr. unless stated otherwise)
C8: Gross Carrying Value | Y8: Gross Carrying Value
B9: Years | C9: =20 -> 20 | F9: =C9+1 -> 21 | I9: =F9+1 -> 22 | L9: =I9+1 -> 23 | O9: =L9+1 -> 24 | R9: =O9+1 -> 25 | U9: =R9+1 -> 26 | X9: Basis | Y9: 27 | AB9: =Y9+1 -> 28 | AE9: =AB9+1 -> 29 | AH9: =AE9+1 -> 30
C10: Opening Balance | D10: Addition/ Adjustments | E10: Gross | F10: =C10 -> Opening Balance | G10: =D10 -> Addition/ Adjustments | H10: =E10 -> Gross | I10: =F10 -> Opening Balance | J10: =G10 -> Addition/ Adjustments | K10: =H10 -> Gross | L10: =I10 -> Opening Balance | M10: =J10 -> Addition/ Adjustments | ... W10: =T10 -> Gross | Y10: Opening Balance | Z10: Addition/ Adjustments | AA10: Gross | AB10: =Y10 -> Opening Balance | AC10: =Z10 -> Addition/ Adjustments | AD10: =AA10 -> Gross | AE10: =AB10 -> Opening Balance | AF10: =AC10 -> Addition/ Adjustments | AG10: =AD10 -> Gross | AH10: =AE10 -> Opening Balance | AI10: =AF10 -> Addition/ Adjustments | AJ10: =AG10 -> Gross
C11: 6302.92 | D11: =30.72+294.98-32.91-28.02 -> 264.77 | E11: =C11+D11 -> 6567.69 | F11: =E11 -> 6567.69 | G11: =263.73-38.22-20.85 -> 204.66 | H11: =F11+G11 -> 6772.35 | I11: =H11 -> 6772.35 | J11: =269.34-22.76-22.07 -> 224.51 | K11: =I11+J11 -> 6996.86 | L11: =K11 -> 6996.86 | M11: =0.92+533.78-20.41-29.37 -> 484.92 | N11: =L11+M11 -> 7481.78 | O11: =N11 -> 7481.78 | P11: =18.69-13.6-21.62+786.65 -> 770.12 | Q11: =O11+P11 -> 8251.9 | R11: =Q11 -> 8251.9 | S11: =3100.17-160.64-59.74-28.71 -> 2851.08 | T11: =R11+S11 -> 11102.98 | U11: =T11 -> 11102.98 | V11: =85.06+1111.01-166.5 -> 1029.57 | W11: =U11+V11 -> 12132.55 | Y11: =W11 -> 12132.55 | Z11: =$X$12*SOPL!P13 -> 983.11539 | AA11: =Y11+Z11 -> 13115.665 | AB11: =AA11 -> 13115.665 | AC11: =X12*SOPL!Q13 -> 1072.9857 | AD11: =AB11+AC11 -> 14188.651 | AE11: =AD11 -> 14188.651 | AF11: =X12*SOPL!R13 -> 1171.1116 | AG11: =AE11+AF11 -> 15359.763 | AH11: =AG11 -> 15359.763 | AI11: =X12*SOPL!S13 -> 1278.2485 | AJ11: =AH11+AI11 -> 16638.011
B12: CapEx as % of Revenue | D12: =D11/SOPL!I$13 -> 0.01310013 | G12: =G11/SOPL!J$13 -> 0.0094257808 | J12: =J11/SOPL!K$13 -> 0.0077147809 | M12: =M11/SOPL!L$13 -> 0.014060302 | P12: =P11/SOPL!M$13 -> 0.021696742 | S12: =S11/SOPL!N$13 -> 0.084088714 | V12: =V11/SOPL!O$13 -> 0.028933883 | X12: =MEDIAN(M12,P12,S12,V12) -> 0.025315313 | Z12: =Z27 -> (CAPEX) | AC12: =AC27 -> (CAPEX) | AF12: =AF27 -> (CAPEX) | AI12: =AI27 -> (CAPEX)
C13: Depreciation | Y13: Depreciation
B14: Years | C14: =20 -> 20 | F14: =C14+1 -> 21 | I14: =F14+1 -> 22 | L14: =I14+1 -> 23 | O14: =L14+1 -> 24 | R14: =O14+1 -> 25 | U14: =R14+1 -> 26 | Y14: =Y9 -> 27 | AB14: =Y14+1 -> 28 | AE14: =AB14+1 -> 29 | AH14: =AE14+1 -> 30
C15: Opening Balance | D15: =D10 -> Addition/ Adjustments | E15: Gross | F15: =C15 -> Opening Balance | G15: =D15 -> Addition/ Adjustments | H15: =E15 -> Gross | I15: =F15 -> Opening Balance | J15: =G15 -> Addition/ Adjustments | K15: =H15 -> Gross | L15: =I15 -> Opening Balance | M15: =J15 -> Addition/ Adjustments | ... W15: =T15 -> Gross | Y15: =Y10 -> Opening Balance | Z15: =Z10 -> Addition/ Adjustments | AA15: =AA10 -> Gross | AB15: =AB10 -> Opening Balance | AC15: =AC10 -> Addition/ Adjustments | AD15: =AD10 -> Gross | AE15: =AE10 -> Opening Balance | AF15: =AF10 -> Addition/ Adjustments | ... AJ15: =AJ10 -> Gross
C16: 1272.48 | D16: =14.07+533.39-7.66-9.35 -> 530.45 | E16: =C16+D16 -> 1802.93 | F16: =E16 -> 1802.93 | G16: =544.45-34.8-16.58 -> 493.07 | H16: =F16+G16 -> 2296 | I16: =H16 -> 2296 | J16: =546.29-12.67-17.22 -> 516.4 | K16: =I16+J16 -> 2812.4 | L16: =K16 -> 2812.4 | M16: =551.5-4.08-23.69 -> 523.73 | N16: =L16+M16 -> 3336.13 | O16: =N16 -> 3336.13 | P16: =8.09+483.64-18.57-3.59 -> 469.57 | Q16: =O16+P16 -> 3805.7 | R16: =Q16 -> 3805.7 | S16: =617.08-11-53-43.42 -> 509.66 | T16: =R16+S16 -> 4315.36 | U16: =T16 -> 4315.36 | V16: =21.13+809.32-159.49 -> 670.96 | W16: =U16+V16 -> 4986.32 | Y16: =W16 -> 4986.32 | Z16: =$X$17*(Y11+Z11-Y16) -> 806.60043 | AA16: =Y16+Z16 -> 5792.9204 | AB16: =AA16 -> 5792.9204 | AC16: =X17*(AB11+AC11-AB16) -> 833.03141 | AD16: =AB16+AC16 -> 6625.9518 | AE16: =AD16 -> 6625.9518 | AF16: =X17*(AE11+AF11-AE16) -> 866.576 | AG16: =AE16+AF16 -> 7492.5278 | AH16: =AG16 -> 7492.5278 | AI16: =X17*(AH11+AI11-AH16) -> 907.42249 | AJ16: =AH16+AI16 -> 8399.9503
B17: Depreciation % | E17: =D16/(C11+D11-C16) -> 0.10017544 | H17: =G16/(F11+G11-F16) -> 0.099220835 | K17: =J16/(I11+J11-I16) -> 0.10985224 | N17: =M16/(L11+M11-L16) -> 0.11216264 | Q17: =P16/(O11+P11-O16) -> 0.095523184 | T17: =S16/(R11+S11-R16) -> 0.069842462 | W17: =V16/(U11+V11-U16) -> 0.085831354 | X17: =MEDIAN(N17,E17,H17,K17,Q17,T17,W17) -> 0.099220835 | Z17: (Depreciation) | AC17: =Z17 -> (Depreciation) | AF17: =AC17 -> (Depreciation) | AI17: =AF17 -> (Depreciation)
B18: Year-end Carrying Value | E18: =E11-E16 -> 4764.76 | H18: =H11-H16 -> 4476.35 | K18: =K11-K16 -> 4184.46 | N18: =N11-N16 -> 4145.65 | Q18: =Q11-Q16 -> 4446.2 | T18: =T11-T16 -> 6787.62 | W18: =W11-W16 -> 7146.23 | AA18: =AA11-AA16 -> 7322.745 | AD18: =AD11-AD16 -> 7562.6993 | AG18: =AG11-AG16 -> 7867.2348 | AJ18: =AJ11-AJ16 -> 8238.0609
B21: GOODWILL & INTANGIBLE ASSETS
B22: (in ₹ Cr. unless stated otherwise)
C23: Gross Carrying Value | Y23: Gross Carrying Value
B24: Years | C24: =20 -> 20 | F24: =C24+1 -> 21 | I24: =F24+1 -> 22 | L24: =I24+1 -> 23 | O24: =L24+1 -> 24 | R24: =O24+1 -> 25 | U24: =R24+1 -> 26 | X24: Basis | Y24: 27 | AB24: =Y24+1 -> 28 | AE24: =AB24+1 -> 29 | AH24: =AE24+1 -> 30
C25: Opening Balance | D25: Addition/ Adjustments | E25: Gross | F25: =C25 -> Opening Balance | G25: =D25 -> Addition/ Adjustments | H25: =E25 -> Gross | I25: =F25 -> Opening Balance | J25: =G25 -> Addition/ Adjustments | K25: =H25 -> Gross | L25: =I25 -> Opening Balance | M25: =J25 -> Addition/ Adjustments | ... W25: =T25 -> Gross | Y25: Opening Balance | Z25: Addition/ Adjustments | AA25: Gross | AB25: =Y25 -> Opening Balance | AC25: =Z25 -> Addition/ Adjustments | AD25: =AA25 -> Gross | AE25: =AB25 -> Opening Balance | AF25: =AC25 -> Addition/ Adjustments | AG25: =AD25 -> Gross | AH25: =AE25 -> Opening Balance | AI25: =AF25 -> Addition/ Adjustments | AJ25: =AG25 -> Gross
C26: 769.15 | D26: =31.72-2.77-3.69-0.15 -> 25.11 | E26: =C26+D26 -> 794.26 | F26: =E26 -> 794.26 | G26: =15.82-36.13-0.2 -> -20.51 | H26: =F26+G26 -> 773.75 | I26: =H26 -> 773.75 | J26: =24.82-96.76-0.2 -> -72.14 | K26: =I26+J26 -> 701.61 | L26: =K26 -> 701.61 | M26: =12.98+30.48-35.52-1.76 -> 6.18 | N26: =L26+M26 -> 707.79 | O26: =N26 -> 707.79 | P26: =17.87+403.95+37.63 -> 459.45 | Q26: =O26+P26 -> 1167.24 | R26: =Q26 -> 1167.24 | S26: =25.16-25.9-13.57-0.94 -> -15.25 | T26: =R26+S26 -> 1151.99 | U26: =T26 -> 1151.99 | V26: =8.78+5.86-1.45 -> 13.19 | W26: =U26+V26 -> 1165.18 | Y26: =W26 -> 1165.18 | Z26: =X27*SOPL!P13 -> 126.64288 | AA26: =Y26+Z26 -> 1291.8229 | AB26: =AA26 -> 1291.8229 | AC26: =SOPL!Q13*X27 -> 138.21979 | AD26: =AB26+AC26 -> 1430.0427 | AE26: =AD26 -> 1430.0427 | AF26: =SOPL!R13*X27 -> 150.86016 | AG26: =AE26+AF26 -> 1580.9028 | AH26: =AG26 -> 1580.9028 | AI26: =SOPL!S13*X27 -> 164.66132 | AJ26: =AH26+AI26 -> 1745.5641
B27: CapEx as % of Revenue | D27: =D26/SOPL!I$13 -> 0.0012423774 | G27: =G26/SOPL!J$13 -> -0.00094460454 | J27: =J26/SOPL!K$13 -> -0.0024789288 | M27: =M26/SOPL!L$13 -> 0.0001791897 | P27: =P26/SOPL!M$13 -> 0.012944175 | S27: =S26/SOPL!N$13 -> -0.00044977794 | V27: =V26/SOPL!O$13 -> 0.000370677 | X27: =AVERAGE(M27,P27,S27,V27) -> 0.003261066 | Z27: (CAPEX) | AC27: (CAPEX) | AF27: (CAPEX) | AI27: (CAPEX)
C28: Amortisation | Y28: Amortisation
B29: Years | C29: =20 -> 20 | F29: =C29+1 -> 21 | I29: =F29+1 -> 22 | L29: =I29+1 -> 23 | O29: =L29+1 -> 24 | R29: =O29+1 -> 25 | U29: =R29+1 -> 26 | Y29: =Y24 -> 27 | AB29: =Y29+1 -> 28 | AE29: =AB29+1 -> 29 | AH29: =AE29+1 -> 30
C30: Opening Balance | D30: =D25 -> Addition/ Adjustments | E30: Gross | F30: =C30 -> Opening Balance | G30: =D30 -> Addition/ Adjustments | H30: =E30 -> Gross | I30: =F30 -> Opening Balance | J30: =G30 -> Addition/ Adjustments | K30: =H30 -> Gross | L30: =I30 -> Opening Balance | M30: =J30 -> Addition/ Adjustments | ... W30: =T30 -> Gross | Y30: Opening Balance | Z30: =Z25 -> Addition/ Adjustments | AA30: Gross | AB30: =Y30 -> Opening Balance | AC30: =Z30 -> Addition/ Adjustments | AD30: =AA30 -> Gross | AE30: =AB30 -> Opening Balance | AF30: =AC30 -> Addition/ Adjustments | AG30: =AD30 -> Gross | AH30: =AE30 -> Opening Balance | AI30: =AF30 -> Addition/ Adjustments | AJ30: =AG30 -> Gross
C31: 121.7 | D31: =0.27+35.15-2.77 -> 32.65 | E31: =C31+D31 -> 154.35 | F31: =E31 -> 154.35 | G31: =31.66-0.19-1.14 -> 30.33 | H31: =F31+G31 -> 184.68 | I31: =H31 -> 184.68 | J31: =28.83-6.63-0.19 -> 22.01 | K31: =I31+J31 -> 206.69 | L31: =K31 -> 206.69 | M31: =29.09-35.13-0.54 -> -6.58 | N31: =L31+M31 -> 200.11 | O31: =N31 -> 200.11 | P31: =27.34+1.76 -> 29.1 | Q31: =O31+P31 -> 229.21 | R31: =Q31 -> 229.21 | S31: =31.09-13.57-0.8-1.38 -> 15.34 | T31: =R31+S31 -> 244.55 | U31: =T31 -> 244.55 | V31: =1.41+27.04-1.45 -> 27 | W31: =U31+V31 -> 271.55 | Y31: 121.7 | Z31: =X32*(Y26+Z26-Y31) -> 35.207858 | AA31: =Y31+Z31 -> 156.90786 | AB31: =AA31 -> 156.90786 | AC31: =X32*(AB26+AC26-AB31) -> 38.307387 | AD31: =AB31+AC31 -> 195.21525 | AE31: =AD31 -> 195.21525 | AF31: =X32*(AE26+AF26-AE31) -> 41.69399 | AG31: =AE31+AF31 -> 236.90924 | AH31: =AG31 -> 236.90924 | AI31: =X32*(AH26+AI26-AH31) -> 45.393957 | AJ31: =AH31+AI31 -> 282.30319
B32: Amortisation % | E32: =D31/(C26+D26-C31) -> 0.048545855 | H32: =G31/(F26+G26-F31) -> 0.048966742 | K32: =J31/(I26+J26-I31) -> 0.042578299 | N32: =M31/(L26+M26-L31) -> -0.013131112 | Q32: =P31/(O26+P26-O31) -> 0.030089026 | T32: =S31/(R26+S26-R31) -> 0.016623681 | W32: =V31/(U26+V26-U31) -> 0.029327743 | X32: =MEDIAN(N32,E32,H32,K32,Q32,T32,W32) -> 0.030089026 | Z32: (Amortisation) | AC32: (Amortisation) | AF32: (Amortisation) | AI32: (Amortisation)
C33: Impairment | Y33: Impairment
B34: Years | C34: =20 -> 20 | F34: =C34+1 -> 21 | I34: =F34+1 -> 22 | L34: =I34+1 -> 23 | O34: =L34+1 -> 24 | R34: =O34+1 -> 25 | U34: =R34+1 -> 26 | Y34: 27 | AB34: =Y34+1 -> 28 | AE34: =AB34+1 -> 29 | AH34: =AE34+1 -> 30
C35: Opening Balance | D35: =D30 -> Addition/ Adjustments | E35: Gross | F35: =C35 -> Opening Balance | G35: =D35 -> Addition/ Adjustments | H35: =E35 -> Gross | I35: =F35 -> Opening Balance | J35: =G35 -> Addition/ Adjustments | K35: =H35 -> Gross | L35: =I35 -> Opening Balance | M35: =J35 -> Addition/ Adjustments | ... W35: =T35 -> Gross | Y35: Opening Balance | Z35: =Z30 -> Addition/ Adjustments | AA35: Gross | AB35: =Y35 -> Opening Balance | AC35: =Z35 -> Addition/ Adjustments | AD35: =AA35 -> Gross | AE35: =AB35 -> Opening Balance | AF35: =AC35 -> Addition/ Adjustments | AG35: =AD35 -> Gross | AH35: =AE35 -> Opening Balance | AI35: =AF35 -> Addition/ Adjustments | AJ35: =AG35 -> Gross
C36: 52.45 | D36: 0 | E36: =C36+D36 -> 52.45 | F36: =E36 -> 52.45 | G36: 0 | H36: =F36 -> 52.45 | I36: =H36 -> 52.45 | J36: =0.15+13.47 -> 13.62 | K36: =I36+J36 -> 66.07 | L36: =K36 -> 66.07 | M36: =1.06+24.66 -> 25.72 | N36: =L36+M36 -> 91.79 | O36: =N36 -> 91.79 | P36: =1.4+0.68 -> 2.08 | Q36: =O36+P36 -> 93.87 | R36: =Q36 -> 93.87 | S36: =1.55+223.25 -> 224.8 | T36: =R36+S36 -> 318.67 | U36: =T36 -> 318.67 | V36: =5.8+93.87 -> 99.67 | W36: =U36+V36 -> 418.34 | X36: =MEDIAN(J36,M36,P36,S36,V36) -> 25.72 | Y36: =W36 -> 418.34 | Z36: =X36 -> 25.72 | AA36: =Y36+Z36 -> 444.06 | AB36: =AA36 -> 444.06 | AC36: =Z36 -> 25.72 | AD36: =AB36+AC36 -> 469.78 | AE36: =AD36 -> 469.78 | AF36: =AC36 -> 25.72 | AG36: =AE36+AF36 -> 495.5 | AH36: =AG36 -> 495.5 | AI36: =AF36 -> 25.72 | AJ36: =AH36+AI36 -> 521.22
B37: Year-end Carrying Value | E37: =E26-E31-E36 -> 587.46 | H37: =H26-H31-H36 -> 536.62 | K37: =K26-K31-K36 -> 428.85 | N37: =N26-N31-N36 -> 415.89 | Q37: =Q26-Q31-Q36 -> 844.16 | T37: =T26-T31-T36 -> 588.77 | W37: =W26-W31-W36 -> 475.29 | AA37: =AA26-AA31-AA36 -> 690.85502 | AD37: =AD26-AD31-AD36 -> 765.04743 | AG37: =AG26-AG31-AG36 -> 848.49359 | AJ37: =AJ26-AJ31-AJ36 -> 942.04096
B40: RIGHT-OF-USE ASSET | V40: DEPRECIATION & AMORTISATION EXPENSE
B41: (in ₹ Cr. unless stated otherwise) | V41: (in ₹ Cr. unless stated otherwise)
B42: Years | F42: =G42-1 -> 20 | G42: 21 | H42: =G42+1 -> 22 | I42: =H42+1 -> 23 | J42: =I42+1 -> 24 | K42: =J42+1 -> 25 | L42: =K42+1 -> 26 | M42: =L42+1 -> 27 | N42: =M42+1 -> 28 | O42: =N42+1 -> 29 | P42: =O42+1 -> 30 | V42: Years | Z42: =AA42-1 -> 20 | AA42: 21 | AB42: =AA42+1 -> 22 | AC42: =AB42+1 -> 23 | AD42: =AC42+1 -> 24 | AE42: =AD42+1 -> 25 | AF42: =AE42+1 -> 26 | AG42: =AF42+1 -> 27 | AH42: =AG42+1 -> 28 | AI42: =AH42+1 -> 29 | AJ42: =AI42+1 -> 30
B44: Balance at 1st April | F44: 871.12 | G44: =F47 -> 920.09 | H44: =G47 -> 845.55 | I44: =H47 -> 905.75 | J44: =I47 -> 1208.92 | K44: =J47 -> 1856.27 | L44: =K47 -> 1843.72 | M44: =L47 -> 2018.77 | N44: =M47 -> 2162.4989 | ... P44: =O47 -> 2481.3841 | V44: Depreciation of Property, Plant and Equipment | Z44: 532.43 | AA44: 544.45 | AB44: 546.29 | AC44: 551.5 | AD44: 483.64 | AE44: 617.08 | AF44: 809.32 | AG44: =Z16 -> 806.60043 | AH44: =AC16 -> 833.03141 | AI44: =AF16 -> 866.576 | AJ44: =AI16 -> 907.42249
B45: Net Additions | F45: =302.19+2.96-9.35-33.43 -> 262.37 | G45: =222.48+1.17-83.03 -> 140.62 | H45: =346.17-42.13-2.6 -> 301.44 | I45: =613.58-2.67-30.31 -> 580.6 | J45: =1011.35+34.4-51.71-0.57 -> 993.47 | K45: =439.68+0-58.34-0.19-8.21 -> 372.94 | L45: =607.89+21.59-53.89 -> 575.59 | M45: =M47-M44+M46 -> 639.99171 | N45: =N47-N44+N46 -> 685.55673 | O45: =O47-O44+O46 -> 734.36581 | P45: =P47-P44+P46 -> 786.64991 | V45: Depreciation of Right-of-Use assets (net) | Z45: 212.91 | AA45: 215.16 | AB45: 241.24 | AC45: 277.43 | AD45: 342.02 | AE45: 378.17 | AF45: 392.49 | AG45: =M46 -> 496.26283 | AH45: =N46 -> 531.59489 | AI45: =O46 -> 569.44246 | AJ45: =P46 -> 609.98464
B46: Depreciation | F46: 213.4 | G46: 215.16 | H46: 241.24 | I46: 277.43 | J46: 346.12 | K46: 385.49 | L46: 400.54 | M46: =M47*$M$50 -> 496.26283 | N46: =N47*$M$50 -> 531.59489 | O46: =O47*$M$50 -> 569.44246 | P46: =P47*$M$50 -> 609.98464 | V46: Amortisation of Other Intangible assets (net) | Z46: 35.16 | AA46: 31.66 | AB46: 28.83 | AC46: 29.09 | AD46: 27.34 | AE46: 31.09 | AF46: 27.04 | AG46: =Z31 -> 35.207858 | AH46: =AC31 -> 38.307387 | AI46: =AF31 -> 41.69399 | AJ46: =AI31 -> 45.393957
B47: Balance at 31st March | F47: =F44+F45-F46 -> 920.09 | G47: =G44+G45-G46 -> 845.55 | H47: =H44+H45-H46 -> 905.75 | I47: =I44+I45-I46 -> 1208.92 | J47: =J44+J45-J46 -> 1856.27 | K47: =K44+K45-K46 -> 1843.72 | L47: =L44+L45-L46 -> 2018.77 | M47: =L47*(1+$M$51) -> 2162.4989 | N47: =M47*(1+$M$51) -> 2316.4607 | O47: =N47*(1+$M$51) -> 2481.3841 | P47: =O47*(1+$M$51) -> 2658.0493 | V47: Total (A) | Z47: =SUM(Z44:Z46) -> 780.5 | AA47: =SUM(AA44:AA46) -> 791.27 | AB47: =SUM(AB44:AB46) -> 816.36 | AC47: =SUM(AC44:AC46) -> 858.02 | AD47: =SUM(AD44:AD46) -> 853 | AE47: =SUM(AE44:AE46) -> 1026.34 | AF47: =SUM(AF44:AF46) -> 1228.85 | AG47: =SUM(AG44:AG46) -> 1338.0711 | ... AJ47: =SUM(AJ44:AJ46) -> 1562.8011
B49: Depreciation % | F49: =F46/(F44+F45) -> 0.18826809 | G49: =G46/(G44+G45) -> 0.20284526 | H49: =H46/(H44+H45) -> 0.21032441 | I49: =I46/(I44+I45) -> 0.18665187 | J49: =J46/(J44+J45) -> 0.15715654 | K49: =K46/(K44+K45) -> 0.17292673 | L49: =L46/(L44+L45) -> 0.1655596 | M49: =MEDIAN(F49:L49) -> 0.18665187 | V49: Proportion of Depreciation of PPE to (A) | Z49: =Z44/Z$47 -> 0.68216528 | AA49: =AA44/AA$47 -> 0.68807108 | AB49: =AB44/AB$47 -> 0.66917781 | AC49: =AC44/AC$47 -> 0.64275891 | AD49: =AD44/AD$47 -> 0.5669871 | AE49: =AE44/AE$47 -> 0.60124325 | AF49: =AF44/AF$47 -> 0.6585995 | AG49: =AVERAGE(Z49:AF49) -> 0.64414328
B50: Depreciation as % of closing balance of ROU Asset | F50: =F46/F47 -> 0.23193383 | G50: =G46/G47 -> 0.25446159 | H50: =H46/H47 -> 0.26634281 | I50: =I46/I47 -> 0.22948582 | J50: =J46/J47 -> 0.18645994 | K50: =K46/K47 -> 0.20908272 | L50: =L46/L47 -> 0.19840794 | M50: =MEDIAN(F50:L50) -> 0.22948582 | V50: Proportion of Depreciation of ROU Assets (net) to (A) | Z50: =Z45/Z$47 -> 0.27278668 | AA50: =AA45/AA$47 -> 0.2719173 | AB50: =AB45/AB$47 -> 0.29550688 | AC50: =AC45/AC$47 -> 0.32333745 | AD50: =AD45/AD$47 -> 0.40096131 | AE50: =AE45/AE$47 -> 0.36846464 | AF50: =AF45/AF$47 -> 0.31939618 | AG50: =AVERAGE(Z50:AF50) -> 0.32176721
B51: Growth % | F51: 0 | G51: =G47/F47-1 -> -0.081013814 | H51: =H47/G47-1 -> 0.071196263 | I51: =I47/H47-1 -> 0.33471709 | J51: =J47/I47-1 -> 0.53547795 | K51: =K47/J47-1 -> -0.0067608699 | L51: =L47/K47-1 -> 0.094943918 | M51: =MEDIAN(F51:L51) -> 0.071196263 | V51: Proportion of Amortisation of Other Intangible assets to (A) | Z51: =Z46/Z$47 -> 0.045048046 | AA51: =AA46/AA$47 -> 0.040011627 | AB51: =AB46/AB$47 -> 0.035315302 | AC51: =AC46/AC$47 -> 0.033903639 | AD51: =AD46/AD$47 -> 0.032051583 | AE51: =AE46/AE$47 -> 0.030292106 | AF51: =AF46/AF$47 -> 0.022004313 | AG51: =AVERAGE(Z51:AF51) -> 0.034089516
AF52: Ʃ | AG52: =SUM(AG49:AG51) -> 1
B54: FINANCE COST
B55: (in ₹ Cr. unless stated otherwise)
B56: Years | F56: =G56-1 -> 20 | G56: 21 | H56: =G56+1 -> 22 | I56: =H56+1 -> 23 | J56: =I56+1 -> 24 | K56: =J56+1 -> 25 | L56: =K56+1 -> 26 | M56: =L56+1 -> 27 | N56: =M56+1 -> 28 | O56: =N56+1 -> 29 | P56: =O56+1 -> 30
B58: Interest on Bank Borrowings | F58: 15.11 | G58: 9.95 | H58: 11.55 | I58: 42.82 | J58: 57.44 | K58: 60.65 | L58: 45.4 | M58: =M$64*$M67 -> 48.753923 | N58: =N$64*$M67 -> 52.355617 | O58: =O$64*$M67 -> 56.223386 | P58: =P$64*$M67 -> 60.376886
B59: Interest on Bill Discounting | F59: 18.98 | G59: 10.75 | H59: 17.74 | I59: 31.51 | J59: 29.91 | K59: 31.56 | L59: 18.8 | M59: =M$64*$M68 -> 30.591661 | N59: =N$64*$M68 -> 32.851618 | O59: =O$64*$M68 -> 35.27853 | P59: =P$64*$M68 -> 37.88473
B60: Interest on Loan from State Government | F60: 1.59 | G60: 2.32 | H60: 1.85 | I60: 1.54 | J60: 4.08 | K60: 3.63 | L60: 3.19 | M60: =M$64*$M69 -> 3.4256611 | N60: =N$64*$M69 -> 3.6787317 | O60: =O$64*$M69 -> 3.9504978 | P60: =P$64*$M69 -> 4.2423407
B61: Interest on Lease Labilities | F61: 64.41 | G61: 57.46 | H61: 56.73 | I61: 64.99 | J61: 89.55 | K61: 108.45 | L61: 111.26 | M61: =M64*M70 -> 119.47933 | N61: =N$64*$M70 -> 128.30586 | O61: =O$64*$M70 -> 137.78445 | P61: =P$64*$M70 -> 147.96327
B62: Other Interest Expense | F62: 2.08 | G62: 2.15 | H62: 6.72 | I62: 1.79 | J62: 21.61 | K62: 22 | L62: 4.56 | M62: =M$64*$M71 -> 4.9238099 | N62: =N$64*$M71 -> 5.2875561 | O62: =O$64*$M71 -> 5.6781741 | P62: =P$64*$M71 -> 6.097649
B63: Interest on Income Tax | F63: 0.16 | G63: 9 | H63: 0.82 | I63: 1.8 | J63: 2.58 | K63: 0.73 | L63: 12.2 | M63: =M$64*$M72 -> 2.6149022 | N63: =N$64*$M72 -> 2.808078 | O63: =O$64*$M72 -> 3.0155247 | P63: =P$64*$M72 -> 3.2382965
B64: Total (B) | F64: 102.3 | G64: 91.63 | H64: =SUM(H58:H63) -> 95.41 | I64: =SUM(I58:I63) -> 144.45 | J64: =SUM(J58:J63) -> 205.17 | K64: =SUM(K58:K63) -> 227.02 | L64: =SUM(L58:L63) -> 195.41 | M64: =L64*(1+$M$65) -> 209.84591 | N64: =M64*(1+$M$65) -> 225.34826 | O64: =N64*(1+$M$65) -> 241.99586 | P64: =O64*(1+$M$65) -> 259.87329
B65: Growth % | F65: 0 | G65: =G64/F64-1 -> -0.10430108 | H65: =H64/G64-1 -> 0.041252865 | I65: =I64/H64-1 -> 0.51399224 | J65: =J64/I64-1 -> 0.42035306 | K65: =K64/J64-1 -> 0.10649705 | L65: =L64/K64-1 -> -0.13923883 | M65: =MEDIAN(G65:L65) -> 0.073874958
B67: Proportion of Interest on Bank Borrowings to (B) | F67: =F58/F$64 -> 0.14770283 | G67: =G58/G$64 -> 0.10858889 | H67: =H58/H$64 -> 0.12105649 | I67: =I58/I$64 -> 0.29643475 | J67: =J58/J$64 -> 0.27996296 | K67: =K58/K$64 -> 0.26715708 | L67: =L58/L$64 -> 0.23233202 | M67: =MEDIAN(F67:L67) -> 0.23233202
B68: Proportion of Interest on Bill Discounting to (B) | F68: =F59/F$64 -> 0.18553275 | G68: =G59/G$64 -> 0.11731966 | H68: =H59/H$64 -> 0.18593439 | I68: =I59/I$64 -> 0.21813776 | J68: =J59/J$64 -> 0.14578155 | K68: =K59/K$64 -> 0.13901859 | L68: =L59/L$64 -> 0.096207973 | M68: =MEDIAN(F68:L68) -> 0.14578155
B69: Proportion of Interest on Loan from State Government to (B) | F69: =F60/F$64 -> 0.015542522 | G69: =G60/G$64 -> 0.025319219 | H69: =H60/H$64 -> 0.019390001 | I69: =I60/I$64 -> 0.010661128 | J69: =J60/J$64 -> 0.019885948 | K69: =K60/K$64 -> 0.015989781 | L69: =L60/L$64 -> 0.016324651 | M69: =MEDIAN(F69:L69) -> 0.016324651
B70: Proportion of Interest on Lease Liabilities to (B) | F70: =F61/F$64 -> 0.62961877 | G70: =G61/G$64 -> 0.6270872 | H70: =H61/H$64 -> 0.59459176 | I70: =I61/I$64 -> 0.44991346 | J70: =J61/J$64 -> 0.43646732 | K70: =K61/K$64 -> 0.47771121 | L70: =L61/L$64 -> 0.56936697 | M70: =MEDIAN(F70:L70) -> 0.56936697
B71: Proportion of Other Interest Expense to (B) | F71: =F62/F$64 -> 0.020332356 | G71: =G62/G$64 -> 0.023463931 | H71: =H62/H$64 -> 0.070432869 | I71: =I62/I$64 -> 0.012391831 | J71: =J62/J$64 -> 0.10532729 | K71: =K62/K$64 -> 0.096907761 | L71: =L62/L$64 -> 0.023335551 | M71: =MEDIAN(F71:L71) -> 0.023463931
B72: Proportion of Interest on Income Tax to (B) | F72: =F63/F$64 -> 0.0015640274 | G72: =G63/G$64 -> 0.098221107 | H72: =H63/H$64 -> 0.008594487 | I72: =I63/I$64 -> 0.012461059 | J72: =J63/J$64 -> 0.012574938 | K72: =K63/K$64 -> 0.0032155757 | L72: =L63/L$64 -> 0.062432834 | M72: =MEDIAN(F72:L72) -> 0.012461059
L73: Ʃ | M73: =ROUND(SUM(M67:M72),0) -> 1

Sheet Ratio Analysis
G2: NSE: ASIANPAINT | BSE:500820
G3: 52-WEEK (HIGH: ₹ 2985.70| LOW: ₹ 2115.00 )
G4: 2649.4
G5: (as at 13 July 2026)
B6: FINANCIAL RATIOS
H8: Historical | S8: Forecasts
B9: Years | I9: =J9-1 -> 20 | J9: 21 | K9: =J9+1 -> 22 | L9: =K9+1 -> 23 | M9: =L9+1 -> 24 | N9: =M9+1 -> 25 | O9: =N9+1 -> 26 | P9: Trend | Q9: Median | R9: Mean | S9: =O9+1 -> 27 | T9: =S9+1 -> 28 | U9: =T9+1 -> 29 | V9: =U9+1 -> 30
B11: Year-end Share Price | I11: 1666.5 | J11: 2537.4 | K11: 3079.95 | L11: 2761.65 | M11: 2846.75 | N11: 2340.65 | O11: 2165.2 | Q11: =MEDIAN(I11:O11) -> 2537.4 | R11: =AVERAGE(I11:O11) -> 2485.4429 | S11: N/A | T11: N/A | U11: N/A | V11: N/A
B13: GROWTH ANALYSIS
B14: Revenue Growth % | I14: 0 | J14: =SOPL!J13/SOPL!I13-1 -> 0.074292288 | K14: =SOPL!K13/SOPL!J13-1 -> 0.34028285 | L14: =SOPL!L13/SOPL!K13-1 -> 0.18512278 | M14: =SOPL!M13/SOPL!L13-1 -> 0.029173127 | N14: =SOPL!N13/SOPL!M13-1 -> -0.044770308 | O14: =SOPL!O13/SOPL!N13-1 -> 0.049487961 | Q14: =MEDIAN(I14:O14) -> 0.049487961 | R14: =AVERAGE(I14:O14) -> 0.090512671 | S14: =SOPL!P13/SOPL!O13-1 -> 0.091370092 | T14: =SOPL!Q13/SOPL!P13-1 -> 0.091413824 | U14: =SOPL!R13/SOPL!Q13-1 -> 0.091451199 | V14: =SOPL!S13/SOPL!R13-1 -> 0.091483139
B15: Cost of Goods Sold (COGS) Growth % | I15: 0 | J15: =SOPL!J17/SOPL!I17-1 -> 0.062702377 | K15: =SOPL!K17/SOPL!J17-1 -> 0.512805 | L15: =SOPL!L17/SOPL!K17-1 -> 0.15604552 | M15: =SOPL!M17/SOPL!L17-1 -> -0.050400113 | N15: =SOPL!N17/SOPL!M17-1 -> -0.028592533 | O15: =SOPL!O17/SOPL!N17-1 -> 0.024902925 | Q15: =MEDIAN(I15:O15) -> 0.024902925 | R15: =AVERAGE(I15:O15) -> 0.096780453 | S15: =SOPL!P17/SOPL!O17-1 -> 0.12984109 | T15: =SOPL!Q17/SOPL!P17-1 -> 0.091413824 | U15: =SOPL!R17/SOPL!Q17-1 -> 0.091451199 | V15: =SOPL!S17/SOPL!R17-1 -> 0.091483139
B16: Earnings Before Interest, Tax, Depreciation & Amortisation (EBITDA) Growth % | I16: 0 | J16: =SOPL!J22/SOPL!I22-1 -> 0.15507335 | K16: =SOPL!K22/SOPL!J22-1 -> 0.0048404137 | L16: =SOPL!L22/SOPL!K22-1 -> 0.28217732 | M16: =SOPL!M22/SOPL!L22-1 -> 0.24473995 | N16: =SOPL!N22/SOPL!M22-1 -> -0.20477847 | O16: =SOPL!O22/SOPL!N22-1 -> 0.12781927 | Q16: =MEDIAN(I16:O16) -> 0.12781927 | R16: =AVERAGE(I16:O16) -> 0.087124548 | S16: =SOPL!P22/SOPL!O22-1 -> 0.063955242 | T16: =SOPL!Q22/SOPL!P22-1 -> 0.082109363 | U16: =SOPL!R22/SOPL!Q22-1 -> 0.081883121 | V16: =SOPL!S22/SOPL!R22-1 -> 0.081646083
B17: Earnings Before Interest & Tax (EBIT) Growth % | I17: 0 | J17: =SOPL!J24/SOPL!I24-1 -> 0.18499124 | K17: =SOPL!K24/SOPL!J24-1 -> -2.7476428e-05 | L17: =SOPL!L24/SOPL!K24-1 -> 0.3253848 | M17: =SOPL!M24/SOPL!L24-1 -> 0.28188587 | N17: =SOPL!N24/SOPL!M24-1 -> -0.25168128 | O17: =SOPL!O24/SOPL!N24-1 -> 0.11497385 | Q17: =MEDIAN(I17:O17) -> 0.11497385 | R17: =AVERAGE(I17:O17) -> 0.093646714 | S17: =SOPL!P24/SOPL!O24-1 -> 0.059007677 | T17: =SOPL!Q24/SOPL!P24-1 -> 0.088973973 | U17: =SOPL!R24/SOPL!Q24-1 -> 0.087499449 | V17: =SOPL!S24/SOPL!R24-1 -> 0.086226175
B18: Earnings Before Tax (EBT) Growth % | I18: 0 | J18: =SOPL!J28/SOPL!I28-1 -> 0.18446941 | K18: =SOPL!K28/SOPL!J28-1 -> -0.027095845 | L18: =SOPL!L28/SOPL!K28-1 -> 0.3584552 | M18: =SOPL!M28/SOPL!L28-1 -> 0.29161357 | N18: =SOPL!N28/SOPL!M28-1 -> -0.30549405 | O18: =SOPL!O28/SOPL!N28-1 -> 0.17643693 | Q18: =MEDIAN(I18:O18) -> 0.17643693 | R18: =AVERAGE(I18:O18) -> 0.096912173 | S18: =SOPL!P28/SOPL!O28-1 -> 0.087562937 | T18: =SOPL!Q28/SOPL!P28-1 -> 0.089875609 | U18: =SOPL!R28/SOPL!Q28-1 -> 0.088394411 | V18: =SOPL!S28/SOPL!R28-1 -> 0.087118793
B19: Profit After Tax (PAT) Growth % | I19: 0 | J19: =SOPL!J31/SOPL!I31-1 -> 0.15592299 | K19: =SOPL!K31/SOPL!J31-1 -> -0.038026039 | L19: =SOPL!L31/SOPL!K31-1 -> 0.35999624 | M19: =SOPL!M31/SOPL!L31-1 -> 0.3247325 | N19: =SOPL!N31/SOPL!M31-1 -> -0.33250865 | O19: =SOPL!O31/SOPL!N31-1 -> 0.18464516 | Q19: =MEDIAN(I19:O19) -> 0.15592299 | R19: =AVERAGE(I19:O19) -> 0.093537457 | S19: =SOPL!P31/SOPL!O31-1 -> 0.087562937 | T19: =SOPL!Q31/SOPL!P31-1 -> 0.089875609 | U19: =SOPL!R31/SOPL!Q31-1 -> 0.088394411 | V19: =SOPL!S31/SOPL!R31-1 -> 0.087118793
B20: Earnings Per Share (EPS) Growth % | I20: 0 | J20: =SOPL!J34/SOPL!I34-1 -> 0.1606383 | K20: =SOPL!K34/SOPL!J34-1 -> -0.034830431 | L20: =SOPL!L34/SOPL!K34-1 -> 0.3558088 | M20: =SOPL!M34/SOPL!L34-1 -> 0.32967546 | N20: =SOPL!N34/SOPL!M34-1 -> -0.32835821 | O20: =SOPL!O34/SOPL!N34-1 -> 0.17960784 | Q20: =MEDIAN(I20:O20) -> 0.1606383 | R20: =AVERAGE(I20:O20) -> 0.094648823 | S20: =SOPL!P34/SOPL!O34-1 -> 0.087581056 | T20: =SOPL!Q34/SOPL!P34-1 -> 0.089875609 | U20: =SOPL!R34/SOPL!Q34-1 -> 0.088394411 | V20: =SOPL!S34/SOPL!R34-1 -> 0.087118793
B21: Dividend Growth % | I21: 0 | J21: =SOPL!J35/SOPL!I35-1 -> 0.48749826 | K21: =SOPL!K35/SOPL!J35-1 -> 0.072720583 | L21: =SOPL!L35/SOPL!K35-1 -> 0.37872683 | M21: =SOPL!M35/SOPL!L35-1 -> 0.26136525 | N21: =SOPL!N35/SOPL!M35-1 -> -0.25525573 | O21: =SOPL!O35/SOPL!N35-1 -> 0.10886956 | Q21: =MEDIAN(I21:O21) -> 0.10886956 | R21: =AVERAGE(I21:O21) -> 0.15056068 | S21: =SOPL!P35/SOPL!O35-1 -> 0.081453509 | T21: =SOPL!Q35/SOPL!P35-1 -> 0.089875609 | U21: =SOPL!R35/SOPL!Q35-1 -> 0.088394411 | V21: =SOPL!S35/SOPL!R35-1 -> 0.087118793
B23: LIQUIDITY RATIOS
B24: Current Ratio | I24: ='SOFP '!I33/('SOFP '!I61-'SOFP '!I60) -> 1.8046463 | J24: ='SOFP '!J33/('SOFP '!J61-'SOFP '!J60) -> 2.0718978 | K24: ='SOFP '!K33/('SOFP '!K61-'SOFP '!K60) -> 2.0364201 | L24: ='SOFP '!L33/('SOFP '!L61-'SOFP '!L60) -> 2.1384696 | M24: ='SOFP '!M33/('SOFP '!M61-'SOFP '!M60) -> 2.0931151 | N24: ='SOFP '!N33/('SOFP '!N61-'SOFP '!N60) -> 2.1199401 | O24: ='SOFP '!O33/('SOFP '!O61-'SOFP '!O60) -> 2.2534995 | Q24: =MEDIAN(I24:O24) -> 2.0931151 | R24: =AVERAGE(I24:O24) -> 2.0739983 | S24: ='SOFP '!P33/('SOFP '!P61-'SOFP '!P60) -> 2.2681859 | T24: ='SOFP '!Q33/('SOFP '!Q61-'SOFP '!Q60) -> 2.3233659 | U24: ='SOFP '!R33/('SOFP '!R61-'SOFP '!R60) -> 2.3716164 | V24: ='SOFP '!S33/('SOFP '!S61-'SOFP '!S60) -> 2.4140517
B25: Quick Ratio | I25: =('SOFP '!I33-'SOFP '!I25-'SOFP '!I32)/('SOFP '!I61-'SOFP '!I60) -> 0.99431235 | J25: =('SOFP '!J33-'SOFP '!J25-'SOFP '!J32)/('SOFP '!J61-'SOFP '!J60) -> 1.4151651 | K25: =('SOFP '!K33-'SOFP '!K25-'SOFP '!K32)/('SOFP '!K61-'SOFP '!K60) -> 1.2083885 | L25: =('SOFP '!L33-'SOFP '!L25-'SOFP '!L32)/('SOFP '!L61-'SOFP '!L60) -> 1.335256 | M25: =('SOFP '!M33-'SOFP '!M25-'SOFP '!M32)/('SOFP '!M61-'SOFP '!M60) -> 1.3861335 | N25: =('SOFP '!N33-'SOFP '!N25-'SOFP '!N32)/('SOFP '!N61-'SOFP '!N60) -> 1.281621 | O25: =('SOFP '!O33-'SOFP '!O25-'SOFP '!O32)/('SOFP '!O61-'SOFP '!O60) -> 1.6122494 | Q25: =MEDIAN(I25:O25) -> 1.335256 | R25: =AVERAGE(I25:O25) -> 1.319018 | S25: =('SOFP '!P33-'SOFP '!P25-'SOFP '!P32)/('SOFP '!P61-'SOFP '!P60) -> 1.5946116 | T25: =('SOFP '!Q33-'SOFP '!Q25-'SOFP '!Q32)/('SOFP '!Q61-'SOFP '!Q60) -> 1.6453153 | U25: =('SOFP '!R33-'SOFP '!R25-'SOFP '!R32)/('SOFP '!R61-'SOFP '!R60) -> 1.689595 | V25: =('SOFP '!S33-'SOFP '!S25-'SOFP '!S32)/('SOFP '!S61-'SOFP '!S60) -> 1.728584
B27: SOLVENCY RATIOS
B28: Financial Gearing Ratio | G28: (D/E) | I28: =('SOFP '!I46+'SOFP '!I47)/'SOFP '!I41 -> 0.057773677 | J28: =('SOFP '!J46+'SOFP '!J47)/'SOFP '!J41 -> 0.043531897 | K28: =('SOFP '!K46+'SOFP '!K47)/'SOFP '!K41 -> 0.045278254 | L28: =('SOFP '!L46+'SOFP '!L47)/'SOFP '!L41 -> 0.048953872 | M28: =('SOFP '!M46+'SOFP '!M47)/'SOFP '!M41 -> 0.059189093 | N28: =('SOFP '!N46+'SOFP '!N47)/'SOFP '!N41 -> 0.068942447 | O28: =('SOFP '!O46+'SOFP '!O47)/'SOFP '!O41 -> 0.11601691 | Q28: =MEDIAN(I28:O28) -> 0.057773677 | R28: =AVERAGE(I28:O28) -> 0.062812308 | S28: =('SOFP '!P46+'SOFP '!P47)/'SOFP '!P41 -> 0.12127383 | T28: =('SOFP '!Q46+'SOFP '!Q47)/'SOFP '!Q41 -> 0.12764326 | U28: =('SOFP '!R46+'SOFP '!R47)/'SOFP '!R41 -> 0.13461807 | V28: =('SOFP '!S46+'SOFP '!S47)/'SOFP '!S41 -> 0.1422629
B29: Interest Cover | I29: =SOPL!I24/SOPL!I27 -> 36.016613 | J29: =SOPL!J24/SOPL!J27 -> 47.663211 | K29: =SOPL!K24/SOPL!K27 -> 45.773609 | L29: =SOPL!L24/SOPL!L27 -> 40.071305 | M29: =SOPL!M24/SOPL!M27 -> 36.164839 | N29: =SOPL!N24/SOPL!N27 -> 24.458109 | O29: =SOPL!O24/SOPL!O27 -> 31.681439 | Q29: =MEDIAN(I29:O29) -> 36.164839 | R29: =AVERAGE(I29:O29) -> 37.404161 | S29: =SOPL!P24/SOPL!P27 -> 31.242825 | T29: =SOPL!Q24/SOPL!Q27 -> 31.682109 | U29: =SOPL!R24/SOPL!R27 -> 32.084067 | V29: =SOPL!S24/SOPL!S27 -> 32.453083
B31: PERFORMANCE RATIOS
B32: Gross Profit Margin % | I32: =SOPL!I18/SOPL!I13 -> 0.43677605 | J32: =SOPL!J18/SOPL!J13 -> 0.44285235 | K32: =SOPL!K18/SOPL!K13 -> 0.37113591 | L32: =SOPL!L18/SOPL!L13 -> 0.38656524 | M32: =SOPL!M18/SOPL!M13 -> 0.43399457 | N32: =SOPL!N18/SOPL!N13 -> 0.4244087 | O32: =SOPL!O18/SOPL!O13 -> 0.43789235 | Q32: =MEDIAN(I32:O32) -> 0.43399457 | R32: =AVERAGE(I32:O32) -> 0.41908931 | S32: =SOPL!P18/SOPL!P13 -> 0.41807795 | T32: =SOPL!Q18/SOPL!Q13 -> 0.41807795 | U32: =SOPL!R18/SOPL!R13 -> 0.41807795 | V32: =SOPL!S18/SOPL!S13 -> 0.41807795
B33: Earnings Before Interest, Tax, Depreciation & Amortisation (EBITDA) Margin % | I33: =SOPL!I22/SOPL!I13 -> 0.22097 | J33: =SOPL!J22/SOPL!J13 -> 0.23758577 | K33: =SOPL!K22/SOPL!K13 -> 0.17812344 | L33: =SOPL!L22/SOPL!L13 -> 0.19271069 | M33: =SOPL!M22/SOPL!M13 -> 0.23307516 | N33: =SOPL!N22/SOPL!N13 -> 0.19403332 | O33: =SOPL!O22/SOPL!O13 -> 0.20851551 | Q33: =MEDIAN(I33:O33) -> 0.20851551 | R33: =AVERAGE(I33:O33) -> 0.2092877 | S33: =SOPL!P22/SOPL!P13 -> 0.20327767 | T33: =SOPL!Q22/SOPL!Q13 -> 0.2015447 | U33: =SOPL!R22/SOPL!R13 -> 0.19977788 | V33: =SOPL!S22/SOPL!S13 -> 0.19797737
B34: Earnings Before Interest & Tax (EBIT) Margin % | I34: =SOPL!I24/SOPL!I13 -> 0.1823529 | J34: =SOPL!J24/SOPL!J13 -> 0.2011432 | K34: =SOPL!K24/SOPL!K13 -> 0.15007106 | L34: =SOPL!L24/SOPL!L13 -> 0.16783232 | M34: =SOPL!M24/SOPL!M13 -> 0.20904343 | N34: =SOPL!N24/SOPL!N13 -> 0.16376282 | O34: =SOPL!O24/SOPL!O13 -> 0.17398128 | Q34: =MEDIAN(I34:O34) -> 0.17398128 | R34: =AVERAGE(I34:O34) -> 0.17831243 | S34: =SOPL!P24/SOPL!P13 -> 0.16882221 | T34: =SOPL!Q24/SOPL!Q13 -> 0.16844481 | U34: =SOPL!R24/SOPL!R13 -> 0.16783494 | V34: =SOPL!S24/SOPL!S13 -> 0.16702658
B35: Earnings Before Tax (EBT) Margin % | I35: =SOPL!I28/SOPL!I13 -> 0.17980036 | J35: =SOPL!J28/SOPL!J13 -> 0.1982403 | K35: =SOPL!K28/SOPL!K13 -> 0.14390157 | L35: =SOPL!L28/SOPL!L13 -> 0.16494818 | M35: =SOPL!M28/SOPL!M13 -> 0.20701017 | N35: =SOPL!N28/SOPL!N13 -> 0.15050809 | O35: =SOPL!O28/SOPL!O13 -> 0.16871396 | Q35: =MEDIAN(I35:O35) -> 0.16871396 | R35: =AVERAGE(I35:O35) -> 0.17330323 | S35: =SOPL!P28/SOPL!P13 -> 0.16812542 | T35: =SOPL!Q28/SOPL!Q13 -> 0.16788846 | U35: =SOPL!R28/SOPL!R13 -> 0.16741827 | V35: =SOPL!S28/SOPL!S13 -> 0.16674884
B36: Profit After Tax (PAT) Margin % | I36: =SOPL!I31/SOPL!I13 -> 0.13725969 | J36: =SOPL!J31/SOPL!J13 -> 0.14768945 | K36: =SOPL!K31/SOPL!K13 -> 0.10600255 | L36: =SOPL!L31/SOPL!L13 -> 0.121644 | M36: =SOPL!M31/SOPL!M13 -> 0.15657789 | N36: =SOPL!N31/SOPL!N13 -> 0.10941283 | O36: =SOPL!O31/SOPL!O13 -> 0.12350345 | Q36: =MEDIAN(I36:O36) -> 0.12350345 | R36: =AVERAGE(I36:O36) -> 0.12886998 | S36: =SOPL!P31/SOPL!P13 -> 0.12307262 | T36: =SOPL!Q31/SOPL!Q13 -> 0.12289916 | U36: =SOPL!R31/SOPL!R13 -> 0.12255496 | V36: =SOPL!S31/SOPL!S13 -> 0.12206492
B37: Return on Capital Employed (ROCE) % | I37: =SOPL!I24*SOPL!I52/('SOFP '!I41-'SOFP '!I40) -> 0.35477083 | J37: =SOPL!J24*SOPL!J52/('SOFP '!J41-'SOFP '!J40) -> 0.33385969 | K37: =SOPL!K24*SOPL!K52/('SOFP '!K41-'SOFP '!K40) -> 0.31064346 | L37: =SOPL!L24*SOPL!L52/('SOFP '!L41-'SOFP '!L40) -> 0.35427656 | M37: =SOPL!M24*SOPL!M52/('SOFP '!M41-'SOFP '!M40) -> 0.38924107 | N37: =SOPL!N24*SOPL!N52/('SOFP '!N41-'SOFP '!N40) -> 0.28293568 | O37: =SOPL!O24*SOPL!O52/('SOFP '!O41-'SOFP '!O40) -> 0.28510699 | Q37: =MEDIAN(I37:O37) -> 0.33385969 | R37: =AVERAGE(I37:O37) -> 0.33011918 | S37: =SOPL!P24*SOPL!P52/('SOFP '!P41-'SOFP '!P40) -> 0.27857809 | T37: =SOPL!Q24*SOPL!Q52/('SOFP '!Q41-'SOFP '!Q40) -> 0.27978024 | U37: =SOPL!R24*SOPL!R52/('SOFP '!R41-'SOFP '!R40) -> 0.28052465 | V37: =SOPL!S24*SOPL!S52/('SOFP '!S41-'SOFP '!S40) -> 0.2808911
B38: Return on Equity (ROE) % | I38: =SOPL!I32/('SOFP '!I38+'SOFP '!I39) -> 0.26704119 | J38: =SOPL!J32/('SOFP '!J38+'SOFP '!J39) -> 0.24513657 | K38: =SOPL!K32/('SOFP '!K38+'SOFP '!K39) -> 0.21942272 | L38: =SOPL!L32/('SOFP '!L38+'SOFP '!L39) -> 0.25677782 | M38: =SOPL!M32/('SOFP '!M38+'SOFP '!M39) -> 0.29154969 | N38: =SOPL!N32/('SOFP '!N38+'SOFP '!N39) -> 0.18903433 | O38: =SOPL!O32/('SOFP '!O38+'SOFP '!O39) -> 0.20238784 | Q38: =MEDIAN(I38:O38) -> 0.24513657 | R38: =AVERAGE(I38:O38) -> 0.23876431 | S38: =SOPL!P32/('SOFP '!P38+'SOFP '!P39) -> 0.20308545 | T38: =SOPL!Q32/('SOFP '!Q38+'SOFP '!Q39) -> 0.2041307 | U38: =SOPL!R32/('SOFP '!R38+'SOFP '!R39) -> 0.20484226 | V38: =SOPL!S32/('SOFP '!S38+'SOFP '!S39) -> 0.2052784
B39: Return on Assets (ROA) % | I39: =SOPL!I31/'SOFP '!I34 -> 0.17172575 | J39: =SOPL!J31/'SOFP '!J34 -> 0.15742807 | K39: =SOPL!K31/'SOFP '!K34 -> 0.13421291 | L39: =SOPL!L31/'SOFP '!L34 -> 0.1626223 | M39: =SOPL!M31/'SOFP '!M34 -> 0.18572628 | N39: =SOPL!N31/'SOFP '!N34 -> 0.12214497 | O39: =SOPL!O31/'SOFP '!O34 -> 0.1272551 | Q39: =MEDIAN(I39:O39) -> 0.15742807 | R39: =AVERAGE(I39:O39) -> 0.15158791 | S39: =SOPL!P31/'SOFP '!P34 -> 0.12644033 | T39: =SOPL!Q31/'SOFP '!Q34 -> 0.12669868 | U39: =SOPL!R31/'SOFP '!R34 -> 0.1266724 | V39: =SOPL!S31/'SOFP '!S34 -> 0.1263915
B41: EFFICIENCY RATIOS
B42: Asset Turnover | I42: =SOPL!I13/'SOFP '!I34 -> 1.2511011 | J42: =SOPL!J13/'SOFP '!J34 -> 1.0659399 | K42: =SOPL!K13/'SOFP '!K34 -> 1.2661291 | L42: =SOPL!L13/'SOFP '!L34 -> 1.3368707 | M42: =SOPL!M13/'SOFP '!M34 -> 1.186159 | N42: =SOPL!N13/'SOFP '!N34 -> 1.1163678 | O42: =SOPL!O13/'SOFP '!O34 -> 1.0303769 | Q42: =MEDIAN(I42:O42) -> 1.186159 | R42: =AVERAGE(I42:O42) -> 1.1789921 | S42: =SOPL!P13/'SOFP '!P34 -> 1.0273636 | T42: =SOPL!Q13/'SOFP '!Q34 -> 1.0309157 | U42: =SOPL!R13/'SOFP '!R34 -> 1.0335967 | V42: =SOPL!S13/'SOFP '!S34 -> 1.0354449
B43: Working Capital Turnover | I43: =SOPL!I13/('SOFP '!I33-'SOFP '!I61) -> 6.3165486 | J43: =SOPL!J13/('SOFP '!J33-'SOFP '!J61) -> 3.559042 | K43: =SOPL!K13/('SOFP '!K33-'SOFP '!K61) -> 3.8384392 | L43: =SOPL!L13/('SOFP '!L33-'SOFP '!L61) -> 3.9920907 | M43: =SOPL!M13/('SOFP '!M33-'SOFP '!M61) -> 3.9281028 | N43: =SOPL!N13/('SOFP '!N33-'SOFP '!N61) -> 3.8309617 | O43: =SOPL!O13/('SOFP '!O33-'SOFP '!O61) -> 3.2209265 | Q43: =MEDIAN(I43:O43) -> 3.8384392 | R43: =AVERAGE(I43:O43) -> 4.0980159 | S43: =SOPL!P13/('SOFP '!P33-'SOFP '!P61) -> 3.1156662 | T43: =SOPL!Q13/('SOFP '!Q33-'SOFP '!Q61) -> 3.0061315 | U43: =SOPL!R13/('SOFP '!R33-'SOFP '!R61) -> 2.9181882 | V43: =SOPL!S13/('SOFP '!S33-'SOFP '!S61) -> 2.8459542
B44: Inventory Turnover | I44: =SOPL!I17/'SOFP '!I25 -> 3.358141 | J44: =SOPL!J17/'SOFP '!J25 -> 3.1846549 | K44: =SOPL!K17/'SOFP '!K25 -> 2.9742905 | L44: =SOPL!L17/'SOFP '!L25 -> 3.4064927 | M44: =SOPL!M17/'SOFP '!M25 -> 3.3916629 | N44: =SOPL!N17/'SOFP '!N25 -> 2.9044494 | O44: =SOPL!O17/'SOFP '!O25 -> 3.482392 | Q44: =MEDIAN(I44:O44) -> 3.358141 | R44: =AVERAGE(I44:O44) -> 3.2431548 | S44: =SOPL!P17/'SOFP '!P25 -> 3.358141 | T44: =SOPL!Q17/'SOFP '!Q25 -> 3.358141 | U44: =SOPL!R17/'SOFP '!R25 -> 3.358141 | V44: =SOPL!S17/'SOFP '!S25 -> 3.358141
B45: Receivables Turnover | I45: =SOPL!I13/'SOFP '!I27 -> 11.258369 | J45: =SOPL!J13/'SOFP '!J27 -> 8.344109 | K45: =SOPL!K13/'SOFP '!K27 -> 7.5169136 | L45: =SOPL!L13/'SOFP '!L27 -> 7.4377909 | M45: =SOPL!M13/'SOFP '!M27 -> 7.2600464 | N45: =SOPL!N13/'SOFP '!N27 -> 7.8600767 | O45: =SOPL!O13/'SOFP '!O27 -> 7.9751535 | Q45: =MEDIAN(I45:O45) -> 7.8600767 | R45: =AVERAGE(I45:O45) -> 8.2360657 | S45: =SOPL!P13/'SOFP '!P27 -> 7.8600767 | T45: =SOPL!Q13/'SOFP '!Q27 -> 7.8600767 | U45: =SOPL!R13/'SOFP '!R27 -> 7.8600767 | V45: =SOPL!S13/'SOFP '!S27 -> 7.8600767
B46: Payables Turnover | I46: =SUM(SOPL!I14:I15)/'SOFP '!I55 -> 5.4398452 | J46: =SUM(SOPL!J14:J15)/'SOFP '!J55 -> 3.6077805 | K46: =SUM(SOPL!K14:K15)/'SOFP '!K55 -> 4.7128497 | L46: =SUM(SOPL!L14:L15)/'SOFP '!L55 -> 5.904713 | M46: =SUM(SOPL!M14:M15)/'SOFP '!M55 -> 5.1486973 | N46: =SUM(SOPL!N14:N15)/'SOFP '!N55 -> 5.1249428 | O46: =SUM(SOPL!O14:O15)/'SOFP '!O55 -> 5.0214598 | Q46: =MEDIAN(I46:O46) -> 5.1249428 | R46: =AVERAGE(I46:O46) -> 4.9943269 | S46: =SUM(SOPL!P14:P15)/'SOFP '!P55 -> 5.1249428 | T46: =SUM(SOPL!Q14:Q15)/'SOFP '!Q55 -> 5.1249428 | U46: =SUM(SOPL!R14:R15)/'SOFP '!R55 -> 5.1249428 | V46: =SUM(SOPL!S14:S15)/'SOFP '!S55 -> 5.1249428
B48: Inventory Holding Period | I48: =$G$52/I44 -> 108.69109 | J48: =$G$52/J44 -> 114.61211 | K48: =$G$52/K44 -> 122.71834 | L48: =$G$52/L44 -> 107.14833 | M48: =$G$52/M44 -> 107.61683 | N48: =$G$52/N44 -> 125.66926 | O48: =$G$52/O44 -> 104.81301 | Q48: =MEDIAN(I48:O48) -> 108.69109 | R48: =AVERAGE(I48:O48) -> 113.03842 | S48: =$G$52/S44 -> 108.69109 | T48: =$G$52/T44 -> 108.69109 | U48: =$G$52/U44 -> 108.69109 | V48: =$G$52/V44 -> 108.69109
B49: Receivables Collection Period | I49: =$G$52/I45 -> 32.420325 | J49: =$G$52/J45 -> 43.743436 | K49: =$G$52/K45 -> 48.557163 | L49: =$G$52/L45 -> 49.073711 | M49: =$G$52/M45 -> 50.275161 | N49: =$G$52/N45 -> 46.437206 | O49: =$G$52/O45 -> 45.767144 | Q49: =MEDIAN(I49:O49) -> 46.437206 | R49: =AVERAGE(I49:O49) -> 45.182021 | S49: =$G$52/S45 -> 46.437206 | T49: =$G$52/T45 -> 46.437206 | U49: =$G$52/U45 -> 46.437206 | V49: =$G$52/V45 -> 46.437206
B50: Payables Payment Period | I50: =$G$52/I46 -> 67.097498 | J50: =$G$52/J46 -> 101.17024 | K50: =$G$52/K46 -> 77.447834 | L50: =$G$52/L46 -> 61.815028 | M50: =$G$52/M46 -> 70.891718 | N50: =$G$52/N46 -> 71.220307 | O50: =$G$52/O46 -> 72.688026 | Q50: =MEDIAN(I50:O50) -> 71.220307 | R50: =AVERAGE(I50:O50) -> 74.618664 | S50: =$G$52/S46 -> 71.220307 | T50: =$G$52/T46 -> 71.220307 | U50: =$G$52/U46 -> 71.220307 | V50: =$G$52/V46 -> 71.220307
B51: Working Capital Cycle | I51: =SUM(I48:I49)-I50 -> 74.013915 | J51: =SUM(J48:J49)-J50 -> 57.185306 | K51: =SUM(K48:K49)-K50 -> 93.827672 | L51: =SUM(L48:L49)-L50 -> 94.407011 | M51: =SUM(M48:M49)-M50 -> 87.000269 | N51: =SUM(N48:N49)-N50 -> 100.88615 | O51: =SUM(O48:O49)-O50 -> 77.892132 | Q51: =MEDIAN(I51:O51) -> 87.000269 | R51: =AVERAGE(I51:O51) -> 83.60178 | S51: =SUM(S48:S49)-S50 -> 83.907987 | T51: =SUM(T48:T49)-T50 -> 83.907987 | U51: =SUM(U48:U49)-U50 -> 83.907987 | V51: =SUM(V48:V49)-V50 -> 83.907987
B52: Days in Period | G52: 365
B54: INVESTOR RATIOS
B55: Earnings Per Share (Basic) | G55: (₹/Share) | I55: =SOPL!I34 -> 28.2 | J55: =SOPL!J34 -> 32.73 | K55: =SOPL!K34 -> 31.59 | L55: =SOPL!L34 -> 42.83 | M55: =SOPL!M34 -> 56.95 | N55: =SOPL!N34 -> 38.25 | O55: =SOPL!O34 -> 45.12 | Q55: =MEDIAN(I55:O55) -> 38.25 | R55: =AVERAGE(I55:O55) -> 39.381429 | S55: =SOPL!P34 -> 49.071657 | T55: =SOPL!Q34 -> 53.482002 | U55: =SOPL!R34 -> 58.209512 | V55: =SOPL!S34 -> 63.280655
B56: Dividend Per Share | G56: (₹/Share) | I56: =SOPL!I35 -> 12.000028 | J56: =SOPL!J35 -> 17.85002 | K56: =SOPL!K35 -> 19.148084 | L56: =SOPL!L35 -> 26.399977 | M56: =SOPL!M35 -> 33.300014 | N56: =SOPL!N35 -> 24.799995 | O56: =SOPL!O35 -> 27.499959 | Q56: =MEDIAN(I56:O56) -> 24.799995 | R56: =AVERAGE(I56:O56) -> 22.999725 | S56: =SOPL!P35 -> 29.739927 | T56: =SOPL!Q35 -> 32.412821 | U56: =SOPL!R35 -> 35.277934 | V56: =SOPL!S35 -> 38.351305
B57: Dividend Payout Ratio | I57: =SOPL!I53 -> 0.42549636 | J57: =SOPL!J53 -> 0.54540039 | K57: =SOPL!K53 -> 0.60605101 | L57: =SOPL!L53 -> 0.61665916 | M57: =SOPL!M53 -> 0.58498085 | N57: =SOPL!N53 -> 0.6486667 | O57: =SOPL!O53 -> 0.60984429 | Q57: =MEDIAN(I57:O57) -> 0.60605101 | R57: =AVERAGE(I57:O57) -> 0.5767284 | S57: =SOPL!P53 -> 0.60605101 | T57: =SOPL!Q53 -> 0.60605101 | U57: =SOPL!R53 -> 0.60605101 | V57: =SOPL!S53 -> 0.60605101
B58: Retention Ratio | I58: =1-I57 -> 0.57450364 | J58: =1-J57 -> 0.45459961 | K58: =1-K57 -> 0.39394899 | L58: =1-L57 -> 0.38334084 | M58: =1-M57 -> 0.41501915 | N58: =1-N57 -> 0.3513333 | O58: =1-O57 -> 0.39015571 | Q58: =MEDIAN(I58:O58) -> 0.39394899 | R58: =AVERAGE(I58:O58) -> 0.4232716 | S58: =1-S57 -> 0.39394899 | T58: =1-T57 -> 0.39394899 | U58: =1-U57 -> 0.39394899 | V58: =1-V57 -> 0.39394899
B59: Dividend Yield | I59: =SOPL!I35/'Ratio Analysis'!I11 -> 0.0072007367 | J59: =SOPL!J35/'Ratio Analysis'!J11 -> 0.007034768 | K59: =SOPL!K35/'Ratio Analysis'!K11 -> 0.0062170114 | L59: =SOPL!L35/'Ratio Analysis'!L11 -> 0.0095594943 | M59: =SOPL!M35/'Ratio Analysis'!M11 -> 0.011697555 | N59: =SOPL!N35/'Ratio Analysis'!N11 -> 0.010595345 | O59: =SOPL!O35/'Ratio Analysis'!O11 -> 0.012700886 | Q59: =MEDIAN(I59:O59) -> 0.0095594943 | R59: =AVERAGE(I59:O59) -> 0.0092865424 | S59: N/A | T59: N/A | U59: N/A | V59: N/A
B60: Earnings Yield | I60: =SOPL!I34/'Ratio Analysis'!I11 -> 0.016921692 | J60: =SOPL!J34/'Ratio Analysis'!J11 -> 0.012899031 | K60: =SOPL!K34/'Ratio Analysis'!K11 -> 0.01025666 | L60: =SOPL!L34/'Ratio Analysis'!L11 -> 0.015508844 | M60: =SOPL!M34/'Ratio Analysis'!M11 -> 0.020005269 | N60: =SOPL!N34/'Ratio Analysis'!N11 -> 0.016341615 | O60: =SOPL!O34/'Ratio Analysis'!O11 -> 0.020838722 | Q60: =MEDIAN(I60:O60) -> 0.016341615 | R60: =AVERAGE(I60:O60) -> 0.016110262 | S60: N/A | T60: N/A | U60: N/A | V60: N/A
B61: P/E Ratio | I61: =I11/SOPL!I34 -> 59.095745 | J61: =J11/SOPL!J34 -> 77.525206 | K61: =K11/SOPL!K34 -> 97.497626 | L61: =L11/SOPL!L34 -> 64.479337 | M61: =M11/SOPL!M34 -> 49.986831 | N61: =N11/SOPL!N34 -> 61.193464 | O61: =O11/SOPL!O34 -> 47.987589 | Q61: =MEDIAN(I61:O61) -> 61.193464 | R61: =AVERAGE(I61:O61) -> 65.395114 | S61: N/A | T61: N/A | U61: N/A | V61: N/A

Sheet Common-Size Analysis
F2: NSE: ASIANPAINT | BSE:500820
F3: 52-WEEK (HIGH: ₹ 2985.70| LOW: ₹ 2115.00 )
F4: 2649.4
F5: (as at 13 July 2026)
B6: COMMON-SIZE CONSOLIDATED STATEMENT OF PROFIT AND LOSS
I8: Historical | P8: Forecasts
B9: Years | I9: =J9-1 -> 20 | J9: 21 | K9: =J9+1 -> 22 | L9: =K9+1 -> 23 | M9: =L9+1 -> 24 | N9: =M9+1 -> 25 | O9: =N9+1 -> 26 | P9: =O9+1 -> 27 | Q9: =P9+1 -> 28 | R9: =Q9+1 -> 29 | S9: =R9+1 -> 30
B11: Revenue from Sale of Products and Services | I11: =SOPL!I11/SOPL!I$13 -> 0.99193865 | J11: =SOPL!J11/SOPL!J$13 -> 0.98951816 | K11: =SOPL!K11/SOPL!K$13 -> 0.9938903 | L11: =SOPL!L11/SOPL!L$13 -> 0.99649855 | M11: =SOPL!M11/SOPL!M$13 -> 0.99682742 | N11: =SOPL!N11/SOPL!N$13 -> 0.99680702 | O11: =SOPL!O11/SOPL!O$13 -> 0.99811233 | P11: =SOPL!P11/SOPL!P$13 -> 0.9983871 | ... S11: =SOPL!S11/SOPL!S$13 -> 0.99899409
B12: Other Operating Revenue | I12: =SOPL!I12/SOPL!I$13 -> 0.008061352 | J12: =SOPL!J12/SOPL!J$13 -> 0.01048184 | K12: =SOPL!K12/SOPL!K$13 -> 0.0061096969 | L12: =SOPL!L12/SOPL!L$13 -> 0.0035014479 | M12: =SOPL!M12/SOPL!M$13 -> 0.0031725836 | N12: =SOPL!N12/SOPL!N$13 -> 0.003192981 | O12: =SOPL!O12/SOPL!O$13 -> 0.0018876705 | P12: =SOPL!P12/SOPL!P$13 -> 0.0016129021 | ... S12: =SOPL!S12/SOPL!S$13 -> 0.0010059092
B13: REVENUE FROM OPERATIONS | I13: =SOPL!I13/SOPL!I$13 -> 1 | J13: =SOPL!J13/SOPL!J$13 -> 1 | K13: =SOPL!K13/SOPL!K$13 -> 1 | L13: =SOPL!L13/SOPL!L$13 -> 1 | M13: =SOPL!M13/SOPL!M$13 -> 1 | N13: =SOPL!N13/SOPL!N$13 -> 1 | O13: =SOPL!O13/SOPL!O$13 -> 1 | P13: =SOPL!P13/SOPL!P$13 -> 1 | ... S13: =SOPL!S13/SOPL!S$13 -> 1
B14: Materials Cost | I14: =SOPL!I14/SOPL!I$13 -> 0.49931499 | J14: =SOPL!J14/SOPL!J$13 -> 0.47516187 | K14: =SOPL!K14/SOPL!K$13 -> 0.55855241 | L14: =SOPL!L14/SOPL!L$13 -> 0.50250184 | M14: =SOPL!M14/SOPL!M$13 -> 0.4470582 | N14: =SOPL!N14/SOPL!N$13 -> 0.46582012 | O14: =SOPL!O14/SOPL!O$13 -> 0.43233613 | P14: =SOPL!P14/SOPL!P$13 -> 0.47516187 | ... S14: =SOPL!S14/SOPL!S$13 -> 0.47516187
B15: Purchases of Stock-in-Trade | I15: =SOPL!I15/SOPL!I$13 -> 0.075741481 | J15: =SOPL!J15/SOPL!J$13 -> 0.086243638 | K15: =SOPL!K15/SOPL!K$13 -> 0.1158413 | L15: =SOPL!L15/SOPL!L$13 -> 0.11991357 | M15: =SOPL!M15/SOPL!M$13 -> 0.10869783 | N15: =SOPL!N15/SOPL!N$13 -> 0.11581738 | O15: =SOPL!O15/SOPL!O$13 -> 0.11280637 | P15: =SOPL!P15/SOPL!P$13 -> 0.11280637 | ... S15: =SOPL!S15/SOPL!S$13 -> 0.11280637
B16: Changes in Inventories | I16: =SOPL!I16/SOPL!I$13 -> -0.011832519 | J16: =SOPL!J16/SOPL!J$13 -> -0.0042578591 | K16: =SOPL!K16/SOPL!K$13 -> -0.045529612 | L16: =SOPL!L16/SOPL!L$13 -> -0.0089806513 | M16: =SOPL!M16/SOPL!M$13 -> 0.010249409 | N16: =SOPL!N16/SOPL!N$13 -> -0.0060461953 | O16: =SOPL!O16/SOPL!O$13 -> 0.016965147 | P16: =SOPL!P16/SOPL!P$13 -> -0.0060461953 | ... S16: =SOPL!S16/SOPL!S$13 -> -0.0060461953
B17: COST OF GOODS SOLD | I17: =SOPL!I17/SOPL!I$13 -> 0.56322395 | J17: =SOPL!J17/SOPL!J$13 -> 0.55714765 | K17: =SOPL!K17/SOPL!K$13 -> 0.62886409 | L17: =SOPL!L17/SOPL!L$13 -> 0.61343476 | M17: =SOPL!M17/SOPL!M$13 -> 0.56600543 | N17: =SOPL!N17/SOPL!N$13 -> 0.5755913 | O17: =SOPL!O17/SOPL!O$13 -> 0.56210765 | P17: =SOPL!P17/SOPL!P$13 -> 0.58192205 | ... S17: =SOPL!S17/SOPL!S$13 -> 0.58192205
B18: GROSS MARGIN | I18: =SOPL!I18/SOPL!I$13 -> 0.43677605 | J18: =SOPL!J18/SOPL!J$13 -> 0.44285235 | K18: =SOPL!K18/SOPL!K$13 -> 0.37113591 | L18: =SOPL!L18/SOPL!L$13 -> 0.38656524 | M18: =SOPL!M18/SOPL!M$13 -> 0.43399457 | N18: =SOPL!N18/SOPL!N$13 -> 0.4244087 | O18: =SOPL!O18/SOPL!O$13 -> 0.43789235 | P18: =SOPL!P18/SOPL!P$13 -> 0.41807795 | ... S18: =SOPL!S18/SOPL!S$13 -> 0.41807795
B19: Other Non-Operating Income | I19: =SOPL!I19/SOPL!I$13 -> 0.015056466 | J19: =SOPL!J19/SOPL!J$13 -> 0.013957211 | K19: =SOPL!K19/SOPL!K$13 -> 0.013058189 | L19: =SOPL!L19/SOPL!L$13 -> 0.011206025 | M19: =SOPL!M19/SOPL!M$13 -> 0.019382032 | N19: =SOPL!N19/SOPL!N$13 -> 0.016888351 | O19: =SOPL!O19/SOPL!O$13 -> 0.020340865 | P19: =SOPL!P19/SOPL!P$13 -> 0.021533491 | ... S19: =SOPL!S19/SOPL!S$13 -> 0.025541995
B20: Employee Benefits Expense | I20: =SOPL!I20/SOPL!I$13 -> 0.067590575 | J20: =SOPL!J20/SOPL!J$13 -> 0.07096048 | K20: =SOPL!K20/SOPL!K$13 -> 0.061394894 | L20: =SOPL!L20/SOPL!L$13 -> 0.058804086 | M20: =SOPL!M20/SOPL!M$13 -> 0.065535926 | N20: =SOPL!N20/SOPL!N$13 -> 0.076601755 | O20: =SOPL!O20/SOPL!O$13 -> 0.078676545 | P20: =SOPL!P20/SOPL!P$13 -> 0.08156826 | ... S20: =SOPL!S20/SOPL!S$13 -> 0.090877063
B21: Other Expenses | I21: =SOPL!I21/SOPL!I$13 -> 0.16327194 | J21: =SOPL!J21/SOPL!J$13 -> 0.1482633 | K21: =SOPL!K21/SOPL!K$13 -> 0.14467577 | L21: =SOPL!L21/SOPL!L$13 -> 0.14625649 | M21: =SOPL!M21/SOPL!M$13 -> 0.15476551 | N21: =SOPL!N21/SOPL!N$13 -> 0.17066197 | O21: =SOPL!O21/SOPL!O$13 -> 0.17104116 | P21: =SOPL!P21/SOPL!P$13 -> 0.15476551 | ... S21: =SOPL!S21/SOPL!S$13 -> 0.15476551
B22: EBITDA | I22: =SOPL!I22/SOPL!I$13 -> 0.22097 | J22: =SOPL!J22/SOPL!J$13 -> 0.23758577 | K22: =SOPL!K22/SOPL!K$13 -> 0.17812344 | L22: =SOPL!L22/SOPL!L$13 -> 0.19271069 | M22: =SOPL!M22/SOPL!M$13 -> 0.23307516 | N22: =SOPL!N22/SOPL!N$13 -> 0.19403332 | O22: =SOPL!O22/SOPL!O$13 -> 0.20851551 | P22: =SOPL!P22/SOPL!P$13 -> 0.20327767 | ... S22: =SOPL!S22/SOPL!S$13 -> 0.19797737
... B31: PROFIT AFTER TAX | I31: =SOPL!I31/SOPL!I$13 -> 0.13725969 | J31: =SOPL!J31/SOPL!J$13 -> 0.14768945 | K31: =SOPL!K31/SOPL!K$13 -> 0.10600255 | L31: =SOPL!L31/SOPL!L$13 -> 0.121644 | M31: =SOPL!M31/SOPL!M$13 -> 0.15657789 | N31: =SOPL!N31/SOPL!N$13 -> 0.10941283 | O31: =SOPL!O31/SOPL!O$13 -> 0.12350345 | P31: =SOPL!P31/SOPL!P$13 -> 0.12307262 | ... S31: =SOPL!S31/SOPL!S$13 -> 0.12206492
B33: COMMON-SIZE CONSOLIDATED STATEMENT OF FINANCIAL POSITION
I35: Historical | P35: Forecasts
B36: Years | I36: =J36-1 -> 20 | J36: 21 | K36: =J36+1 -> 22 | L36: =K36+1 -> 23 | M36: =L36+1 -> 24 | N36: =M36+1 -> 25 | O36: =N36+1 -> 26 | P36: =O36+1 -> 27 | Q36: =P36+1 -> 28 | R36: =Q36+1 -> 29 | S36: =R36+1 -> 30
B38: ASSETS
B39: Non-Current Assets
B40: Property, Plant & Equipment | I40: ='SOFP '!I13/'SOFP '!I$34 -> 0.29494447 | J40: ='SOFP '!J13/'SOFP '!J$34 -> 0.21975619 | K40: ='SOFP '!K13/'SOFP '!K$34 -> 0.18205613 | L40: ='SOFP '!L13/'SOFP '!L$34 -> 0.16069657 | M40: ='SOFP '!M13/'SOFP '!M$34 -> 0.14858263 | N40: ='SOFP '!N13/'SOFP '!N$34 -> 0.22348745 | O40: ='SOFP '!O13/'SOFP '!O$34 -> 0.20693023 | P40: ='SOFP '!P13/'SOFP '!P$34 -> 0.19372108 | ... S40: ='SOFP '!S13/'SOFP '!S$34 -> 0.16893513
B41: Right-of-Use Assets | I41: ='SOFP '!I14/'SOFP '!I$34 -> 0.056954695 | J41: ='SOFP '!J14/'SOFP '!J$34 -> 0.041510347 | K41: ='SOFP '!K14/'SOFP '!K$34 -> 0.039407077 | L41: ='SOFP '!L14/'SOFP '!L$34 -> 0.046860997 | M41: ='SOFP '!M14/'SOFP '!M$34 -> 0.06203263 | N41: ='SOFP '!N14/'SOFP '!N$34 -> 0.060705856 | O41: ='SOFP '!O14/'SOFP '!O$34 -> 0.058456633 | P41: ='SOFP '!P14/'SOFP '!P$34 -> 0.057208276 | ... S41: ='SOFP '!S14/'SOFP '!S$34 -> 0.05450772
B42: Capital work-in-progress | I42: ='SOFP '!I15/'SOFP '!I$34 -> 0.0086810273 | J42: ='SOFP '!J15/'SOFP '!J$34 -> 0.0089829854 | K42: ='SOFP '!K15/'SOFP '!K$34 -> 0.018552978 | L42: ='SOFP '!L15/'SOFP '!L$34 -> 0.039522056 | M42: ='SOFP '!M15/'SOFP '!M$34 -> 0.090173837 | N42: ='SOFP '!N15/'SOFP '!N$34 -> 0.041305019 | O42: ='SOFP '!O15/'SOFP '!O$34 -> 0.053531122 | P42: ='SOFP '!P15/'SOFP '!P$34 -> 0.0488791 | ... S42: ='SOFP '!S15/'SOFP '!S$34 -> 0.042625187
B43: Goodwill and Intangible Assets | I43: ='SOFP '!I16/'SOFP '!I$34 -> 0.036364492 | J43: ='SOFP '!J16/'SOFP '!J$34 -> 0.026344134 | K43: ='SOFP '!K16/'SOFP '!K$34 -> 0.018658267 | L43: ='SOFP '!L16/'SOFP '!L$34 -> 0.016121017 | M43: ='SOFP '!M16/'SOFP '!M$34 -> 0.028209713 | N43: ='SOFP '!N16/'SOFP '!N$34 -> 0.019385362 | O43: ='SOFP '!O16/'SOFP '!O$34 -> 0.013762473 | P43: ='SOFP '!P16/'SOFP '!P$34 -> 0.018276368 | ... S43: ='SOFP '!S16/'SOFP '!S$34 -> 0.019318116
B44: Investment in Associates | I44: ='SOFP '!I17/'SOFP '!I$34 -> 0.028265955 | J44: ='SOFP '!J17/'SOFP '!J$34 -> 0.023755966 | K44: ='SOFP '!K17/'SOFP '!K$34 -> 0.022426902 | L44: ='SOFP '!L17/'SOFP '!L$34 -> 0.030301961 | M44: ='SOFP '!M17/'SOFP '!M$34 -> 0.019486975 | N44: ='SOFP '!N17/'SOFP '!N$34 -> 0.020018853 | O44: ='SOFP '!O17/'SOFP '!O$34 -> 0.018998109 | P44: ='SOFP '!P17/'SOFP '!P$34 -> 0.018413209 | ... S44: ='SOFP '!S17/'SOFP '!S$34 -> 0.017041617
B45: Financial Assets | I45: ='SOFP '!I18/'SOFP '!I$34 -> 0.084835624 | J45: ='SOFP '!J18/'SOFP '!J$34 -> 0.077700517 | K45: ='SOFP '!K18/'SOFP '!K$34 -> 0.045239716 | L45: ='SOFP '!L18/'SOFP '!L$34 -> 0.044512365 | M45: ='SOFP '!M18/'SOFP '!M$34 -> 0.047108199 | N45: ='SOFP '!N18/'SOFP '!N$34 -> 0.057894655 | O45: ='SOFP '!O18/'SOFP '!O$34 -> 0.048199351 | P45: ='SOFP '!P18/'SOFP '!P$34 -> 0.048630634 | ... S45: ='SOFP '!S18/'SOFP '!S$34 -> 0.050773851
B46: Deferred Tax Assets (Net) | I46: ='SOFP '!I19/'SOFP '!I$34 -> 0.0010399405 | J46: ='SOFP '!J19/'SOFP '!J$34 -> 0.00070104401 | K46: ='SOFP '!K19/'SOFP '!K$34 -> 0.0011320697 | L46: ='SOFP '!L19/'SOFP '!L$34 -> 0.00072369951 | M46: ='SOFP '!M19/'SOFP '!M$34 -> 0.00077930524 | N46: ='SOFP '!N19/'SOFP '!N$34 -> 0.00053076302 | O46: ='SOFP '!O19/'SOFP '!O$34 -> 0.00045577624 | P46: ='SOFP '!P19/'SOFP '!P$34 -> 0.00042181452 | ... S46: ='SOFP '!S19/'SOFP '!S$34 -> 0.00033990299
B47: Income Tax Assets (Net) | I47: ='SOFP '!I20/'SOFP '!I$34 -> 0.01566658 | J47: ='SOFP '!J20/'SOFP '!J$34 -> 0.0074733844 | K47: ='SOFP '!K20/'SOFP '!K$34 -> 0.0075033338 | L47: ='SOFP '!L20/'SOFP '!L$34 -> 0.0073463059 | M47: ='SOFP '!M20/'SOFP '!M$34 -> 0.0066204185 | N47: ='SOFP '!N20/'SOFP '!N$34 -> 0.0072970037 | O47: ='SOFP '!O20/'SOFP '!O$34 -> 0.0071991797 | P47: ='SOFP '!P20/'SOFP '!P$34 -> 0.0072277929 | ... S47: ='SOFP '!S20/'SOFP '!S$34 -> 0.0074352865
B48: Other Non-Current Assets | I48: ='SOFP '!I21/'SOFP '!I$34 -> 0.0040291505 | J48: ='SOFP '!J21/'SOFP '!J$34 -> 0.00335696 | K48: ='SOFP '!K21/'SOFP '!K$34 -> 0.0057808649 | L48: ='SOFP '!L21/'SOFP '!L$34 -> 0.012967672 | M48: ='SOFP '!M21/'SOFP '!M$34 -> 0.010954719 | N48: ='SOFP '!N21/'SOFP '!N$34 -> 0.0099113079 | O48: ='SOFP '!O21/'SOFP '!O$34 -> 0.0079894042 | P48: ='SOFP '!P21/'SOFP '!P$34 -> 0.0077300457 | ... S48: ='SOFP '!S21/'SOFP '!S$34 -> 0.0071171975
B49: Total Non-Current Assets | I49: ='SOFP '!I22/'SOFP '!I$34 -> 0.53078193 | J49: ='SOFP '!J22/'SOFP '!J$34 -> 0.40958152 | K49: ='SOFP '!K22/'SOFP '!K$34 -> 0.34075734 | L49: ='SOFP '!L22/'SOFP '!L$34 -> 0.35905264 | M49: ='SOFP '!M22/'SOFP '!M$34 -> 0.41394843 | N49: ='SOFP '!N22/'SOFP '!N$34 -> 0.44053627 | O49: ='SOFP '!O22/'SOFP '!O$34 -> 0.41552228 | P49: ='SOFP '!P22/'SOFP '!P$34 -> 0.40050832 | ... S49: ='SOFP '!S22/'SOFP '!S$34 -> 0.36809401
B51: Current Assets
B52: Inventories | I52: ='SOFP '!I25/'SOFP '!I$34 -> 0.20983338 | J52: ='SOFP '!J25/'SOFP '!J$34 -> 0.1864836 | K52: ='SOFP '!K25/'SOFP '!K$34 -> 0.26770186 | L52: ='SOFP '!L25/'SOFP '!L$34 -> 0.24074114 | M52: ='SOFP '!M25/'SOFP '!M$34 -> 0.19794787 | N52: ='SOFP '!N25/'SOFP '!N$34 -> 0.22123697 | O52: ='SOFP '!O25/'SOFP '!O$34 -> 0.1663175 | P52: ='SOFP '!P25/'SOFP '!P$34 -> 0.17802871 | ... S52: ='SOFP '!S25/'SOFP '!S$34 -> 0.1794291
B53: Financial Assets | I53: ='SOFP '!I26/'SOFP '!I$34 -> 0 | J53: ='SOFP '!J26/'SOFP '!J$34 -> 0 | K53: ='SOFP '!K26/'SOFP '!K$34 -> 0 | L53: ='SOFP '!L26/'SOFP '!L$34 -> 0 | M53: ='SOFP '!M26/'SOFP '!M$34 -> 0 | N53: ='SOFP '!N26/'SOFP '!N$34 -> 0 | O53: ='SOFP '!O26/'SOFP '!O$34 -> 0 | P53: ='SOFP '!P26/'SOFP '!P$34 -> 0 | ... S53: ='SOFP '!S26/'SOFP '!S$34 -> 0
B54: Trade Receivables | I54: ='SOFP '!I27/'SOFP '!I$34 -> 0.11112631 | J54: ='SOFP '!J27/'SOFP '!J$34 -> 0.1277476 | K54: ='SOFP '!K27/'SOFP '!K$34 -> 0.16843736 | L54: ='SOFP '!L27/'SOFP '!L$34 -> 0.17974029 | M54: ='SOFP '!M27/'SOFP '!M$34 -> 0.16338174 | N54: ='SOFP '!N27/'SOFP '!N$34 -> 0.14203014 | O54: ='SOFP '!O27/'SOFP '!O$34 -> 0.12919838 | P54: ='SOFP '!P27/'SOFP '!P$34 -> 0.13070656 | ... S54: ='SOFP '!S27/'SOFP '!S$34 -> 0.1317347
B55: Cash & Cash Equivalents | I55: ='SOFP '!I28/'SOFP '!I$34 -> 0.034901766 | J55: ='SOFP '!J28/'SOFP '!J$34 -> 0.017005226 | K55: ='SOFP '!K28/'SOFP '!K$34 -> 0.027049592 | L55: ='SOFP '!L28/'SOFP '!L$34 -> 0.020276766 | M55: ='SOFP '!M28/'SOFP '!M$34 -> 0.027714794 | N55: ='SOFP '!N28/'SOFP '!N$34 -> 0.014661176 | O55: ='SOFP '!O28/'SOFP '!O$34 -> 0.019482842 | P55: ='SOFP '!P28/'SOFP '!P$34 -> 0.016819593 | ... S55: ='SOFP '!S28/'SOFP '!S$34 -> 0.020001283
B56: Other Balances with Bank | I56: ='SOFP '!I29/'SOFP '!I$34 -> 0.013556368 | J56: ='SOFP '!J29/'SOFP '!J$34 -> 0.012978151 | K56: ='SOFP '!K29/'SOFP '!K$34 -> 0.010555397 | L56: ='SOFP '!L29/'SOFP '!L$34 -> 0.012431971 | M56: ='SOFP '!M29/'SOFP '!M$34 -> 0.0085105345 | N56: ='SOFP '!N29/'SOFP '!N$34 -> 0.011086099 | O56: ='SOFP '!O29/'SOFP '!O$34 -> 0.011607237 | P56: ='SOFP '!P29/'SOFP '!P$34 -> 0.01002056 | ... S56: ='SOFP '!S29/'SOFP '!S$34 -> 0.011916107
B57: Other Financial Assets | I57: ='SOFP '!I30/'SOFP '!I$34 -> 0.081263924 | J57: ='SOFP '!J30/'SOFP '!J$34 -> 0.21916756 | K57: ='SOFP '!K30/'SOFP '!K$34 -> 0.16159621 | L57: ='SOFP '!L30/'SOFP '!L$34 -> 0.16628343 | M57: ='SOFP '!M30/'SOFP '!M$34 -> 0.16223584 | N57: ='SOFP '!N30/'SOFP '!N$34 -> 0.14497436 | O57: ='SOFP '!O30/'SOFP '!O$34 -> 0.23480758 | P57: ='SOFP '!P30/'SOFP '!P$34 -> 0.2423783 | ... S57: ='SOFP '!S30/'SOFP '!S$34 -> 0.27099581
B58: Other Current Assets | I58: ='SOFP '!I31/'SOFP '!I$34 -> 0.01767837 | J58: ='SOFP '!J31/'SOFP '!J$34 -> 0.026374081 | K58: ='SOFP '!K31/'SOFP '!K$34 -> 0.02354853 | L58: ='SOFP '!L31/'SOFP '!L$34 -> 0.021473758 | M58: ='SOFP '!M31/'SOFP '!M$34 -> 0.026260782 | N58: ='SOFP '!N31/'SOFP '!N$34 -> 0.025474979 | O58: ='SOFP '!O31/'SOFP '!O$34 -> 0.023064189 | P58: ='SOFP '!P31/'SOFP '!P$34 -> 0.021537947 | ... S58: ='SOFP '!S31/'SOFP '!S$34 -> 0.017828986
B59: Assets classified as Held for Sale | I59: ='SOFP '!I32/'SOFP '!I$34 -> 0.00085795093 | J59: ='SOFP '!J32/'SOFP '!J$34 -> 0.00066226076 | K59: ='SOFP '!K32/'SOFP '!K$34 -> 0.0003537174 | L59: ='SOFP '!L32/'SOFP '!L$34 -> 0 | M59: ='SOFP '!M32/'SOFP '!M$34 -> 0 | N59: ='SOFP '!N32/'SOFP '!N$34 -> 0 | O59: ='SOFP '!O32/'SOFP '!O$34 -> 0 | P59: ='SOFP '!P32/'SOFP '!P$34 -> 0 | ... S59: ='SOFP '!S32/'SOFP '!S$34 -> 0
B60: Total Current Assets | I60: ='SOFP '!I33/'SOFP '!I$34 -> 0.46921807 | J60: ='SOFP '!J33/'SOFP '!J$34 -> 0.59041848 | K60: ='SOFP '!K33/'SOFP '!K$34 -> 0.65924266 | L60: ='SOFP '!L33/'SOFP '!L$34 -> 0.64094736 | M60: ='SOFP '!M33/'SOFP '!M$34 -> 0.58605157 | N60: ='SOFP '!N33/'SOFP '!N$34 -> 0.55946373 | O60: ='SOFP '!O33/'SOFP '!O$34 -> 0.58447772 | P60: ='SOFP '!P33/'SOFP '!P$34 -> 0.59949168 | ... S60: ='SOFP '!S33/'SOFP '!S$34 -> 0.63190599
B61: TOTAL ASSETS | I61: ='SOFP '!I34/'SOFP '!I$34 -> 1 | J61: ='SOFP '!J34/'SOFP '!J$34 -> 1 | K61: ='SOFP '!K34/'SOFP '!K$34 -> 1 | L61: ='SOFP '!L34/'SOFP '!L$34 -> 1 | M61: ='SOFP '!M34/'SOFP '!M$34 -> 1 | N61: ='SOFP '!N34/'SOFP '!N$34 -> 1 | O61: ='SOFP '!O34/'SOFP '!O$34 -> 1 | P61: ='SOFP '!P34/'SOFP '!P$34 -> 1 | ... S61: ='SOFP '!S34/'SOFP '!S$34 -> 1
B63: EQUITY AND LIABILITIES
B64: Equity
B65: Equity Share capital | I65: ='SOFP '!I38/'SOFP '!I$62 -> 0.0059375652 | J65: ='SOFP '!J38/'SOFP '!J$62 -> 0.0047089735 | K65: ='SOFP '!K38/'SOFP '!K$62 -> 0.0041732926 | L65: ='SOFP '!L38/'SOFP '!L$62 -> 0.0037181177 | M65: ='SOFP '!M38/'SOFP '!M$62 -> 0.0032054442 | N65: ='SOFP '!N38/'SOFP '!N$62 -> 0.0031582344 | O65: ='SOFP '!O38/'SOFP '!O$62 -> 0.0027775131 | P65: ='SOFP '!P38/'SOFP '!P$62 -> 0.002537536 | ... S65: ='SOFP '!S38/'SOFP '!S$62 -> 0.001966999
B66: Other Equity | I66: ='SOFP '!I39/'SOFP '!I$62 -> 0.62113172 | J66: ='SOFP '!J39/'SOFP '!J$62 -> 0.6239866 | K66: ='SOFP '!K39/'SOFP '!K$62 -> 0.59674081 | L66: ='SOFP '!L39/'SOFP '!L$62 -> 0.61618381 | M66: ='SOFP '!M39/'SOFP '!M$62 -> 0.62265486 | N66: ='SOFP '!N39/'SOFP '!N$62 -> 0.63559434 | O66: ='SOFP '!O39/'SOFP '!O$62 -> 0.6160702 | P66: ='SOFP '!P39/'SOFP '!P$62 -> 0.61023583 | ... S66: ='SOFP '!S39/'SOFP '!S$62 -> 0.60402599
B67: NCI | I67: ='SOFP '!I40/'SOFP '!I$62 -> 0.024979 | J67: ='SOFP '!J40/'SOFP '!J$62 -> 0.020759347 | K67: ='SOFP '!K40/'SOFP '!K$62 -> 0.016860676 | L67: ='SOFP '!L40/'SOFP '!L$62 -> 0.017585084 | M67: ='SOFP '!M40/'SOFP '!M$62 -> 0.023238134 | N67: ='SOFP '!N40/'SOFP '!N$62 -> 0.021705947 | O67: ='SOFP '!O40/'SOFP '!O$62 -> 0.018630361 | P67: ='SOFP '!P40/'SOFP '!P$62 -> 0.018651709 | ... S67: ='SOFP '!S40/'SOFP '!S$62 -> 0.018966113
B68: Total Equity | I68: ='SOFP '!I41/'SOFP '!I$62 -> 0.65204828 | J68: ='SOFP '!J41/'SOFP '!J$62 -> 0.64945492 | K68: ='SOFP '!K41/'SOFP '!K$62 -> 0.61777478 | L68: ='SOFP '!L41/'SOFP '!L$62 -> 0.63748701 | M68: ='SOFP '!M41/'SOFP '!M$62 -> 0.64909844 | N68: ='SOFP '!N41/'SOFP '!N$62 -> 0.66045852 | O68: ='SOFP '!O41/'SOFP '!O$62 -> 0.63747807 | P68: ='SOFP '!P41/'SOFP '!P$62 -> 0.63142508 | ... S68: ='SOFP '!S41/'SOFP '!S$62 -> 0.6249591
B70: Liabilities
B71: Non-Current Liabilities
B72: Financial Liabilities
B73: Lease Liabilities | I73: ='SOFP '!I46/'SOFP '!I$62 -> 0.036518007 | J73: ='SOFP '!J46/'SOFP '!J$62 -> 0.027558688 | K73: ='SOFP '!K46/'SOFP '!K$62 -> 0.026033915 | L73: ='SOFP '!L46/'SOFP '!L$62 -> 0.028255679 | M73: ='SOFP '!M46/'SOFP '!M$62 -> 0.036602283 | N73: ='SOFP '!N46/'SOFP '!N$62 -> 0.036985453 | O73: ='SOFP '!O46/'SOFP '!O$62 -> 0.037844485 | P73: ='SOFP '!P46/'SOFP '!P$62 -> 0.04117317 | ... S73: ='SOFP '!S46/'SOFP '!S$62 -> 0.053898053
B74: Borrowings | I74: ='SOFP '!I47/'SOFP '!I$62 -> 0.0011532198 | J74: ='SOFP '!J47/'SOFP '!J$62 -> 0.00071331719 | K74: ='SOFP '!K47/'SOFP '!K$62 -> 0.0019378487 | L74: ='SOFP '!L47/'SOFP '!L$62 -> 0.0029517792 | M74: ='SOFP '!M47/'SOFP '!M$62 -> 0.001817265 | N74: ='SOFP '!N47/'SOFP '!N$62 -> 0.0085481736 | O74: ='SOFP '!O47/'SOFP '!O$62 -> 0.036113752 | P74: ='SOFP '!P47/'SOFP '!P$62 -> 0.035402171 | ... S74: ='SOFP '!S47/'SOFP '!S$62 -> 0.035010443
B75: Other Financial Liabilities | I75: ='SOFP '!I48/'SOFP '!I$62 -> 0.00018198959 | J75: ='SOFP '!J48/'SOFP '!J$62 -> 0.00016593339 | K75: ='SOFP '!K48/'SOFP '!K$62 -> 9.4847559e-05 | L75: ='SOFP '!L48/'SOFP '!L$62 -> 0.0017978138 | M75: ='SOFP '!M48/'SOFP '!M$62 -> 0.0080396764 | N75: ='SOFP '!N48/'SOFP '!N$62 -> 0.0026317522 | O75: ='SOFP '!O48/'SOFP '!O$62 -> 0.0032912025 | P75: ='SOFP '!P48/'SOFP '!P$62 -> 0.003015189 | ... S75: ='SOFP '!S48/'SOFP '!S$62 -> 0.0023567743
B76: Deferred Tax Liabilities (Net) | I76: ='SOFP '!I49/'SOFP '!I$62 -> 0.027471762 | J76: ='SOFP '!J49/'SOFP '!J$62 -> 0.020402442 | K76: ='SOFP '!K49/'SOFP '!K$62 -> 0.015177785 | L76: ='SOFP '!L49/'SOFP '!L$62 -> 0.012979301 | M76: ='SOFP '!M49/'SOFP '!M$62 -> 0.011768779 | N76: ='SOFP '!N49/'SOFP '!N$62 -> 0.01333195 | O76: ='SOFP '!O49/'SOFP '!O$62 -> 0.011677022 | P76: ='SOFP '!P49/'SOFP '!P$62 -> 0.010922461 | ... S76: ='SOFP '!S49/'SOFP '!S$62 -> 0.0090867673
B77: Other Non-Current Liabilities | I77: ='SOFP '!I50/'SOFP '!I$62 -> 0.011475867 | J77: ='SOFP '!J50/'SOFP '!J$62 -> 0.010788125 | K77: ='SOFP '!K50/'SOFP '!K$62 -> 0.0095904804 | L77: ='SOFP '!L50/'SOFP '!L$62 -> 0.010460888 | M77: ='SOFP '!M50/'SOFP '!M$62 -> 0.0085894007 | N77: ='SOFP '!N50/'SOFP '!N$62 -> 0.0099873565 | O77: ='SOFP '!O50/'SOFP '!O$62 -> 0.0090185203 | P77: ='SOFP '!P50/'SOFP '!P$62 -> 0.0083114359 | ... S77: ='SOFP '!S50/'SOFP '!S$62 -> 0.0066133582
B78: Total Non-Current Liabilities | I78: ='SOFP '!I51/'SOFP '!I$62 -> 0.076800846 | J78: ='SOFP '!J51/'SOFP '!J$62 -> 0.059628506 | K78: ='SOFP '!K51/'SOFP '!K$62 -> 0.052834876 | L78: ='SOFP '!L51/'SOFP '!L$62 -> 0.056445461 | M78: ='SOFP '!M51/'SOFP '!M$62 -> 0.066817404 | N78: ='SOFP '!N51/'SOFP '!N$62 -> 0.071484686 | O78: ='SOFP '!O51/'SOFP '!O$62 -> 0.097944982 | P78: ='SOFP '!P51/'SOFP '!P$62 -> 0.098824426 | ... S78: ='SOFP '!S51/'SOFP '!S$62 -> 0.1069654
B80: Current Liabilities
B81: Financial Liabilities
B82: Trade Payables | I82: ='SOFP '!I55/'SOFP '!I$62 -> 0.13225629 | J82: ='SOFP '!J55/'SOFP '!J$62 -> 0.16587055 | K82: ='SOFP '!K55/'SOFP '!K$62 -> 0.18118059 | L82: ='SOFP '!L55/'SOFP '!L$62 -> 0.14091945 | M82: ='SOFP '!M55/'SOFP '!M$62 -> 0.12803531 | N82: ='SOFP '!N55/'SOFP '!N$62 -> 0.12669814 | O82: ='SOFP '!O55/'SOFP '!O$62 -> 0.11186035 | P82: ='SOFP '!P55/'SOFP '!P$62 -> 0.11786615 | ... S82: ='SOFP '!S55/'SOFP '!S$62 -> 0.11879327
B83: Borrowings | I83: ='SOFP '!I56/'SOFP '!I$62 -> 0.019900005 | J83: ='SOFP '!J56/'SOFP '!J$62 -> 0.015989498 | K83: ='SOFP '!K56/'SOFP '!K$62 -> 0.031809609 | L83: ='SOFP '!L56/'SOFP '!L$62 -> 0.0347337 | M83: ='SOFP '!M56/'SOFP '!M$62 -> 0.03518102 | N83: ='SOFP '!N56/'SOFP '!N$62 -> 0.019892399 | O83: ='SOFP '!O56/'SOFP '!O$62 -> 0.030291167 | P83: ='SOFP '!P56/'SOFP '!P$62 -> 0.029694313 | ... S83: ='SOFP '!S56/'SOFP '!S$62 -> 0.029365744
B84: Lease Liabilities | I84: ='SOFP '!I57/'SOFP '!I$62 -> 0.010762765 | J84: ='SOFP '!J57/'SOFP '!J$62 -> 0.008992804 | K84: ='SOFP '!K57/'SOFP '!K$62 -> 0.0092606894 | L84: ='SOFP '!L57/'SOFP '!L$62 -> 0.008972401 | M84: ='SOFP '!M57/'SOFP '!M$62 -> 0.0090879957 | N84: ='SOFP '!N57/'SOFP '!N$62 -> 0.0099843932 | O84: ='SOFP '!O57/'SOFP '!O$62 -> 0.0095188897 | P84: ='SOFP '!P57/'SOFP '!P$62 -> 0.012134758 | ... S84: ='SOFP '!S57/'SOFP '!S$62 -> 0.015885098
B85: Other Financial Liabilities | I85: ='SOFP '!I58/'SOFP '!I$62 -> 0.085073325 | J85: ='SOFP '!J58/'SOFP '!J$62 -> 0.078696608 | K85: ='SOFP '!K58/'SOFP '!K$62 -> 0.082082731 | L85: ='SOFP '!L58/'SOFP '!L$62 -> 0.0944267 | M85: ='SOFP '!M58/'SOFP '!M$62 -> 0.089407564 | N85: ='SOFP '!N58/'SOFP '!N$62 -> 0.090283622 | O85: ='SOFP '!O58/'SOFP '!O$62 -> 0.088164615 | P85: ='SOFP '!P58/'SOFP '!P$62 -> 0.086493859 | ... S85: ='SOFP '!S58/'SOFP '!S$62 -> 0.083019829
B86: Other Current Liabilities | I86: ='SOFP '!I59/'SOFP '!I$62 -> 0.01201317 | J86: ='SOFP '!J59/'SOFP '!J$62 -> 0.015415604 | K86: ='SOFP '!K59/'SOFP '!K$62 -> 0.019395456 | L86: ='SOFP '!L59/'SOFP '!L$62 -> 0.020670207 | M86: ='SOFP '!M59/'SOFP '!M$62 -> 0.01827825 | N86: ='SOFP '!N59/'SOFP '!N$62 -> 0.017046629 | O86: ='SOFP '!O59/'SOFP '!O$62 -> 0.019529462 | P86: ='SOFP '!P59/'SOFP '!P$62 -> 0.018115432 | ... S86: ='SOFP '!S59/'SOFP '!S$62 -> 0.01469764
B87: Income Tax Liabilities (Net) | I87: ='SOFP '!I60/'SOFP '!I$62 -> 0.011145315 | J87: ='SOFP '!J60/'SOFP '!J$62 -> 0.0059515101 | K87: ='SOFP '!K60/'SOFP '!K$62 -> 0.005661268 | L87: ='SOFP '!L60/'SOFP '!L$62 -> 0.0063450655 | M87: ='SOFP '!M60/'SOFP '!M$62 -> 0.0040940259 | N87: ='SOFP '!N60/'SOFP '!N$62 -> 0.0041516032 | O87: ='SOFP '!O60/'SOFP '!O$62 -> 0.0052124702 | P87: ='SOFP '!P60/'SOFP '!P$62 -> 0.0054459872 | ... S87: ='SOFP '!S60/'SOFP '!S$62 -> 0.0063139244
B88: Total Current-Liabilities | I88: ='SOFP '!I61/'SOFP '!I$62 -> 0.27115087 | J88: ='SOFP '!J61/'SOFP '!J$62 -> 0.29091657 | K88: ='SOFP '!K61/'SOFP '!K$62 -> 0.32939034 | L88: ='SOFP '!L61/'SOFP '!L$62 -> 0.30606752 | M88: ='SOFP '!M61/'SOFP '!M$62 -> 0.28408416 | N88: ='SOFP '!N61/'SOFP '!N$62 -> 0.26805679 | O88: ='SOFP '!O61/'SOFP '!O$62 -> 0.26457695 | P88: ='SOFP '!P61/'SOFP '!P$62 -> 0.2697505 | ... S88: ='SOFP '!S61/'SOFP '!S$62 -> 0.2680755
B89: TOTAL EQUITY AND LIABILITIES | I89: ='SOFP '!I62/'SOFP '!I$62 -> 1 | J89: ='SOFP '!J62/'SOFP '!J$62 -> 1 | K89: ='SOFP '!K62/'SOFP '!K$62 -> 1 | L89: ='SOFP '!L62/'SOFP '!L$62 -> 1 | M89: ='SOFP '!M62/'SOFP '!M$62 -> 1 | N89: ='SOFP '!N62/'SOFP '!N$62 -> 1 | O89: ='SOFP '!O62/'SOFP '!O$62 -> 1 | P89: ='SOFP '!P62/'SOFP '!P$62 -> 1 | ... S89: ='SOFP '!S62/'SOFP '!S$62 -> 1

Sheet Comparative Analysis
F2: NSE: ASIANPAINT | BSE:500820
F3: 52-WEEK (HIGH: ₹ 2985.70| LOW: ₹ 2115.00 )
F4: 2649.4
F5: (as at 13 July 2026)
B6: COMPARATIVE CONSOLIDATED STATEMENT OF PROFIT AND LOSS
I8: Historical | P8: Forecasts
B9: Years | I9: =J9-1 -> 20 | J9: 21 | K9: =J9+1 -> 22 | L9: =K9+1 -> 23 | M9: =L9+1 -> 24 | N9: =M9+1 -> 25 | O9: =N9+1 -> 26 | P9: =O9+1 -> 27 | Q9: =P9+1 -> 28 | R9: =Q9+1 -> 29 | S9: =R9+1 -> 30
B11: Revenue from Sale of Products and Services | I11: 0 | J11: =SOPL!J11/SOPL!I11-1 -> 0.071670843 | K11: =SOPL!K11/SOPL!J11-1 -> 0.34620483 | L11: =SOPL!L11/SOPL!K11-1 -> 0.18823288 | M11: =SOPL!M11/SOPL!L11-1 -> 0.029512774 | N11: =SOPL!N11/SOPL!M11-1 -> -0.044789854 | O11: =SOPL!O11/SOPL!N11-1 -> 0.050862257 | P11: =SOPL!P11/SOPL!O11-1 -> 0.091670533 | Q11: =SOPL!Q11/SOPL!P11-1 -> 0.091670533 | ... S11: =SOPL!S11/SOPL!R11-1 -> 0.091670533
B12: Other Operating Revenue | I12: 0 | J12: =SOPL!J12/SOPL!I12-1 -> 0.39685755 | K12: =SOPL!K12/SOPL!J12-1 -> -0.2187706 | L12: =SOPL!L12/SOPL!K12-1 -> -0.3208099 | M12: =SOPL!M12/SOPL!L12-1 -> -0.067489235 | N12: =SOPL!N12/SOPL!M12-1 -> -0.038628896 | O12: =SOPL!O12/SOPL!N12-1 -> -0.37954923 | P12: =SOPL!P12/SOPL!O12-1 -> -0.067489235 | Q12: =SOPL!Q12/SOPL!P12-1 -> -0.067489235 | ... S12: =SOPL!S12/SOPL!R12-1 -> -0.067489235
B13: REVENUE FROM OPERATIONS | I13: 0 | J13: =SOPL!J13/SOPL!I13-1 -> 0.074292288 | K13: =SOPL!K13/SOPL!J13-1 -> 0.34028285 | L13: =SOPL!L13/SOPL!K13-1 -> 0.18512278 | M13: =SOPL!M13/SOPL!L13-1 -> 0.029173127 | N13: =SOPL!N13/SOPL!M13-1 -> -0.044770308 | O13: =SOPL!O13/SOPL!N13-1 -> 0.049487961 | P13: =SOPL!P13/SOPL!O13-1 -> 0.091370092 | Q13: =SOPL!Q13/SOPL!P13-1 -> 0.091413824 | ... S13: =SOPL!S13/SOPL!R13-1 -> 0.091483139
B14: Materials Cost | I14: 0 | J14: =SOPL!J14/SOPL!I14-1 -> 0.022326091 | K14: =SOPL!K14/SOPL!J14-1 -> 0.57550143 | L14: =SOPL!L14/SOPL!K14-1 -> 0.066196071 | M14: =SOPL!M14/SOPL!L14-1 -> -0.084380904 | N14: =SOPL!N14/SOPL!M14-1 -> -0.0046816875 | O14: =SOPL!O14/SOPL!N14-1 -> -0.025951125 | P14: =SOPL!P14/SOPL!O14-1 -> 0.19947749 | Q14: =SOPL!Q14/SOPL!P14-1 -> 0.091413824 | ... S14: =SOPL!S14/SOPL!R14-1 -> 0.091483139
B15: Purchases of Stock-in-Trade | I15: 0 | J15: =SOPL!J15/SOPL!I15-1 -> 0.22325144 | K15: =SOPL!K15/SOPL!J15-1 -> 0.80024992 | L15: =SOPL!L15/SOPL!K15-1 -> 0.22678449 | M15: =SOPL!M15/SOPL!L15-1 -> -0.067087399 | N15: =SOPL!N15/SOPL!M15-1 -> 0.017795863 | O15: =SOPL!O15/SOPL!N15-1 -> 0.022203491 | P15: =SOPL!P15/SOPL!O15-1 -> 0.091370092 | Q15: =SOPL!Q15/SOPL!P15-1 -> 0.091413824 | ... S15: =SOPL!S15/SOPL!R15-1 -> 0.091483139
B16: Changes in Inventories | I16: 0 | J16: =SOPL!J16/SOPL!I16-1 -> -0.61342254 | K16: =SOPL!K16/SOPL!J16-1 -> 13.331747 | L16: =SOPL!L16/SOPL!K16-1 -> -0.76623622 | M16: =SOPL!M16/SOPL!L16-1 -> -2.1745714 | N16: =SOPL!N16/SOPL!M16-1 -> -1.5634964 | O16: =SOPL!O16/SOPL!N16-1 -> -3.9447805 | P16: =SOPL!P16/SOPL!O16-1 -> -1.3889525 | Q16: =SOPL!Q16/SOPL!P16-1 -> 0.091413824 | ... S16: =SOPL!S16/SOPL!R16-1 -> 0.091483139
B17: COST OF GOODS SOLD | I17: 0 | J17: =SOPL!J17/SOPL!I17-1 -> 0.062702377 | K17: =SOPL!K17/SOPL!J17-1 -> 0.512805 | L17: =SOPL!L17/SOPL!K17-1 -> 0.15604552 | M17: =SOPL!M17/SOPL!L17-1 -> -0.050400113 | N17: =SOPL!N17/SOPL!M17-1 -> -0.028592533 | O17: =SOPL!O17/SOPL!N17-1 -> 0.024902925 | P17: =SOPL!P17/SOPL!O17-1 -> 0.12984109 | Q17: =SOPL!Q17/SOPL!P17-1 -> 0.091413824 | ... S17: =SOPL!S17/SOPL!R17-1 -> 0.091483139
B18: GROSS MARGIN | I18: 0 | J18: =SOPL!J18/SOPL!I18-1 -> 0.08923751 | K18: =SOPL!K18/SOPL!J18-1 -> 0.12323463 | L18: =SOPL!L18/SOPL!K18-1 -> 0.2343922 | M18: =SOPL!M18/SOPL!L18-1 -> 0.15544675 | N18: =SOPL!N18/SOPL!M18-1 -> -0.065868979 | O18: =SOPL!O18/SOPL!N18-1 -> 0.082830664 | P18: =SOPL!P18/SOPL!O18-1 -> 0.041986162 | Q18: =SOPL!Q18/SOPL!P18-1 -> 0.091413824 | ... S18: =SOPL!S18/SOPL!R18-1 -> 0.091483139
B19: Other Non-Operating Income | I19: 0 | J19: =SOPL!J19/SOPL!I19-1 -> -0.0041405146 | K19: =SOPL!K19/SOPL!J19-1 -> 0.25395149 | L19: =SOPL!L19/SOPL!K19-1 -> 0.017025868 | M19: =SOPL!M19/SOPL!L19-1 -> 0.78006624 | N19: =SOPL!N19/SOPL!M19-1 -> -0.16766963 | O19: =SOPL!O19/SOPL!N19-1 -> 0.2640366 | P19: =SOPL!P19/SOPL!O19-1 -> 0.15535929 | Q19: =SOPL!Q19/SOPL!P19-1 -> 0.15535929 | ... S19: =SOPL!S19/SOPL!R19-1 -> 0.15535929
B20: Employee Benefits Expense | I20: 0 | J20: =SOPL!J20/SOPL!I20-1 -> 0.12785395 | K20: =SOPL!K20/SOPL!J20-1 -> 0.15961058 | L20: =SOPL!L20/SOPL!K20-1 -> 0.13511169 | M20: =SOPL!M20/SOPL!L20-1 -> 0.14699197 | N20: =SOPL!N20/SOPL!M20-1 -> 0.11652151 | O20: =SOPL!O20/SOPL!N20-1 -> 0.077913777 | P20: =SOPL!P20/SOPL!O20-1 -> 0.13148282 | Q20: =SOPL!Q20/SOPL!P20-1 -> 0.13148282 | ... S20: =SOPL!S20/SOPL!R20-1 -> 0.13148282
B21: Other Expenses | I21: 0 | J21: =SOPL!J21/SOPL!I21-1 -> -0.024461125 | K21: =SOPL!K21/SOPL!J21-1 -> 0.30785193 | L21: =SOPL!L21/SOPL!K21-1 -> 0.19807137 | M21: =SOPL!M21/SOPL!L21-1 -> 0.089049162 | N21: =SOPL!N21/SOPL!M21-1 -> 0.053344401 | O21: =SOPL!O21/SOPL!N21-1 -> 0.051819784 | P21: =SOPL!P21/SOPL!O21-1 -> -0.012480692 | Q21: =SOPL!Q21/SOPL!P21-1 -> 0.091413824 | ... S21: =SOPL!S21/SOPL!R21-1 -> 0.091483139
B22: EBITDA | I22: 0 | J22: =SOPL!J22/SOPL!I22-1 -> 0.15507335 | K22: =SOPL!K22/SOPL!J22-1 -> 0.0048404137 | L22: =SOPL!L22/SOPL!K22-1 -> 0.28217732 | M22: =SOPL!M22/SOPL!L22-1 -> 0.24473995 | N22: =SOPL!N22/SOPL!M22-1 -> -0.20477847 | O22: =SOPL!O22/SOPL!N22-1 -> 0.12781927 | P22: =SOPL!P22/SOPL!O22-1 -> 0.063955242 | Q22: =SOPL!Q22/SOPL!P22-1 -> 0.082109363 | ... S22: =SOPL!S22/SOPL!R22-1 -> 0.081646083
... B25: Share of Profit in Associate | I25: 0 | J25: =SOPL!J25/SOPL!I25-1 -> -0.43634214 | K25: =SOPL!K25/SOPL!J25-1 -> 0.10384615 | L25: =SOPL!L25/SOPL!K25-1 -> 1.9727589 | M25: =SOPL!M25/SOPL!L25-1 -> 0.41715503 | N25: =SOPL!N25/SOPL!M25-1 -> 0.057969925 | O25: =SOPL!O25/SOPL!N25-1 -> 0.17681757 | P25: =SOPL!P25/SOPL!O25-1 -> 0.10384615 | Q25: =SOPL!Q25/SOPL!P25-1 -> 0.10384615 | ... S25: =SOPL!S25/SOPL!R25-1 -> 0.10384615
B26: Exceptional Items | I26: 0 | J26: 0 | K26: 0 | L26: =SOPL!L26/SOPL!K26-1 -> -0.57761452 | M26: =SOPL!M26/SOPL!L26-1 -> -1 | N26: 0 | O26: =SOPL!O26/SOPL!N26-1 -> -0.56593225 | P26: =SOPL!P26/SOPL!O26-1 -> -1 | Q26: 0 | R26: 0 | S26: 0
B27: Finance Costs | I27: 0 | J27: =SOPL!J27/SOPL!I27-1 -> -0.10456367 | K27: =SOPL!K27/SOPL!J27-1 -> 0.041252865 | L27: =SOPL!L27/SOPL!K27-1 -> 0.51399224 | M27: =SOPL!M27/SOPL!L27-1 -> 0.42035306 | N27: =SOPL!N27/SOPL!M27-1 -> 0.10649705 | O27: =SOPL!O27/SOPL!N27-1 -> -0.13923883 | P27: =SOPL!P27/SOPL!O27-1 -> 0.073874958 | Q27: =SOPL!Q27/SOPL!P27-1 -> 0.073874958 | ... S27: =SOPL!S27/SOPL!R27-1 -> 0.073874958
B28: PROFIT BEFORE TAX | I28: 0 | J28: =SOPL!J28/SOPL!I28-1 -> 0.18446941 | K28: =SOPL!K28/SOPL!J28-1 -> -0.027095845 | L28: =SOPL!L28/SOPL!K28-1 -> 0.3584552 | M28: =SOPL!M28/SOPL!L28-1 -> 0.29161357 | N28: =SOPL!N28/SOPL!M28-1 -> -0.30549405 | O28: =SOPL!O28/SOPL!N28-1 -> 0.17643693 | P28: =SOPL!P28/SOPL!O28-1 -> 0.087562937 | Q28: =SOPL!Q28/SOPL!P28-1 -> 0.089875609 | ... S28: =SOPL!S28/SOPL!R28-1 -> 0.087118793
B29: Tax Expense | I29: 0 | J29: =SOPL!J29/SOPL!I29-1 -> 0.28396795 | K29: =SOPL!K29/SOPL!J29-1 -> 0.004837828 | L29: =SOPL!L29/SOPL!K29-1 -> 0.35414494 | M29: =SOPL!M29/SOPL!L29-1 -> 0.19858052 | N29: =SOPL!N29/SOPL!M29-1 -> -0.22162138 | O29: =SOPL!O29/SOPL!N29-1 -> 0.15458317 | P29: =SOPL!P29/SOPL!O29-1 -> 0.087562937 | Q29: =SOPL!Q29/SOPL!P29-1 -> 0.089875609 | ... S29: =SOPL!S29/SOPL!R29-1 -> 0.087118793
B30: (Loss)/Profit from Discontinued Operations | I30: 0 | J30: =SOPL!J30/SOPL!I30-1 -> -1 | K30: 0 | L30: 0 | M30: 0 | N30: 0 | O30: 0 | P30: 0 | Q30: 0 | R30: 0 | S30: 0
B31: PROFIT AFTER TAX | I31: 0 | J31: =SOPL!J31/SOPL!I31-1 -> 0.15592299 | K31: =SOPL!K31/SOPL!J31-1 -> -0.038026039 | L31: =SOPL!L31/SOPL!K31-1 -> 0.35999624 | M31: =SOPL!M31/SOPL!L31-1 -> 0.3247325 | N31: =SOPL!N31/SOPL!M31-1 -> -0.33250865 | O31: =SOPL!O31/SOPL!N31-1 -> 0.18464516 | P31: =SOPL!P31/SOPL!O31-1 -> 0.087562937 | Q31: =SOPL!Q31/SOPL!P31-1 -> 0.089875609 | ... S31: =SOPL!S31/SOPL!R31-1 -> 0.087118793
B33: COMPARATIVE CONSOLIDATED STATEMENT OF FINANCIAL POSITION
I35: Historical | P35: Forecasts
B36: Years | I36: =J36-1 -> 20 | J36: 21 | K36: =J36+1 -> 22 | L36: =K36+1 -> 23 | M36: =L36+1 -> 24 | N36: =M36+1 -> 25 | O36: =N36+1 -> 26 | P36: =O36+1 -> 27 | Q36: =P36+1 -> 28 | R36: =Q36+1 -> 29 | S36: =R36+1 -> 30
B38: ASSETS
B39: Non-Current Assets
B40: Property, Plant & Equipment | I40: - | J40: ='SOFP '!J13/'SOFP '!I13-1 -> -0.060529806 | K40: ='SOFP '!K13/'SOFP '!J13-1 -> -0.065207144 | L40: ='SOFP '!L13/'SOFP '!K13-1 -> -0.0092747929 | M40: ='SOFP '!M13/'SOFP '!L13-1 -> 0.072497678 | N40: ='SOFP '!N13/'SOFP '!M13-1 -> 0.52661149 | O40: ='SOFP '!O13/'SOFP '!N13-1 -> 0.052832952 | P40: ='SOFP '!P13/'SOFP '!O13-1 -> 0.024700431 | Q40: ='SOFP '!Q13/'SOFP '!P13-1 -> 0.032768358 | ... S40: ='SOFP '!S13/'SOFP '!R13-1 -> 0.047135498
B41: Right-of-Use Assets | I41: - | J41: ='SOFP '!J14/'SOFP '!I14-1 -> -0.081013814 | K41: ='SOFP '!K14/'SOFP '!J14-1 -> 0.071196263 | L41: ='SOFP '!L14/'SOFP '!K14-1 -> 0.33471709 | M41: ='SOFP '!M14/'SOFP '!L14-1 -> 0.53547795 | N41: ='SOFP '!N14/'SOFP '!M14-1 -> -0.0067608699 | O41: ='SOFP '!O14/'SOFP '!N14-1 -> 0.094943918 | P41: ='SOFP '!P14/'SOFP '!O14-1 -> 0.071196263 | Q41: ='SOFP '!Q14/'SOFP '!P14-1 -> 0.071196263 | ... S41: ='SOFP '!S14/'SOFP '!R14-1 -> 0.071196263
B42: Capital work-in-progress | I42: - | J42: ='SOFP '!J15/'SOFP '!I15-1 -> 0.30476326 | K42: ='SOFP '!K15/'SOFP '!J15-1 -> 1.3304733 | L42: ='SOFP '!L15/'SOFP '!K15-1 -> 1.3909903 | M42: ='SOFP '!M15/'SOFP '!L15-1 -> 1.6465246 | N42: ='SOFP '!N15/'SOFP '!M15-1 -> -0.53509341 | O42: ='SOFP '!O15/'SOFP '!N15-1 -> 0.47364268 | P42: ='SOFP '!P15/'SOFP '!O15-1 -> -0.00055054351 | Q42: ='SOFP '!Q15/'SOFP '!P15-1 -> 0.032768358 | ... S42: ='SOFP '!S15/'SOFP '!R15-1 -> 0.047135498
B43: Goodwill and Intangible Assets | I43: - | J43: ='SOFP '!J16/'SOFP '!I16-1 -> -0.086542062 | K43: ='SOFP '!K16/'SOFP '!J16-1 -> -0.20083113 | L43: ='SOFP '!L16/'SOFP '!K16-1 -> -0.030220357 | M43: ='SOFP '!M16/'SOFP '!L16-1 -> 1.0297434 | N43: ='SOFP '!N16/'SOFP '!M16-1 -> -0.30254102 | O43: ='SOFP '!O16/'SOFP '!N16-1 -> -0.19274407 | P43: ='SOFP '!P16/'SOFP '!O16-1 -> 0.45357478 | Q43: ='SOFP '!Q16/'SOFP '!P16-1 -> 0.10739215 | ... S43: ='SOFP '!S16/'SOFP '!R16-1 -> 0.11025111
B44: Investment in Associates | I44: - | J44: ='SOFP '!J17/'SOFP '!I17-1 -> 0.059720124 | K44: ='SOFP '!K17/'SOFP '!J17-1 -> 0.065240752 | L44: ='SOFP '!L17/'SOFP '!K17-1 -> 0.5165383 | M44: ='SOFP '!M17/'SOFP '!L17-1 -> -0.25405191 | N44: ='SOFP '!N17/'SOFP '!M17-1 -> 0.042649152 | O44: ='SOFP '!O17/'SOFP '!N17-1 -> 0.079095395 | P44: ='SOFP '!P17/'SOFP '!O17-1 -> 0.060872273 | Q44: ='SOFP '!Q17/'SOFP '!P17-1 -> 0.060872273 | ... S44: ='SOFP '!S17/'SOFP '!R17-1 -> 0.060872273
B45: Financial Assets | I45: - | J45: ='SOFP '!J18/'SOFP '!I18-1 -> 0.15485589 | K45: ='SOFP '!K18/'SOFP '!J18-1 -> -0.34302755 | L45: ='SOFP '!L18/'SOFP '!K18-1 -> 0.10436522 | M45: ='SOFP '!M18/'SOFP '!L18-1 -> 0.22758266 | N45: ='SOFP '!N18/'SOFP '!M18-1 -> 0.24734158 | O45: ='SOFP '!O18/'SOFP '!N18-1 -> -0.053345769 | P45: ='SOFP '!P18/'SOFP '!O18-1 -> 0.10436522 | Q45: ='SOFP '!Q18/'SOFP '!P18-1 -> 0.10436522 | ... S45: ='SOFP '!S18/'SOFP '!R18-1 -> 0.10436522
B46: Deferred Tax Assets (Net) | I46: - | J46: ='SOFP '!J19/'SOFP '!I19-1 -> -0.15 | K46: ='SOFP '!K19/'SOFP '!J19-1 -> 0.82212885 | L46: ='SOFP '!L19/'SOFP '!K19-1 -> -0.28247502 | M46: ='SOFP '!M19/'SOFP '!L19-1 -> 0.24906267 | N46: ='SOFP '!N19/'SOFP '!M19-1 -> -0.30874786 | O46: ='SOFP '!O19/'SOFP '!N19-1 -> -0.023573201 | P46: ='SOFP '!P19/'SOFP '!O19-1 -> 0.013010204 | Q46: ='SOFP '!Q19/'SOFP '!P19-1 -> 0.013010204 | ... S46: ='SOFP '!S19/'SOFP '!R19-1 -> 0.013010204
B47: Income Tax Assets (Net) | I47: - | J47: ='SOFP '!J20/'SOFP '!I20-1 -> -0.39851436 | K47: ='SOFP '!K20/'SOFP '!J20-1 -> 0.13289102 | L47: ='SOFP '!L20/'SOFP '!K20-1 -> 0.098921489 | M47: ='SOFP '!M20/'SOFP '!L20-1 -> 0.045325032 | N47: ='SOFP '!N20/'SOFP '!M20-1 -> 0.11867145 | O47: ='SOFP '!O20/'SOFP '!N20-1 -> 0.12183016 | P47: ='SOFP '!P20/'SOFP '!O20-1 -> 0.098921489 | Q47: ='SOFP '!Q20/'SOFP '!P20-1 -> 0.098921489 | ... S47: ='SOFP '!S20/'SOFP '!R20-1 -> 0.098921489
B48: Other Non-Current Assets | I48: - | J48: ='SOFP '!J21/'SOFP '!I21-1 -> 0.050545399 | K48: ='SOFP '!K21/'SOFP '!J21-1 -> 0.94311202 | L48: ='SOFP '!L21/'SOFP '!K21-1 -> 1.5177994 | M48: ='SOFP '!M21/'SOFP '!L21-1 -> -0.020117176 | N48: ='SOFP '!N21/'SOFP '!M21-1 -> -0.081724169 | O48: ='SOFP '!O21/'SOFP '!N21-1 -> -0.083416384 | P48: ='SOFP '!P21/'SOFP '!O21-1 -> 0.059038257 | Q48: ='SOFP '!Q21/'SOFP '!P21-1 -> 0.059038257 | ... S48: ='SOFP '!S21/'SOFP '!R21-1 -> 0.059038257
B49: Total Non-Current Assets | I49: - | J49: ='SOFP '!J22/'SOFP '!I22-1 -> -0.027014482 | K49: ='SOFP '!K22/'SOFP '!J22-1 -> -0.061236818 | L49: ='SOFP '!L22/'SOFP '!K22-1 -> 0.1826734 | M49: ='SOFP '!M22/'SOFP '!L22-1 -> 0.33728209 | N49: ='SOFP '!N22/'SOFP '!M22-1 -> 0.080137047 | O49: ='SOFP '!O22/'SOFP '!N22-1 -> 0.072509901 | P49: ='SOFP '!P22/'SOFP '!O22-1 -> 0.055021255 | Q49: ='SOFP '!Q22/'SOFP '!P22-1 -> 0.053328241 | ... S49: ='SOFP '!S22/'SOFP '!R22-1 -> 0.063292512
B51: Current Assets
B52: Inventories | I52: - | J52: ='SOFP '!J25/'SOFP '!I25-1 -> 0.12059378 | K52: ='SOFP '!K25/'SOFP '!J25-1 -> 0.61980203 | L52: ='SOFP '!L25/'SOFP '!K25-1 -> 0.009371069 | M52: ='SOFP '!M25/'SOFP '!L25-1 -> -0.046248052 | N52: ='SOFP '!N25/'SOFP '!M25-1 -> 0.13435842 | O52: ='SOFP '!O25/'SOFP '!N25-1 -> -0.14519137 | P52: ='SOFP '!P25/'SOFP '!O25-1 -> 0.17164513 | Q52: ='SOFP '!Q25/'SOFP '!P25-1 -> 0.091413824 | ... S52: ='SOFP '!S25/'SOFP '!R25-1 -> 0.091483139
B53: Financial Assets
B54: Trade Receivables | I54: - | J54: ='SOFP '!J27/'SOFP '!I27-1 -> 0.44949923 | K54: ='SOFP '!K27/'SOFP '!J27-1 -> 0.48777367 | L54: ='SOFP '!L27/'SOFP '!K27-1 -> 0.19773004 | M54: ='SOFP '!M27/'SOFP '!L27-1 -> 0.054369908 | N54: ='SOFP '!N27/'SOFP '!M27-1 -> -0.11769158 | O54: ='SOFP '!O27/'SOFP '!N27-1 -> 0.034344465 | P54: ='SOFP '!P27/'SOFP '!O27-1 -> 0.10734848 | Q54: ='SOFP '!Q27/'SOFP '!P27-1 -> 0.091413824 | ... S54: ='SOFP '!S27/'SOFP '!R27-1 -> 0.091483139
B55: Cash & Cash Equivalents | I55: - | J55: ='SOFP '!J28/'SOFP '!I28-1 -> -0.38564816 | K55: ='SOFP '!K28/'SOFP '!J28-1 -> 0.79485551 | L55: ='SOFP '!L28/'SOFP '!K28-1 -> -0.15862446 | M55: ='SOFP '!M28/'SOFP '!L28-1 -> 0.585433 | N55: ='SOFP '!N28/'SOFP '!M28-1 -> -0.46309113 | O55: ='SOFP '!O28/'SOFP '!N28-1 -> 0.51102677 | P55: ='SOFP '!P28/'SOFP '!O28-1 -> -0.055053647 | Q55: ='SOFP '!Q28/'SOFP '!P28-1 -> 0.22799807 | ... S55: ='SOFP '!S28/'SOFP '!R28-1 -> 0.090638993
B56: Other Balances with Bank | I56: - | J56: ='SOFP '!J29/'SOFP '!I29-1 -> 0.20712329 | K56: ='SOFP '!K29/'SOFP '!J29-1 -> -0.082274172 | L56: ='SOFP '!L29/'SOFP '!K29-1 -> 0.32195705 | M56: ='SOFP '!M29/'SOFP '!L29-1 -> -0.20594288 | N56: ='SOFP '!N29/'SOFP '!M29-1 -> 0.32210311 | O56: ='SOFP '!O29/'SOFP '!N29-1 -> 0.19052569 | P56: ='SOFP '!P29/'SOFP '!O29-1 -> -0.055053647 | Q56: ='SOFP '!Q29/'SOFP '!P29-1 -> 0.22799807 | ... S56: ='SOFP '!S29/'SOFP '!R29-1 -> 0.090638993
B57: Other Financial Assets | I57: - | J57: ='SOFP '!J30/'SOFP '!I30-1 -> 2.4006399 | K57: ='SOFP '!K30/'SOFP '!J30-1 -> -0.16803304 | L57: ='SOFP '!L30/'SOFP '!K30-1 -> 0.15496742 | M57: ='SOFP '!M30/'SOFP '!L30-1 -> 0.13170372 | N57: ='SOFP '!N30/'SOFP '!M30-1 -> -0.093040645 | O57: ='SOFP '!O30/'SOFP '!N30-1 -> 0.84166048 | P57: ='SOFP '!P30/'SOFP '!O30-1 -> 0.12986254 | Q57: ='SOFP '!Q30/'SOFP '!P30-1 -> 0.12986254 | ... S57: ='SOFP '!S30/'SOFP '!R30-1 -> 0.12986254
B58: Other Current Assets | I58: - | J58: ='SOFP '!J31/'SOFP '!I31-1 -> 0.88112329 | K58: ='SOFP '!K31/'SOFP '!J31-1 -> 0.0074828286 | L58: ='SOFP '!L31/'SOFP '!K31-1 -> 0.02351963 | M58: ='SOFP '!M31/'SOFP '!L31-1 -> 0.41851691 | N58: ='SOFP '!N31/'SOFP '!M31-1 -> -0.015423183 | O58: ='SOFP '!O31/'SOFP '!N31-1 -> 0.029468405 | P58: ='SOFP '!P31/'SOFP '!O31-1 -> 0.022139343 | Q58: ='SOFP '!Q31/'SOFP '!P31-1 -> 0.022139343 | ... S58: ='SOFP '!S31/'SOFP '!R31-1 -> 0.022139343
B59: Assets classified as Held for Sale | I59: - | J59: ='SOFP '!J32/'SOFP '!I32-1 -> -0.026695527 | K59: ='SOFP '!K32/'SOFP '!J32-1 -> -0.39733136 | L59: ='SOFP '!L32/'SOFP '!K32-1 -> -1 | M59: - | N59: - | O59: - | P59: - | Q59: - | R59: - | S59: -
B60: Total Current Assets | I60: - | J60: ='SOFP '!J33/'SOFP '!I33-1 -> 0.58659967 | K60: ='SOFP '!K33/'SOFP '!J33-1 -> 0.25990139 | L60: ='SOFP '!L33/'SOFP '!K33-1 -> 0.091261872 | M60: ='SOFP '!M33/'SOFP '!L33-1 -> 0.060592096 | N60: ='SOFP '!N33/'SOFP '!M33-1 -> -0.031098713 | O60: ='SOFP '!O33/'SOFP '!N33-1 -> 0.18791314 | P60: ='SOFP '!P33/'SOFP '!O33-1 -> 0.12268825 | Q60: ='SOFP '!Q33/'SOFP '!P33-1 -> 0.11058514 | ... S60: ='SOFP '!S33/'SOFP '!R33-1 -> 0.10542722
B61: TOTAL ASSETS | I61: - | J61: ='SOFP '!J34/'SOFP '!I34-1 -> 0.26090436 | K61: ='SOFP '!K34/'SOFP '!J34-1 -> 0.12836911 | L61: ='SOFP '!L34/'SOFP '!K34-1 -> 0.12241102 | M61: ='SOFP '!M34/'SOFP '!L34-1 -> 0.15993837 | N61: ='SOFP '!N34/'SOFP '!M34-1 -> 0.014947155 | O61: ='SOFP '!O34/'SOFP '!N34-1 -> 0.13707383 | P61: ='SOFP '!P34/'SOFP '!O34-1 -> 0.094571108 | Q61: ='SOFP '!Q34/'SOFP '!P34-1 -> 0.087653278 | ... S61: ='SOFP '!S34/'SOFP '!R34-1 -> 0.089534904
B63: EQUITY AND LIABILITIES
B64: Equity
B65: Equity Share capital | I65: - | J65: ='SOFP '!J38/'SOFP '!I38-1 -> 0 | K65: ='SOFP '!K38/'SOFP '!J38-1 -> 0 | L65: ='SOFP '!L38/'SOFP '!K38-1 -> 0 | M65: ='SOFP '!M38/'SOFP '!L38-1 -> 0 | N65: ='SOFP '!N38/'SOFP '!M38-1 -> 0 | O65: ='SOFP '!O38/'SOFP '!N38-1 -> 0 | P65: ='SOFP '!P38/'SOFP '!O38-1 -> 0 | Q65: ='SOFP '!Q38/'SOFP '!P38-1 -> 0 | ... S65: ='SOFP '!S38/'SOFP '!R38-1 -> 0
B66: Other Equity | I66: - | J66: ='SOFP '!J39/'SOFP '!I39-1 -> 0.26669982 | K66: ='SOFP '!K39/'SOFP '!J39-1 -> 0.079090538 | L66: ='SOFP '!L39/'SOFP '!K39-1 -> 0.15899149 | M66: ='SOFP '!M39/'SOFP '!L39-1 -> 0.17211982 | N66: ='SOFP '!N39/'SOFP '!M39-1 -> 0.036039948 | O66: ='SOFP '!O39/'SOFP '!N39-1 -> 0.10214418 | P66: ='SOFP '!P39/'SOFP '!O39-1 -> 0.084205042 | Q66: ='SOFP '!Q39/'SOFP '!P39-1 -> 0.084645448 | ... S66: ='SOFP '!S39/'SOFP '!R39-1 -> 0.085108745
B67: NCI | I67: - | J67: ='SOFP '!J40/'SOFP '!I40-1 -> 0.047902263 | K67: ='SOFP '!K40/'SOFP '!J40-1 -> -0.083550111 | L67: ='SOFP '!L40/'SOFP '!K40-1 -> 0.17064485 | M67: ='SOFP '!M40/'SOFP '!L40-1 -> 0.53282194 | N67: ='SOFP '!N40/'SOFP '!M40-1 -> -0.051971584 | O67: ='SOFP '!O40/'SOFP '!N40-1 -> -0.024042837 | P67: ='SOFP '!P40/'SOFP '!O40-1 -> 0.095825205 | Q67: ='SOFP '!Q40/'SOFP '!P40-1 -> 0.095304938 | ... S67: ='SOFP '!S40/'SOFP '!R40-1 -> 0.094047467
B68: Total Equity | I68: - | J68: ='SOFP '!J41/'SOFP '!I41-1 -> 0.25588944 | K68: ='SOFP '!K41/'SOFP '!J41-1 -> 0.073318392 | L68: ='SOFP '!L41/'SOFP '!K41-1 -> 0.15823549 | M68: ='SOFP '!M41/'SOFP '!L41-1 -> 0.18106591 | N68: ='SOFP '!N41/'SOFP '!M41-1 -> 0.032711103 | O68: ='SOFP '!O41/'SOFP '!N41-1 -> 0.097508606 | P68: ='SOFP '!P41/'SOFP '!O41-1 -> 0.084177758 | Q68: ='SOFP '!Q41/'SOFP '!P41-1 -> 0.084620151 | ... S68: ='SOFP '!S41/'SOFP '!R41-1 -> 0.08508713
B70: Liabilities
B71: Non-Current Liabilities
B72: Financial Liabilities
B73: Lease Liabilities | I73: - | J73: ='SOFP '!J46/'SOFP '!I46-1 -> -0.048445605 | K73: ='SOFP '!K46/'SOFP '!J46-1 -> 0.065929172 | L73: ='SOFP '!L46/'SOFP '!K46-1 -> 0.21820947 | M73: ='SOFP '!M46/'SOFP '!L46-1 -> 0.50257909 | N73: ='SOFP '!N46/'SOFP '!M46-1 -> 0.025573136 | O73: ='SOFP '!O46/'SOFP '!N46-1 -> 0.1634826 | P73: ='SOFP '!P46/'SOFP '!O46-1 -> 0.19084603 | Q73: ='SOFP '!Q46/'SOFP '!P46-1 -> 0.19084603 | ... S73: ='SOFP '!S46/'SOFP '!R46-1 -> 0.19084603
B74: Borrowings | I74: - | J74: ='SOFP '!J47/'SOFP '!I47-1 -> -0.22007515 | K74: ='SOFP '!K47/'SOFP '!J47-1 -> 2.065382 | L74: ='SOFP '!L47/'SOFP '!K47-1 -> 0.70969915 | M74: ='SOFP '!M47/'SOFP '!L47-1 -> -0.28588313 | N74: ='SOFP '!N47/'SOFP '!M47-1 -> 3.7741817 | O74: ='SOFP '!O47/'SOFP '!N47-1 -> 3.8038287 | P74: ='SOFP '!P47/'SOFP '!O47-1 -> 0.073003641 | Q74: ='SOFP '!Q47/'SOFP '!P47-1 -> 0.084294925 | ... S74: ='SOFP '!S47/'SOFP '!R47-1 -> 0.084809061
B75: Other Financial Liabilities | I75: - | J75: ='SOFP '!J48/'SOFP '!I48-1 -> 0.14965986 | K75: ='SOFP '!K48/'SOFP '!J48-1 -> -0.35502959 | L75: ='SOFP '!L48/'SOFP '!K48-1 -> 20.275229 | M75: ='SOFP '!M48/'SOFP '!L48-1 -> 4.1871496 | N75: ='SOFP '!N48/'SOFP '!M48-1 -> -0.66776124 | O75: ='SOFP '!O48/'SOFP '!N48-1 -> 0.42199424 | P75: ='SOFP '!P48/'SOFP '!O48-1 -> 0.0027757999 | Q75: ='SOFP '!Q48/'SOFP '!P48-1 -> 0.0027757999 | ... S75: ='SOFP '!S48/'SOFP '!R48-1 -> 0.0027757999
B76: Deferred Tax Liabilities (Net) | I76: - | J76: ='SOFP '!J49/'SOFP '!I49-1 -> -0.063564669 | K76: ='SOFP '!K49/'SOFP '!J49-1 -> -0.16059097 | L76: ='SOFP '!L49/'SOFP '!K49-1 -> -0.040160527 | M76: ='SOFP '!M49/'SOFP '!L49-1 -> 0.051756063 | N76: ='SOFP '!N49/'SOFP '!M49-1 -> 0.14975722 | O76: ='SOFP '!O49/'SOFP '!N49-1 -> -0.0040749796 | P76: ='SOFP '!P49/'SOFP '!O49-1 -> 0.023840541 | Q76: ='SOFP '!Q49/'SOFP '!P49-1 -> 0.023840541 | ... S76: ='SOFP '!S49/'SOFP '!R49-1 -> 0.023840541
B77: Other Non-Current Liabilities | I77: - | J77: ='SOFP '!J50/'SOFP '!I50-1 -> 0.18533902 | K77: ='SOFP '!K50/'SOFP '!J50-1 -> 0.0030944255 | L77: ='SOFP '!L50/'SOFP '!K50-1 -> 0.22428889 | M77: ='SOFP '!M50/'SOFP '!L50-1 -> -0.047578464 | N77: ='SOFP '!N50/'SOFP '!M50-1 -> 0.18013461 | O77: ='SOFP '!O50/'SOFP '!N50-1 -> 0.026769525 | P77: ='SOFP '!P50/'SOFP '!O50-1 -> 0.0087526424 | Q77: ='SOFP '!Q50/'SOFP '!P50-1 -> 0.0087526424 | ... S77: ='SOFP '!S50/'SOFP '!R50-1 -> 0.0087526424
B78: Total Non-Current Liabilities | I78: - | J78: ='SOFP '!J51/'SOFP '!I51-1 -> -0.021028452 | K78: ='SOFP '!K51/'SOFP '!J51-1 -> -0.00019759429 | L78: ='SOFP '!L51/'SOFP '!K51-1 -> 0.19912383 | M78: ='SOFP '!M51/'SOFP '!L51-1 -> 0.37307888 | N78: ='SOFP '!N51/'SOFP '!M51-1 -> 0.085843607 | O78: ='SOFP '!O51/'SOFP '!N51-1 -> 0.55796397 | P78: ='SOFP '!P51/'SOFP '!O51-1 -> 0.10439905 | Q78: ='SOFP '!Q51/'SOFP '!P51-1 -> 0.11316507 | ... S78: ='SOFP '!S51/'SOFP '!R51-1 -> 0.12222954
B80: Current Liabilities
B81: Financial Liabilities
B82: Trade Payables | I82: - | J82: ='SOFP '!J55/'SOFP '!I55-1 -> 0.58137576 | K82: ='SOFP '!K55/'SOFP '!J55-1 -> 0.23250817 | L82: ='SOFP '!L55/'SOFP '!K55-1 -> -0.12699854 | M82: ='SOFP '!M55/'SOFP '!L55-1 -> 0.053886187 | N82: ='SOFP '!N55/'SOFP '!M55-1 -> 0.0043483481 | O82: ='SOFP '!O55/'SOFP '!N55-1 -> 0.0039085239 | P82: ='SOFP '!P55/'SOFP '!O55-1 -> 0.15333864 | Q82: ='SOFP '!Q55/'SOFP '!P55-1 -> 0.091413824 | ... S82: ='SOFP '!S55/'SOFP '!R55-1 -> 0.091483139
B83: Borrowings | I83: - | J83: ='SOFP '!J56/'SOFP '!I56-1 -> 0.013126789 | K83: ='SOFP '!K56/'SOFP '!J56-1 -> 1.2447651 | L83: ='SOFP '!L56/'SOFP '!K56-1 -> 0.22559908 | M83: ='SOFP '!M56/'SOFP '!L56-1 -> 0.17487668 | N83: ='SOFP '!N56/'SOFP '!M56-1 -> -0.42611801 | O83: ='SOFP '!O56/'SOFP '!N56-1 -> 0.73147842 | P83: ='SOFP '!P56/'SOFP '!O56-1 -> 0.073003641 | Q83: ='SOFP '!Q56/'SOFP '!P56-1 -> 0.084294925 | ... S83: ='SOFP '!S56/'SOFP '!R56-1 -> 0.084809061
B84: Lease Liabilities | I84: - | J84: ='SOFP '!J57/'SOFP '!I57-1 -> 0.053545753 | K84: ='SOFP '!K57/'SOFP '!J57-1 -> 0.16197183 | L84: ='SOFP '!L57/'SOFP '!K57-1 -> 0.087479446 | M84: ='SOFP '!M57/'SOFP '!L57-1 -> 0.17488227 | N84: ='SOFP '!N57/'SOFP '!M57-1 -> 0.11505792 | O84: ='SOFP '!O57/'SOFP '!N57-1 -> 0.084058831 | P84: ='SOFP '!P57/'SOFP '!O57-1 -> 0.39536792 | Q84: ='SOFP '!Q57/'SOFP '!P57-1 -> 0.19084603 | ... S84: ='SOFP '!S57/'SOFP '!R57-1 -> 0.19084603
B85: Other Financial Liabilities | I85: - | J85: ='SOFP '!J58/'SOFP '!I58-1 -> 0.1663926 | K85: ='SOFP '!K58/'SOFP '!J58-1 -> 0.17690983 | L85: ='SOFP '!L58/'SOFP '!K58-1 -> 0.29121546 | M85: ='SOFP '!M58/'SOFP '!L58-1 -> 0.098283265 | N85: ='SOFP '!N58/'SOFP '!M58-1 -> 0.024893102 | O85: ='SOFP '!O58/'SOFP '!N58-1 -> 0.11038497 | P85: ='SOFP '!P58/'SOFP '!O58-1 -> 0.073828375 | Q85: ='SOFP '!Q58/'SOFP '!P58-1 -> 0.073828375 | ... S85: ='SOFP '!S58/'SOFP '!R58-1 -> 0.073828375
B86: Other Current Liabilities | I86: - | J86: ='SOFP '!J59/'SOFP '!I59-1 -> 0.61802442 | K86: ='SOFP '!K59/'SOFP '!J59-1 -> 0.41966816 | L86: ='SOFP '!L59/'SOFP '!K59-1 -> 0.19619103 | M86: ='SOFP '!M59/'SOFP '!L59-1 -> 0.025710267 | N86: ='SOFP '!N59/'SOFP '!M59-1 -> -0.053440837 | O86: ='SOFP '!O59/'SOFP '!N59-1 -> 0.30268673 | P86: ='SOFP '!P59/'SOFP '!O59-1 -> 0.01531857 | Q86: ='SOFP '!Q59/'SOFP '!P59-1 -> 0.01531857 | ... S86: ='SOFP '!S59/'SOFP '!R59-1 -> 0.01531857
B87: Income Tax Liabilities (Net) | I87: - | J87: ='SOFP '!J60/'SOFP '!I60-1 -> -0.32668703 | K87: ='SOFP '!K60/'SOFP '!J60-1 -> 0.073331684 | L87: ='SOFP '!L60/'SOFP '!K60-1 -> 0.25799262 | M87: ='SOFP '!M60/'SOFP '!L60-1 -> -0.2515731 | N87: ='SOFP '!N60/'SOFP '!M60-1 -> 0.029222104 | O87: ='SOFP '!O60/'SOFP '!N60-1 -> 0.42763106 | P87: ='SOFP '!P60/'SOFP '!O60-1 -> 0.14360736 | Q87: ='SOFP '!Q60/'SOFP '!P60-1 -> 0.14360736 | ... S87: ='SOFP '!S60/'SOFP '!R60-1 -> 0.14360736
B88: Total Current-Liabilities | I88: - | J88: ='SOFP '!J61/'SOFP '!I61-1 -> 0.35281871 | K88: ='SOFP '!K61/'SOFP '!J61-1 -> 0.27758503 | L88: ='SOFP '!L61/'SOFP '!K61-1 -> 0.042946641 | M88: ='SOFP '!M61/'SOFP '!L61-1 -> 0.076625553 | N88: ='SOFP '!N61/'SOFP '!M61-1 -> -0.042312868 | O88: ='SOFP '!O61/'SOFP '!N61-1 -> 0.12231153 | P88: ='SOFP '!P61/'SOFP '!O61-1 -> 0.11597422 | Q88: ='SOFP '!Q61/'SOFP '!P61-1 -> 0.085407935 | ... S88: ='SOFP '!S61/'SOFP '!R61-1 -> 0.087285589
B89: TOTAL EQUITY AND LIABILITIES | I89: - | J89: ='SOFP '!J62/'SOFP '!I62-1 -> 0.26090436 | K89: ='SOFP '!K62/'SOFP '!J62-1 -> 0.12835929 | L89: ='SOFP '!L62/'SOFP '!K62-1 -> 0.12242079 | M89: ='SOFP '!M62/'SOFP '!L62-1 -> 0.15993837 | N89: ='SOFP '!N62/'SOFP '!M62-1 -> 0.014948157 | O89: ='SOFP '!O62/'SOFP '!N62-1 -> 0.13707271 | P89: ='SOFP '!P62/'SOFP '!O62-1 -> 0.094570943 | Q89: ='SOFP '!Q62/'SOFP '!P62-1 -> 0.087653591 | ... S89: ='SOFP '!S62/'SOFP '!R62-1 -> 0.089534909

Sheet DashboardData
A1: Year | B1: Revenue | C1: Gross Profit | D1: EBITDA | E1: PAT | F1: ROCE % | G1: ROE% | H1: ROA% | I1: Gross Profit Margin | J1: EBITDA Margin | K1: PAT Margin | M1: Year | N1: 22 | P1: Year | Q1: 22
A2: 20 | B2: =SOPL!I13 -> 20211.25 | C2: =SOPL!I18 -> 8827.79 | D2: =SOPL!I22 -> 4466.08 | E2: =SOPL!I31 -> 2774.19 | F2: ='Ratio Analysis'!I37 -> 0.35477083 | G2: ='Ratio Analysis'!I38 -> 0.26704119 | H2: ='Ratio Analysis'!I39 -> 0.17172575 | I2: ='Ratio Analysis'!I32 -> 0.43677605 | J2: ='Ratio Analysis'!I33 -> 0.22097 | K2: ='Ratio Analysis'!I36 -> 0.13725969
A3: =A2+1 -> 21 | B3: =SOPL!J13 -> 21712.79 | C3: =SOPL!J18 -> 9615.56 | D3: =SOPL!J22 -> 5158.65 | E3: =SOPL!J31 -> 3206.75 | F3: ='Ratio Analysis'!J37 -> 0.33385969 | G3: ='Ratio Analysis'!J38 -> 0.24513657 | H3: ='Ratio Analysis'!J39 -> 0.15742807 | I3: ='Ratio Analysis'!J32 -> 0.44285235 | J3: ='Ratio Analysis'!J33 -> 0.23758577 | K3: ='Ratio Analysis'!J36 -> 0.14768945 | M3: Values | P3: Values
A4: =A3+1 -> 22 | B4: =SOPL!K13 -> 29101.28 | C4: =SOPL!K18 -> 10800.53 | D4: =SOPL!K22 -> 5183.62 | E4: =SOPL!K31 -> 3084.81 | F4: ='Ratio Analysis'!K37 -> 0.31064346 | G4: ='Ratio Analysis'!K38 -> 0.21942272 | H4: ='Ratio Analysis'!K39 -> 0.13421291 | I4: ='Ratio Analysis'!K32 -> 0.37113591 | J4: ='Ratio Analysis'!K33 -> 0.17812344 | K4: ='Ratio Analysis'!K36 -> 0.10600255 | M4: Revenue | N4: 29101.28 | P4: PAT Margin | Q4: 0.10600255
A5: =A4+1 -> 23 | B5: =SOPL!L13 -> 34488.59 | C5: =SOPL!L18 -> 13332.09 | D5: =SOPL!L22 -> 6646.32 | E5: =SOPL!L31 -> 4195.33 | F5: ='Ratio Analysis'!L37 -> 0.35427656 | G5: ='Ratio Analysis'!L38 -> 0.25677782 | H5: ='Ratio Analysis'!L39 -> 0.1626223 | I5: ='Ratio Analysis'!L32 -> 0.38656524 | J5: ='Ratio Analysis'!L33 -> 0.19271069 | K5: ='Ratio Analysis'!L36 -> 0.121644 | M5: Gross Profit | N5: 10800.53 | P5: ROA % | Q5: 0.13421291
A6: =A5+1 -> 24 | B6: =SOPL!M13 -> 35494.73 | C6: =SOPL!M18 -> 15404.52 | D6: =SOPL!M22 -> 8272.94 | E6: =SOPL!M31 -> 5557.69 | F6: ='Ratio Analysis'!M37 -> 0.38924107 | G6: ='Ratio Analysis'!M38 -> 0.29154969 | H6: ='Ratio Analysis'!M39 -> 0.18572628 | I6: ='Ratio Analysis'!M32 -> 0.43399457 | J6: ='Ratio Analysis'!M33 -> 0.23307516 | K6: ='Ratio Analysis'!M36 -> 0.15657789 | M6: EBITDA | N6: 5183.62 | P6: EBITDA Margin | Q6: 0.17812344
A7: =A6+1 -> 25 | B7: =SOPL!N13 -> 33905.62 | C7: =SOPL!N18 -> 14389.84 | D7: =SOPL!N22 -> 6578.82 | E7: =SOPL!N31 -> 3709.71 | F7: ='Ratio Analysis'!N37 -> 0.28293568 | G7: ='Ratio Analysis'!N38 -> 0.18903433 | H7: ='Ratio Analysis'!N39 -> 0.12214497 | I7: ='Ratio Analysis'!N32 -> 0.4244087 | J7: ='Ratio Analysis'!N33 -> 0.19403332 | K7: ='Ratio Analysis'!N36 -> 0.10941283 | M7: Profit After Tax | N7: 3084.81 | P7: ROE % | Q7: 0.21942272
A8: =A7+1 -> 26 | B8: =SOPL!O13 -> 35583.54 | C8: =SOPL!O18 -> 15581.76 | D8: =SOPL!O22 -> 7419.72 | E8: =SOPL!O31 -> 4394.69 | F8: ='Ratio Analysis'!O37 -> 0.28510699 | G8: ='Ratio Analysis'!O38 -> 0.20238784 | H8: ='Ratio Analysis'!O39 -> 0.1272551 | I8: ='Ratio Analysis'!O32 -> 0.43789235 | J8: ='Ratio Analysis'!O33 -> 0.20851551 | K8: ='Ratio Analysis'!O36 -> 0.12350345 | P8: ROCE % | Q8: 0.31064346
A9: =A8+1 -> 27 | B9: =SOPL!P13 -> 38834.811 | C9: =SOPL!P18 -> 16235.978 | D9: =SOPL!P22 -> 7894.25 | E9: =SOPL!P31 -> 4779.502 | F9: ='Ratio Analysis'!S37 -> 0.27857809 | G9: ='Ratio Analysis'!S38 -> 0.20308545 | H9: ='Ratio Analysis'!S39 -> 0.12644033 | I9: ='Ratio Analysis'!S32 -> 0.41807795 | J9: ='Ratio Analysis'!S33 -> 0.20327767 | K9: ='Ratio Analysis'!S36 -> 0.12307262 | P9: Gross Profit % | Q9: 0.37113591
A10: =A9+1 -> 28 | B10: =SOPL!Q13 -> 42384.85 | C10: =SOPL!Q18 -> 17720.171 | D10: =SOPL!Q22 -> 8542.4418 | E10: =SOPL!Q31 -> 5209.0626 | F10: 0.2798 | G10: ='Ratio Analysis'!T38 -> 0.2041307 | H10: ='Ratio Analysis'!T39 -> 0.12669868 | I10: ='Ratio Analysis'!T32 -> 0.41807795 | J10: ='Ratio Analysis'!T33 -> 0.2015447 | K10: ='Ratio Analysis'!T36 -> 0.12289916
A11: =A10+1 -> 29 | B11: =SOPL!R13 -> 46260.995 | C11: =SOPL!R18 -> 19340.702 | D11: =SOPL!R22 -> 9241.9236 | E11: =SOPL!R31 -> 5669.5146 | F11: 0.2805 | G11: ='Ratio Analysis'!U38 -> 0.20484226 | H11: ='Ratio Analysis'!U39 -> 0.1266724 | I11: ='Ratio Analysis'!U32 -> 0.41807795 | J11: ='Ratio Analysis'!U33 -> 0.19977788 | K11: ='Ratio Analysis'!U36 -> 0.12255496
A12: =A11+1 -> 30 | B12: =SOPL!S13 -> 50493.096 | C12: =SOPL!S18 -> 21110.05 | D12: =SOPL!S22 -> 9996.4905 | E12: =SOPL!S31 -> 6163.4359 | F12: 0.2809 | G12: ='Ratio Analysis'!V38 -> 0.2052784 | H12: ='Ratio Analysis'!V39 -> 0.1263915 | I12: ='Ratio Analysis'!V32 -> 0.41807795 | J12: ='Ratio Analysis'!V33 -> 0.19797737 | K12: ='Ratio Analysis'!V36 -> 0.12206492
A15: PV of FCFF (FY27E-FY30E) | B15: ='Valuation-FCFF'!O19 -> 9749.1524 | C15: =B15/B17 -> 0.22850501
A16: Terminal Value | B16: ='Valuation-FCFF'!O20 -> 32915.787 | C16: =B16/B17 -> 0.77149499
A17: Value of Firm | B17: ='Valuation-FCFF'!O21 -> 42664.939
A18: Equity Value | B18: ='Valuation-FCFF'!O23 -> 40110.829
A19: Intrinsic Value (₹/share) | B19: ='Valuation-FCFF'!L28 -> 418.42412
A20: WACC | B20: ='Valuation-FCFF'!N16 -> 0.11921803
A23: Capital Mix | B23: Weightage | C23: Cost
A24: Debt | B24: 0.12 | C24: 0.0471
A25: Equity | B25: 0.88 | C25: 0.129
